Workbook
Name UPDATE: 'Data Sheet'!$E$1

Sheet Profit & Loss
A1: ='Data Sheet'!B1 -> HINDUSTAN UNILEVER LTD | H1: =UPDATE | M1: SCREENER.IN
A3: Narration | B3: ='Data Sheet'!B16 -> 42825 | C3: ='Data Sheet'!C16 -> 43190 | D3: ='Data Sheet'!D16 -> 43555 | E3: ='Data Sheet'!E16 -> 43921 | F3: ='Data Sheet'!F16 -> 44286 | G3: ='Data Sheet'!G16 -> 44651 | H3: ='Data Sheet'!H16 -> 45016 | I3: ='Data Sheet'!I16 -> 45382 | ... K3: ='Data Sheet'!K16 -> 46112 | L3: Trailing | M3: Best Case | N3: Worst Case
A4: Sales | B4: ='Data Sheet'!B17 -> 33162 | C4: ='Data Sheet'!C17 -> 35545 | D4: ='Data Sheet'!D17 -> 39310 | E4: ='Data Sheet'!E17 -> 39783 | F4: ='Data Sheet'!F17 -> 47028 | G4: ='Data Sheet'!G17 -> 52446 | H4: ='Data Sheet'!H17 -> 60580 | I4: ='Data Sheet'!I17 -> 61896 | ... K4: ='Data Sheet'!K17 -> 64468 | L4: =SUM(Quarters!H4:K4) -> 65225 | M4: =$K4+M23*K4 -> 67768.768 | N4: =$K4+N23*L4 -> 65834.541
A5: Expenses | B5: =SUM('Data Sheet'!B18,'Data Sheet'!B20:B24, -1*'Data Sheet'!B19) -> 26834 | C5: =SUM('Data Sheet'!C18,'Data Sheet'!C20:C24, -1*'Data Sheet'!C19) -> 28046 | D5: =SUM('Data Sheet'!D18,'Data Sheet'!D20:D24, -1*'Data Sheet'!D19) -> 30430 | E5: =SUM('Data Sheet'!E18,'Data Sheet'!E20:E24, -1*'Data Sheet'!E19) -> 29922 | F5: =SUM('Data Sheet'!F18,'Data Sheet'!F20:F24, -1*'Data Sheet'!F19) -> 35402 | G5: =SUM('Data Sheet'!G18,'Data Sheet'!G20:G24, -1*'Data Sheet'!G19) -> 39589 | H5: =SUM('Data Sheet'!H18,'Data Sheet'!H20:H24, -1*'Data Sheet'!H19) -> 46433 | I5: =SUM('Data Sheet'!I18,'Data Sheet'!I20:I24, -1*'Data Sheet'!I19) -> 47237 | ... K5: =SUM('Data Sheet'!K18,'Data Sheet'!K20:K24, -1*'Data Sheet'!K19) -> 49429 | L5: =SUM(Quarters!H5:K5) -> 50108 | M5: =M4-M6 -> 51738.984 | N5: =N4-N6 -> 50576.269
A6: Operating Profit | B6: =B4-B5 -> 6328 | C6: =C4-C5 -> 7499 | D6: =D4-D5 -> 8880 | E6: =E4-E5 -> 9861 | F6: =F4-F5 -> 11626 | G6: =G4-G5 -> 12857 | H6: =H4-H5 -> 14147 | I6: =I4-I5 -> 14659 | ... K6: =K4-K5 -> 15039 | L6: =SUM(Quarters!H6:K6) -> 15117 | M6: =M4*M24 -> 16029.784 | N6: =N4*N24 -> 15258.271
A7: Other Income | B7: ='Data Sheet'!B25 -> 606 | C7: ='Data Sheet'!C25 -> 353 | D7: ='Data Sheet'!D25 -> 322 | E7: ='Data Sheet'!E25 -> 424 | F7: ='Data Sheet'!F25 -> 170 | G7: ='Data Sheet'!G25 -> 219 | H7: ='Data Sheet'!H25 -> 448 | I7: ='Data Sheet'!I25 -> 817 | ... K7: ='Data Sheet'!K25 -> 4923 | L7: =SUM(Quarters!H7:K7) -> 4894 | M7: 0 | N7: 0
A8: Depreciation | B8: ='Data Sheet'!B26 -> 432 | C8: ='Data Sheet'!C26 -> 520 | D8: ='Data Sheet'!D26 -> 565 | E8: ='Data Sheet'!E26 -> 1002 | F8: ='Data Sheet'!F26 -> 1074 | G8: ='Data Sheet'!G26 -> 1091 | H8: ='Data Sheet'!H26 -> 1137 | I8: ='Data Sheet'!I26 -> 1216 | ... K8: ='Data Sheet'!K26 -> 1333 | L8: =SUM(Quarters!H8:K8) -> 1368 | M8: =+$L8 -> 1368 | N8: =+$L8 -> 1368
A9: Interest | B9: ='Data Sheet'!B27 -> 35 | C9: ='Data Sheet'!C27 -> 26 | D9: ='Data Sheet'!D27 -> 33 | E9: ='Data Sheet'!E27 -> 118 | F9: ='Data Sheet'!F27 -> 117 | G9: ='Data Sheet'!G27 -> 106 | H9: ='Data Sheet'!H27 -> 114 | I9: ='Data Sheet'!I27 -> 334 | ... K9: ='Data Sheet'!K27 -> 410 | L9: =SUM(Quarters!H9:K9) -> 415 | M9: =+$L9 -> 415 | N9: =+$L9 -> 415
A10: Profit before tax | B10: ='Data Sheet'!B28 -> 6467 | C10: ='Data Sheet'!C28 -> 7306 | D10: ='Data Sheet'!D28 -> 8604 | E10: ='Data Sheet'!E28 -> 9165 | F10: ='Data Sheet'!F28 -> 10605 | G10: ='Data Sheet'!G28 -> 11879 | H10: ='Data Sheet'!H28 -> 13344 | I10: ='Data Sheet'!I28 -> 13926 | ... K10: ='Data Sheet'!K28 -> 18219 | L10: =SUM(Quarters!H10:K10) -> 18228 | M10: =M6+M7-SUM(M8:M9) -> 14246.784 | N10: =N6+N7-SUM(N8:N9) -> 13475.271
A11: Tax | B11: ='Data Sheet'!B29 -> 1977 | C11: ='Data Sheet'!C29 -> 2079 | D11: ='Data Sheet'!D29 -> 2544 | E11: ='Data Sheet'!E29 -> 2409 | F11: ='Data Sheet'!F29 -> 2606 | G11: ='Data Sheet'!G29 -> 2987 | H11: ='Data Sheet'!H29 -> 3201 | I11: ='Data Sheet'!I29 -> 3644 | ... K11: ='Data Sheet'!K29 -> 3160 | L11: =SUM(Quarters!H11:K11) -> 3169 | M11: =IF($L10>0,$L11/$L10,0) -> 0.17385341 | N11: =IF($L10>0,$L11/$L10,0) -> 0.17385341
A12: Net profit | B12: ='Data Sheet'!B30 -> 4476 | C12: ='Data Sheet'!C30 -> 5214 | D12: ='Data Sheet'!D30 -> 6054 | E12: ='Data Sheet'!E30 -> 6748 | F12: ='Data Sheet'!F30 -> 7995 | G12: ='Data Sheet'!G30 -> 8879 | H12: ='Data Sheet'!H30 -> 10120 | I12: ='Data Sheet'!I30 -> 10277 | ... K12: ='Data Sheet'!K30 -> 15040 | L12: =SUM(Quarters!H12:K12) -> 15040 | M12: =M10-M11*M10 -> 11769.932 | N12: =N10-N11*N10 -> 11132.55
A13: EPS | B13: =IF('Data Sheet'!B93>0,B12/'Data Sheet'!B93,0) -> 20.681052 | C13: =IF('Data Sheet'!C93>0,C12/'Data Sheet'!C93,0) -> 24.088704 | D13: =IF('Data Sheet'!D93>0,D12/'Data Sheet'!D93,0) -> 27.966924 | E13: =IF('Data Sheet'!E93>0,E12/'Data Sheet'!E93,0) -> 31.171471 | F13: =IF('Data Sheet'!F93>0,F12/'Data Sheet'!F93,0) -> 34.027068 | G13: =IF('Data Sheet'!G93>0,G12/'Data Sheet'!G93,0) -> 37.789411 | H13: =IF('Data Sheet'!H93>0,H12/'Data Sheet'!H93,0) -> 43.071161 | I13: =IF('Data Sheet'!I93>0,I12/'Data Sheet'!I93,0) -> 43.73936 | ... K13: =IF('Data Sheet'!K93>0,K12/'Data Sheet'!K93,0) -> 64.010895 | L13: =IF('Data Sheet'!$B6>0,'Profit & Loss'!L12/'Data Sheet'!$B6,0) -> 64.01113 | M13: =IF('Data Sheet'!$B6>0,'Profit & Loss'!M12/'Data Sheet'!$B6,0) -> 50.093527 | N13: =IF('Data Sheet'!$B6>0,'Profit & Loss'!N12/'Data Sheet'!$B6,0) -> 47.380789
A14: Price to earning | B14: =IF(B15>0,B15/B13,"") -> 42.193696 | C14: =IF(C15>0,C15/C13,"") -> 52.975453 | D14: =IF(D15>0,D15/D13,"") -> 58.409356 | E14: =IF(E15>0,E15/E13,"") -> 70.571903 | F14: =IF(F15>0,F15/F13,"") -> 68.390258 | G14: =IF(G15>0,G15/G13,"") -> 51.884905 | H14: =IF(H15>0,H15/H13,"") -> 56.892824 | I14: =IF(I15>0,I15/I13,"") -> 49.546678 | ... K14: =IF(K15>0,K15/K13,"") -> 32.107034 | L14: =IF(L13>0,L15/L13,0) -> 33.619154 | M14: =M25 -> 40.74317 | N14: =N25 -> 33.619154
A15: Price | B15: ='Data Sheet'!B90 -> 872.61 | C15: ='Data Sheet'!C90 -> 1276.11 | D15: ='Data Sheet'!D90 -> 1633.53 | E15: ='Data Sheet'!E90 -> 2199.83 | F15: ='Data Sheet'!F90 -> 2327.12 | G15: ='Data Sheet'!G90 -> 1960.7 | H15: ='Data Sheet'!H90 -> 2450.44 | I15: ='Data Sheet'!I90 -> 2167.14 | ... K15: ='Data Sheet'!K90 -> 2055.2 | L15: ='Data Sheet'!B8 -> 2152 | M15: =M13*M14 -> 2040.9691 | N15: =N13*N14 -> 1592.902
A17: RATIOS:
A18: Dividend Payout | B18: =IF('Data Sheet'!B30>0, 'Data Sheet'!B31/'Data Sheet'!B30, 0) -> 0.82037534 | C18: =IF('Data Sheet'!C30>0, 'Data Sheet'!C31/'Data Sheet'!C30, 0) -> 0.82853855 | D18: =IF('Data Sheet'!D30>0, 'Data Sheet'!D31/'Data Sheet'!D30, 0) -> 0.78493558 | E18: =IF('Data Sheet'!E30>0, 'Data Sheet'!E31/'Data Sheet'!E30, 0) -> 0.80023711 | F18: =IF('Data Sheet'!F30>0, 'Data Sheet'!F31/'Data Sheet'!F30, 0) -> 1.1904315 | G18: =IF('Data Sheet'!G30>0, 'Data Sheet'!G31/'Data Sheet'!G30, 0) -> 0.89987611 | H18: =IF('Data Sheet'!H30>0, 'Data Sheet'!H31/'Data Sheet'!H30, 0) -> 0.90563241 | I18: =IF('Data Sheet'!I30>0, 'Data Sheet'!I31/'Data Sheet'!I30, 0) -> 0.960397 | ... K18: =IF('Data Sheet'!K30>0, 'Data Sheet'!K31/'Data Sheet'!K30, 0) -> 0.640625
A19: OPM | B19: =IF(B6>0,B6/B4,0) -> 0.19082082 | C19: =IF(C6>0,C6/C4,0) -> 0.21097201 | D19: =IF(D6>0,D6/D4,0) -> 0.22589672 | E19: =IF(E6>0,E6/E4,0) -> 0.24786969 | F19: =IF(F6>0,F6/F4,0) -> 0.24721443 | G19: =IF(G6>0,G6/G4,0) -> 0.24514739 | H19: =IF(H6>0,H6/H4,0) -> 0.23352592 | I19: =IF(I6>0,I6/I4,0) -> 0.23683275 | ... L19: =IF(L6>0,L6/L4,0) -> 0.23176696
G22: TRENDS: | H22: 10 YEARS | I22: 7 YEARS | J22: 5 YEARS | K22: 3 YEARS | L22: RECENT | M22: BEST | N22: WORST
G23: Sales Growth | H23: =IF(B4=0,"",POWER($K4/B4,1/9)-1) -> 0.076658974 | I23: =IF(D4=0,"",POWER($K4/D4,1/7)-1) -> 0.073227008 | J23: =IF(F4=0,"",POWER($K4/F4,1/5)-1) -> 0.065117542 | K23: =IF(H4=0,"",POWER($K4/H4, 1/3)-1) -> 0.020951182 | L23: =IF(ISERROR(MAX(IF(J4=0,"",(K4-J4)/J4),IF(K4=0,"",(L4-K4)/K4))),"",MAX(IF(J4=0,"",(K4-J4)/J4),IF(K4=0,"",(L4-K4)/K4))) -> 0.051200104 | M23: =MAX(K23:L23) -> 0.051200104 | N23: =MIN(H23:L23) -> 0.020951182
G24: OPM | H24: =IF(SUM(B4:$K$4)=0,"",SUMPRODUCT(B19:$K$19,B4:$K$4)/SUM(B4:$K$4)) -> 0.23326593 | I24: =IF(SUM(E4:$K$4)=0,"",SUMPRODUCT(E19:$K$19,E4:$K$4)/SUM(E4:$K$4)) -> 0.23969045 | J24: =IF(SUM(G4:$K$4)=0,"",SUMPRODUCT(G19:$K$19,G4:$K$4)/SUM(G4:$K$4)) -> 0.23743175 | K24: =IF(SUM(I4:$K$4)=0, "", SUMPRODUCT(I19:$K$19,I4:$K$4)/SUM(I4:$K$4)) -> 0.23653645 | L24: =L19 -> 0.23176696 | M24: =MAX(K24:L24) -> 0.23653645 | N24: =MIN(H24:L24) -> 0.23176696
G25: Price to Earning | H25: =IF(ISERROR(AVERAGEIF(B14:$L14,">0")),"",AVERAGEIF(B14:$L14,">0")) -> 51.299189 | I25: =IF(ISERROR(AVERAGEIF(E14:$L14,">0")),"",AVERAGEIF(E14:$L14,">0")) -> 51.339071 | J25: =IF(ISERROR(AVERAGEIF(G14:$L14,">0")),"",AVERAGEIF(G14:$L14,">0")) -> 45.291735 | K25: =IF(ISERROR(AVERAGEIF(I14:$L14,">0")),"",AVERAGEIF(I14:$L14,">0")) -> 40.74317 | L25: =L14 -> 33.619154 | M25: =MAX(K25:L25) -> 40.74317 | N25: =MIN(H25:L25) -> 33.619154

Sheet Quarters
A1: ='Profit & Loss'!A1 -> HINDUSTAN UNILEVER LTD | E1: =UPDATE | J1: SCREENER.IN
A3: Narration | B3: ='Data Sheet'!B41 -> 45291 | C3: ='Data Sheet'!C41 -> 45382 | D3: ='Data Sheet'!D41 -> 45473 | E3: ='Data Sheet'!E41 -> 45565 | F3: ='Data Sheet'!F41 -> 45657 | G3: ='Data Sheet'!G41 -> 45747 | H3: ='Data Sheet'!H41 -> 45838 | I3: ='Data Sheet'!I41 -> 45930 | ... K3: ='Data Sheet'!K41 -> 46112
A4: Sales | B4: ='Data Sheet'!B42 -> 15567 | C4: ='Data Sheet'!C42 -> 15210 | D4: ='Data Sheet'!D42 -> 15707 | E4: ='Data Sheet'!E42 -> 15926 | F4: ='Data Sheet'!F42 -> 15556 | G4: ='Data Sheet'!G42 -> 15190 | H4: ='Data Sheet'!H42 -> 16514 | I4: ='Data Sheet'!I42 -> 15919 | ... K4: ='Data Sheet'!K42 -> 16351
A5: Expenses | B5: ='Data Sheet'!B43 -> 11902 | C5: ='Data Sheet'!C43 -> 11675 | D5: ='Data Sheet'!D43 -> 11965 | E5: ='Data Sheet'!E43 -> 12139 | F5: ='Data Sheet'!F43 -> 11867 | G5: ='Data Sheet'!G43 -> 11572 | H5: ='Data Sheet'!H43 -> 12797 | I5: ='Data Sheet'!I43 -> 12137 | ... K5: ='Data Sheet'!K43 -> 12514
A6: Operating Profit | B6: ='Data Sheet'!B50 -> 3665 | C6: ='Data Sheet'!C50 -> 3535 | D6: ='Data Sheet'!D50 -> 3742 | E6: ='Data Sheet'!E50 -> 3787 | F6: ='Data Sheet'!F50 -> 3689 | G6: ='Data Sheet'!G50 -> 3618 | H6: ='Data Sheet'!H50 -> 3717 | I6: ='Data Sheet'!I50 -> 3782 | ... K6: ='Data Sheet'!K50 -> 3837
A7: Other Income | B7: ='Data Sheet'!B44 -> 184 | C7: ='Data Sheet'!C44 -> 309 | D7: ='Data Sheet'!D44 -> 209 | E7: ='Data Sheet'!E44 -> 203 | F7: ='Data Sheet'!F44 -> 733 | G7: ='Data Sheet'!G44 -> 149 | H7: ='Data Sheet'!H44 -> 74 | I7: ='Data Sheet'!I44 -> 269 | ... K7: ='Data Sheet'!K44 -> 503
A8: Depreciation | B8: ='Data Sheet'!B45 -> 313 | C8: ='Data Sheet'!C45 -> 320 | D8: ='Data Sheet'!D45 -> 329 | E8: ='Data Sheet'!E45 -> 338 | F8: ='Data Sheet'!F45 -> 318 | G8: ='Data Sheet'!G45 -> 318 | H8: ='Data Sheet'!H45 -> 361 | I8: ='Data Sheet'!I45 -> 322 | ... K8: ='Data Sheet'!K45 -> 348
A9: Interest | B9: ='Data Sheet'!B46 -> 91 | C9: ='Data Sheet'!C46 -> 105 | D9: ='Data Sheet'!D46 -> 93 | E9: ='Data Sheet'!E46 -> 110 | F9: ='Data Sheet'!F46 -> 109 | G9: ='Data Sheet'!G46 -> 77 | H9: ='Data Sheet'!H46 -> 127 | I9: ='Data Sheet'!I46 -> 124 | ... K9: ='Data Sheet'!K46 -> 76
A10: Profit before tax | B10: ='Data Sheet'!B47 -> 3445 | C10: ='Data Sheet'!C47 -> 3419 | D10: ='Data Sheet'!D47 -> 3529 | E10: ='Data Sheet'!E47 -> 3542 | F10: ='Data Sheet'!F47 -> 3995 | G10: ='Data Sheet'!G47 -> 3372 | H10: ='Data Sheet'!H47 -> 3303 | I10: ='Data Sheet'!I47 -> 3605 | ... K10: ='Data Sheet'!K47 -> 3916
A11: Tax | B11: ='Data Sheet'!B48 -> 937 | C11: ='Data Sheet'!C48 -> 858 | D11: ='Data Sheet'!D48 -> 917 | E11: ='Data Sheet'!E48 -> 947 | F11: ='Data Sheet'!F48 -> 1006 | G11: ='Data Sheet'!G48 -> 897 | H11: ='Data Sheet'!H48 -> 535 | I11: ='Data Sheet'!I48 -> 911 | ... K11: ='Data Sheet'!K48 -> 922
A12: Net profit | B12: ='Data Sheet'!B49 -> 2509 | C12: ='Data Sheet'!C49 -> 2558 | D12: ='Data Sheet'!D49 -> 2610 | E12: ='Data Sheet'!E49 -> 2591 | F12: ='Data Sheet'!F49 -> 2984 | G12: ='Data Sheet'!G49 -> 2464 | H12: ='Data Sheet'!H49 -> 2756 | I12: ='Data Sheet'!I49 -> 2685 | ... K12: ='Data Sheet'!K49 -> 2992
A14: OPM | B14: =IF(B4>0,B6/B4,"") -> 0.23543393 | C14: =IF(C4>0,C6/C4,"") -> 0.23241289 | D14: =IF(D4>0,D6/D4,"") -> 0.23823773 | E14: =IF(E4>0,E6/E4,"") -> 0.23778727 | F14: =IF(F4>0,F6/F4,"") -> 0.23714322 | G14: =IF(G4>0,G6/G4,"") -> 0.23818302 | H14: =IF(H4>0,H6/H4,"") -> 0.22508175 | I14: =IF(I4>0,I6/I4,"") -> 0.23757774 | ... K14: =IF(K4>0,K6/K4,"") -> 0.23466455

Sheet Balance Sheet
A1: ='Profit & Loss'!A1 -> HINDUSTAN UNILEVER LTD | E1: =UPDATE | J1: SCREENER.IN
A3: Narration | B3: ='Data Sheet'!B56 -> 42825 | C3: ='Data Sheet'!C56 -> 43190 | D3: ='Data Sheet'!D56 -> 43555 | E3: ='Data Sheet'!E56 -> 43921 | F3: ='Data Sheet'!F56 -> 44286 | G3: ='Data Sheet'!G56 -> 44651 | H3: ='Data Sheet'!H56 -> 45016 | I3: ='Data Sheet'!I56 -> 45382 | ... K3: ='Data Sheet'!K56 -> 46112
A4: Equity Share Capital | B4: ='Data Sheet'!B57 -> 216 | C4: ='Data Sheet'!C57 -> 216 | D4: ='Data Sheet'!D57 -> 216 | E4: ='Data Sheet'!E57 -> 216 | F4: ='Data Sheet'!F57 -> 235 | G4: ='Data Sheet'!G57 -> 235 | H4: ='Data Sheet'!H57 -> 235 | I4: ='Data Sheet'!I57 -> 235 | ... K4: ='Data Sheet'!K57 -> 235
A5: Reserves | B5: ='Data Sheet'!B58 -> 6528 | C5: ='Data Sheet'!C58 -> 7065 | D5: ='Data Sheet'!D58 -> 7651 | E5: ='Data Sheet'!E58 -> 8013 | F5: ='Data Sheet'!F58 -> 47439 | G5: ='Data Sheet'!G58 -> 48826 | H5: ='Data Sheet'!H58 -> 50069 | I5: ='Data Sheet'!I58 -> 50983 | ... K5: ='Data Sheet'!K58 -> 48504
A6: Borrowings | B6: ='Data Sheet'!B59 -> 277 | C6: ='Data Sheet'!C59 -> 0 | D6: ='Data Sheet'!D59 -> 99 | E6: ='Data Sheet'!E59 -> 0 | F6: ='Data Sheet'!F59 -> 0 | G6: ='Data Sheet'!G59 -> 1043 | H6: ='Data Sheet'!H59 -> 1219 | I6: ='Data Sheet'!I59 -> 1484 | ... K6: ='Data Sheet'!K59 -> 1478
A7: Other Liabilities | B7: ='Data Sheet'!B60 -> 8685 | C7: ='Data Sheet'!C60 -> 10581 | D7: ='Data Sheet'!D60 -> 10663 | E7: ='Data Sheet'!E60 -> 11924 | F7: ='Data Sheet'!F60 -> 21066 | G7: ='Data Sheet'!G60 -> 20402 | H7: ='Data Sheet'!H60 -> 21554 | I7: ='Data Sheet'!I60 -> 25787 | ... K7: ='Data Sheet'!K60 -> 29521
A8: Total | B8: ='Data Sheet'!B61 -> 15706 | C8: ='Data Sheet'!C61 -> 17862 | D8: ='Data Sheet'!D61 -> 18629 | E8: ='Data Sheet'!E61 -> 20153 | F8: ='Data Sheet'!F61 -> 68740 | G8: ='Data Sheet'!G61 -> 70506 | H8: ='Data Sheet'!H61 -> 73077 | I8: ='Data Sheet'!I61 -> 78489 | ... K8: ='Data Sheet'!K61 -> 79738
A10: Net Block | B10: ='Data Sheet'!B62 -> 4419 | C10: ='Data Sheet'!C62 -> 4528 | D10: ='Data Sheet'!D62 -> 4715 | E10: ='Data Sheet'!E62 -> 5479 | F10: ='Data Sheet'!F62 -> 51443 | G10: ='Data Sheet'!G62 -> 51473 | H10: ='Data Sheet'!H62 -> 52678 | I10: ='Data Sheet'!I62 -> 53744 | ... K10: ='Data Sheet'!K62 -> 57428
A11: Capital Work in Progress | B11: ='Data Sheet'!B63 -> 229 | C11: ='Data Sheet'!C63 -> 461 | D11: ='Data Sheet'!D63 -> 406 | E11: ='Data Sheet'!E63 -> 597 | F11: ='Data Sheet'!F63 -> 745 | G11: ='Data Sheet'!G63 -> 1313 | H11: ='Data Sheet'!H63 -> 1132 | I11: ='Data Sheet'!I63 -> 1025 | ... K11: ='Data Sheet'!K63 -> 880
A12: Investments | B12: ='Data Sheet'!B64 -> 3794 | C12: ='Data Sheet'!C64 -> 2873 | D12: ='Data Sheet'!D64 -> 2716 | E12: ='Data Sheet'!E64 -> 1255 | F12: ='Data Sheet'!F64 -> 2709 | G12: ='Data Sheet'!G64 -> 3521 | H12: ='Data Sheet'!H64 -> 2882 | I12: ='Data Sheet'!I64 -> 4625 | ... K12: ='Data Sheet'!K64 -> 4359
A13: Other Assets | B13: ='Data Sheet'!B65 -> 7264 | C13: ='Data Sheet'!C65 -> 10000 | D13: ='Data Sheet'!D65 -> 10792 | E13: ='Data Sheet'!E65 -> 12822 | F13: ='Data Sheet'!F65 -> 13843 | G13: ='Data Sheet'!G65 -> 14199 | H13: ='Data Sheet'!H65 -> 16385 | I13: ='Data Sheet'!I65 -> 19095 | ... K13: ='Data Sheet'!K65 -> 17071
A14: Total | B14: ='Data Sheet'!B66 -> 15706 | C14: ='Data Sheet'!C66 -> 17862 | D14: ='Data Sheet'!D66 -> 18629 | E14: ='Data Sheet'!E66 -> 20153 | F14: ='Data Sheet'!F66 -> 68740 | G14: ='Data Sheet'!G66 -> 70506 | H14: ='Data Sheet'!H66 -> 73077 | I14: ='Data Sheet'!I66 -> 78489 | ... K14: ='Data Sheet'!K66 -> 79738
A16: Working Capital | B16: =B13-B7 -> -1421 | C16: =C13-C7 -> -581 | D16: =D13-D7 -> 129 | E16: =E13-E7 -> 898 | F16: =F13-F7 -> -7223 | G16: =G13-G7 -> -6203 | H16: =H13-H7 -> -5169 | I16: =I13-I7 -> -6692 | ... K16: =K13-K7 -> -12450
A17: Debtors | B17: ='Data Sheet'!B67 -> 1085 | C17: ='Data Sheet'!C67 -> 1310 | D17: ='Data Sheet'!D67 -> 1816 | E17: ='Data Sheet'!E67 -> 1149 | F17: ='Data Sheet'!F67 -> 1758 | G17: ='Data Sheet'!G67 -> 2236 | H17: ='Data Sheet'!H67 -> 3079 | I17: ='Data Sheet'!I67 -> 2997 | ... K17: ='Data Sheet'!K67 -> 3379
A18: Inventory | B18: ='Data Sheet'!B68 -> 2541 | C18: ='Data Sheet'!C68 -> 2513 | D18: ='Data Sheet'!D68 -> 2574 | E18: ='Data Sheet'!E68 -> 2767 | F18: ='Data Sheet'!F68 -> 3579 | G18: ='Data Sheet'!G68 -> 4096 | H18: ='Data Sheet'!H68 -> 4251 | I18: ='Data Sheet'!I68 -> 4022 | ... K18: ='Data Sheet'!K68 -> 4789
A20: Debtor Days | B20: =IF('Profit & Loss'!B4>0,'Balance Sheet'!B17/('Profit & Loss'!B4/365),0) -> 11.942133 | C20: =IF('Profit & Loss'!C4>0,'Balance Sheet'!C17/('Profit & Loss'!C4/365),0) -> 13.451962 | D20: =IF('Profit & Loss'!D4>0,'Balance Sheet'!D17/('Profit & Loss'!D4/365),0) -> 16.861867 | E20: =IF('Profit & Loss'!E4>0,'Balance Sheet'!E17/('Profit & Loss'!E4/365),0) -> 10.541814 | F20: =IF('Profit & Loss'!F4>0,'Balance Sheet'!F17/('Profit & Loss'!F4/365),0) -> 13.644425 | G20: =IF('Profit & Loss'!G4>0,'Balance Sheet'!G17/('Profit & Loss'!G4/365),0) -> 15.56153 | H20: =IF('Profit & Loss'!H4>0,'Balance Sheet'!H17/('Profit & Loss'!H4/365),0) -> 18.551255 | I20: =IF('Profit & Loss'!I4>0,'Balance Sheet'!I17/('Profit & Loss'!I4/365),0) -> 17.673275 | ... K20: =IF('Profit & Loss'!K4>0,'Balance Sheet'!K17/('Profit & Loss'!K4/365),0) -> 19.130964
A21: Inventory Turnover | B21: =IF('Balance Sheet'!B18>0,'Profit & Loss'!B4/'Balance Sheet'!B18,0) -> 13.050767 | C21: =IF('Balance Sheet'!C18>0,'Profit & Loss'!C4/'Balance Sheet'!C18,0) -> 14.144449 | D21: =IF('Balance Sheet'!D18>0,'Profit & Loss'!D4/'Balance Sheet'!D18,0) -> 15.27195 | E21: =IF('Balance Sheet'!E18>0,'Profit & Loss'!E4/'Balance Sheet'!E18,0) -> 14.377665 | F21: =IF('Balance Sheet'!F18>0,'Profit & Loss'!F4/'Balance Sheet'!F18,0) -> 13.139983 | G21: =IF('Balance Sheet'!G18>0,'Profit & Loss'!G4/'Balance Sheet'!G18,0) -> 12.804199 | H21: =IF('Balance Sheet'!H18>0,'Profit & Loss'!H4/'Balance Sheet'!H18,0) -> 14.250765 | I21: =IF('Balance Sheet'!I18>0,'Profit & Loss'!I4/'Balance Sheet'!I18,0) -> 15.389359 | ... K21: =IF('Balance Sheet'!K18>0,'Profit & Loss'!K4/'Balance Sheet'!K18,0) -> 13.461683
A23: Return on Equity | B23: =IF(SUM('Balance Sheet'!B4:B5)>0,'Profit & Loss'!B12/SUM('Balance Sheet'!B4:B5),"") -> 0.66370107 | C23: =IF(SUM('Balance Sheet'!C4:C5)>0,'Profit & Loss'!C12/SUM('Balance Sheet'!C4:C5),"") -> 0.71611042 | D23: =IF(SUM('Balance Sheet'!D4:D5)>0,'Profit & Loss'!D12/SUM('Balance Sheet'!D4:D5),"") -> 0.76954366 | E23: =IF(SUM('Balance Sheet'!E4:E5)>0,'Profit & Loss'!E12/SUM('Balance Sheet'!E4:E5),"") -> 0.82002673 | F23: =IF(SUM('Balance Sheet'!F4:F5)>0,'Profit & Loss'!F12/SUM('Balance Sheet'!F4:F5),"") -> 0.16770147 | G23: =IF(SUM('Balance Sheet'!G4:G5)>0,'Profit & Loss'!G12/SUM('Balance Sheet'!G4:G5),"") -> 0.18097878 | H23: =IF(SUM('Balance Sheet'!H4:H5)>0,'Profit & Loss'!H12/SUM('Balance Sheet'!H4:H5),"") -> 0.20117684 | I23: =IF(SUM('Balance Sheet'!I4:I5)>0,'Profit & Loss'!I12/SUM('Balance Sheet'!I4:I5),"") -> 0.20065211 | ... K23: =IF(SUM('Balance Sheet'!K4:K5)>0,'Profit & Loss'!K12/SUM('Balance Sheet'!K4:K5),"") -> 0.30858245
A24: Return on Capital Emp | C24: =IF((B4+B5+B6+C4+C5+C6)>0,('Profit & Loss'!C10+'Profit & Loss'!C9)*2/(B4+B5+B6+C4+C5+C6),"") -> 1.0253111 | D24: =IF((C4+C5+C6+D4+D5+D6)>0,('Profit & Loss'!D10+'Profit & Loss'!D9)*2/(C4+C5+C6+D4+D5+D6),"") -> 1.1329442 | E24: =IF((D4+D5+D6+E4+E5+E6)>0,('Profit & Loss'!E10+'Profit & Loss'!E9)*2/(D4+D5+D6+E4+E5+E6),"") -> 1.1464032 | F24: =IF((E4+E5+E6+F4+F5+F6)>0,('Profit & Loss'!F10+'Profit & Loss'!F9)*2/(E4+E5+E6+F4+F5+F6),"") -> 0.38359301 | G24: =IF((F4+F5+F6+G4+G5+G6)>0,('Profit & Loss'!G10+'Profit & Loss'!G9)*2/(F4+F5+F6+G4+G5+G6),"") -> 0.24514717 | H24: =IF((G4+G5+G6+H4+H5+H6)>0,('Profit & Loss'!H10+'Profit & Loss'!H9)*2/(G4+G5+G6+H4+H5+H6),"") -> 0.26485088 | I24: =IF((H4+H5+H6+I4+I5+I6)>0,('Profit & Loss'!I10+'Profit & Loss'!I9)*2/(H4+H5+H6+I4+I5+I6),"") -> 0.27363876 | J24: =IF((I4+I5+I6+J4+J5+J6)>0,('Profit & Loss'!J10+'Profit & Loss'!J9)*2/(I4+I5+I6+J4+J5+J6),"") -> 0.28529571 | K24: =IF((J4+J5+J6+K4+K5+K6)>0,('Profit & Loss'!K10+'Profit & Loss'!K9)*2/(J4+J5+J6+K4+K5+K6),"") -> 0.36791847

Sheet Cash Flow
A1: ='Balance Sheet'!A1 -> HINDUSTAN UNILEVER LTD | E1: =UPDATE | J1: SCREENER.IN
A3: Narration | B3: ='Data Sheet'!B81 -> 42825 | C3: ='Data Sheet'!C81 -> 43190 | D3: ='Data Sheet'!D81 -> 43555 | E3: ='Data Sheet'!E81 -> 43921 | F3: ='Data Sheet'!F81 -> 44286 | G3: ='Data Sheet'!G81 -> 44651 | H3: ='Data Sheet'!H81 -> 45016 | I3: ='Data Sheet'!I81 -> 45382 | ... K3: ='Data Sheet'!K81 -> 46112
A4: Cash from Operating Activity | B4: ='Data Sheet'!B82 -> 5185 | C4: ='Data Sheet'!C82 -> 6059 | D4: ='Data Sheet'!D82 -> 5800 | E4: ='Data Sheet'!E82 -> 7623 | F4: ='Data Sheet'!F82 -> 9163 | G4: ='Data Sheet'!G82 -> 9048 | H4: ='Data Sheet'!H82 -> 9991 | I4: ='Data Sheet'!I82 -> 15469 | ... K4: ='Data Sheet'!K82 -> 10999
A5: Cash from Investing Activity | B5: ='Data Sheet'!B83 -> -1173 | C5: ='Data Sheet'!C83 -> -1063 | D5: ='Data Sheet'!D83 -> -438 | E5: ='Data Sheet'!E83 -> 1791 | F5: ='Data Sheet'!F83 -> -1228 | G5: ='Data Sheet'!G83 -> -1728 | H5: ='Data Sheet'!H83 -> -1484 | I5: ='Data Sheet'!I83 -> -5324 | ... K5: ='Data Sheet'!K83 -> -3676
A6: Cash from Financing Activity | B6: ='Data Sheet'!B84 -> -4214 | C6: ='Data Sheet'!C84 -> -4975 | D6: ='Data Sheet'!D84 -> -5390 | E6: ='Data Sheet'!E84 -> -6819 | F6: ='Data Sheet'!F84 -> -9309 | G6: ='Data Sheet'!G84 -> -8015 | H6: ='Data Sheet'!H84 -> -8953 | I6: ='Data Sheet'!I84 -> -10034 | ... K6: ='Data Sheet'!K84 -> -10810
A7: Net Cash Flow | B7: ='Data Sheet'!B85 -> -202 | C7: ='Data Sheet'!C85 -> 21 | D7: ='Data Sheet'!D85 -> -28 | E7: ='Data Sheet'!E85 -> 2595 | F7: ='Data Sheet'!F85 -> -1374 | G7: ='Data Sheet'!G85 -> -695 | H7: ='Data Sheet'!H85 -> -446 | I7: ='Data Sheet'!I85 -> 111 | ... K7: ='Data Sheet'!K85 -> -3487

Sheet Customization
A1: How to use it?
A3: You can customize this workbook as you want.
B4: You can add custom formating, add conditional formating, add your own formulas… do ANYTHING.
B5: Please don't edit the "Data Sheet" only.
A7: After customization, you can upload this back on Screener.
B8: Upload on: | C8: https://www.screener.in/excel/
A10: Download your customized workbooks now onwards.
B11: Now whenever you will "Export to excel" from Screener, it will export your customized file.
A14: TESTING:
B15: This is a testing feature currently.
B16: You can report any formula errors on the worksheet at: support@screener.in

Sheet Data Sheet
A1: COMPANY NAME | B1: HINDUSTAN UNILEVER LTD | E1: =IF(B2<>B3, "A NEW VERSION OF THE WORKSHEET IS AVAILABLE", "")
A2: LATEST VERSION | B2: 2.1 | E2: PLEASE DO NOT MAKE ANY CHANGES TO THIS SHEET
A3: CURRENT VERSION | B3: 2.1
A5: META
A6: Number of shares | B6: =IF(B9>0, B9/B8, 0) -> 234.95914
A7: Face Value | B7: 1
A8: Current Price | B8: 2152
A9: Market Capitalization | B9: 505632.07
A15: PROFIT & LOSS
A16: Report Date | B16: 42825 | C16: 43190 | D16: 43555 | E16: 43921 | F16: 44286 | G16: 44651 | H16: 45016 | I16: 45382 | J16: 45747 | K16: 46112
A17: Sales | B17: 33162 | C17: 35545 | D17: 39310 | E17: 39783 | F17: 47028 | G17: 52446 | H17: 60580 | I17: 61896 | J17: 61328 | K17: 64468
A18: Raw Material Cost | B18: 13606 | C18: 14233 | D18: 15845 | E18: 15697 | F18: 20141 | G18: 22871 | H18: 28427 | I18: 26822 | J18: 26602 | K18: 29158
A19: Change in Inventory | B19: -144 | C19: 72 | D19: -12 | E19: 108 | F19: 405 | G19: 22 | H19: 75 | I19: 11 | J19: 125 | K19: 429
A20: Power and Fuel | B20: 295 | C20: 295 | D20: 308 | E20: 299 | F20: 339 | G20: 318 | H20: 384 | I20: 446 | J20: 403 | K20: 426
A21: Other Mfr. Exp | B21: 2887 | C21: 2998 | D21: 3041 | E21: 2906 | F21: 2868 | G21: 3354 | H21: 3791 | I21: 3385 | J21: 3687 | K21: 3304
A22: Employee Cost | B22: 1743 | C22: 1860 | D22: 1875 | E22: 1820 | F22: 2358 | G22: 2545 | H22: 2854 | I22: 3009 | J22: 2952 | K22: 3175
A23: Selling and admin | B23: 6689 | C23: 7252 | D23: 7796 | E23: 7620 | F23: 7906 | G23: 8164 | H23: 8785 | I23: 10780 | J23: 10145 | K23: 10744
A24: Other Expenses | B24: 1470 | C24: 1480 | D24: 1553 | E24: 1688 | F24: 2195 | G24: 2359 | H24: 2267 | I24: 2806 | J24: 2966 | K24: 3051
A25: Other Income | B25: 606 | C25: 353 | D25: 322 | E25: 424 | F25: 170 | G25: 219 | H25: 448 | I25: 817 | J25: 1355 | K25: 4923
A26: Depreciation | B26: 432 | C26: 520 | D26: 565 | E26: 1002 | F26: 1074 | G26: 1091 | H26: 1137 | I26: 1216 | J26: 1253 | K26: 1333
A27: Interest | B27: 35 | C27: 26 | D27: 33 | E27: 118 | F27: 117 | G27: 106 | H27: 114 | I27: 334 | J27: 381 | K27: 410
... A31: Dividend Amount | B31: 3672 | C31: 4320 | D31: 4752 | E31: 5400 | F31: 9517.5 | G31: 7990 | H31: 9165 | I31: 9870 | J31: 12455 | K31: 9635
A32: EBITDA | B32: =SUM(B26:B28) -> 6934 | C32: =SUM(C26:C28) -> 7852 | D32: =SUM(D26:D28) -> 9202 | E32: =SUM(E26:E28) -> 10285 | F32: =SUM(F26:F28) -> 11796 | G32: =SUM(G26:G28) -> 13076 | H32: =SUM(H26:H28) -> 14595 | I32: =SUM(I26:I28) -> 15476 | ... K32: =SUM(K26:K28) -> 19962
A33: EBIT | B33: =SUM(B27:B28) -> 6502 | C33: =SUM(C27:C28) -> 7332 | D33: =SUM(D27:D28) -> 8637 | E33: =SUM(E27:E28) -> 9283 | F33: =SUM(F27:F28) -> 10722 | G33: =SUM(G27:G28) -> 11985 | H33: =SUM(H27:H28) -> 13458 | I33: =SUM(I27:I28) -> 14260 | ... K33: =SUM(K27:K28) -> 18629
A40: Quarters
A41: Report Date | B41: 45291 | C41: 45382 | D41: 45473 | E41: 45565 | F41: 45657 | G41: 45747 | H41: 45838 | I41: 45930 | J41: 46022 | K41: 46112
A42: Sales | B42: 15567 | C42: 15210 | D42: 15707 | E42: 15926 | F42: 15556 | G42: 15190 | H42: 16514 | I42: 15919 | J42: 16441 | K42: 16351
A43: Expenses | B43: 11902 | C43: 11675 | D43: 11965 | E43: 12139 | F43: 11867 | G43: 11572 | H43: 12797 | I43: 12137 | J43: 12660 | K43: 12514
A44: Other Income | B44: 184 | C44: 309 | D44: 209 | E44: 203 | F44: 733 | G44: 149 | H44: 74 | I44: 269 | J44: 4048 | K44: 503
A45: Depreciation | B45: 313 | C45: 320 | D45: 329 | E45: 338 | F45: 318 | G45: 318 | H45: 361 | I45: 322 | J45: 337 | K45: 348
A46: Interest | B46: 91 | C46: 105 | D46: 93 | E46: 110 | F46: 109 | G46: 77 | H46: 127 | I46: 124 | J46: 88 | K46: 76
A47: Profit before tax | B47: 3445 | C47: 3419 | D47: 3529 | E47: 3542 | F47: 3995 | G47: 3372 | H47: 3303 | I47: 3605 | J47: 7404 | K47: 3916
A48: Tax | B48: 937 | C48: 858 | D48: 917 | E48: 947 | F48: 1006 | G48: 897 | H48: 535 | I48: 911 | J48: 801 | K48: 922
A49: Net profit | B49: 2509 | C49: 2558 | D49: 2610 | E49: 2591 | F49: 2984 | G49: 2464 | H49: 2756 | I49: 2685 | J49: 6607 | K49: 2992
A50: Operating Profit | B50: 3665 | C50: 3535 | D50: 3742 | E50: 3787 | F50: 3689 | G50: 3618 | H50: 3717 | I50: 3782 | J50: 3781 | K50: 3837
A55: BALANCE SHEET
A56: Report Date | B56: 42825 | C56: 43190 | D56: 43555 | E56: 43921 | F56: 44286 | G56: 44651 | H56: 45016 | I56: 45382 | J56: 45747 | K56: 46112
A57: Equity Share Capital | B57: 216 | C57: 216 | D57: 216 | E57: 216 | F57: 235 | G57: 235 | H57: 235 | I57: 235 | J57: 235 | K57: 235
A58: Reserves | B58: 6528 | C58: 7065 | D58: 7651 | E58: 8013 | F58: 47439 | G58: 48826 | H58: 50069 | I58: 50983 | J58: 49167 | K58: 48504
A59: Borrowings | B59: 277 | D59: 99 | G59: 1043 | H59: 1219 | I59: 1484 | J59: 1648 | K59: 1478
A60: Other Liabilities | B60: 8685 | C60: 10581 | D60: 10663 | E60: 11924 | F60: 21066 | G60: 20402 | H60: 21554 | I60: 25787 | J60: 28813 | K60: 29521
A61: Total | B61: 15706 | C61: 17862 | D61: 18629 | E61: 20153 | F61: 68740 | G61: 70506 | H61: 73077 | I61: 78489 | J61: 79863 | K61: 79738
A62: Net Block | B62: 4419 | C62: 4528 | D62: 4715 | E62: 5479 | F62: 51443 | G62: 51473 | H62: 52678 | I62: 53744 | J62: 54335 | K62: 57428
A63: Capital Work in Progress | B63: 229 | C63: 461 | D63: 406 | E63: 597 | F63: 745 | G63: 1313 | H63: 1132 | I63: 1025 | J63: 1009 | K63: 880
A64: Investments | B64: 3794 | C64: 2873 | D64: 2716 | E64: 1255 | F64: 2709 | G64: 3521 | H64: 2882 | I64: 4625 | J64: 3810 | K64: 4359
A65: Other Assets | B65: 7264 | C65: 10000 | D65: 10792 | E65: 12822 | F65: 13843 | G65: 14199 | H65: 16385 | I65: 19095 | J65: 20709 | K65: 17071
A66: Total | B66: 15706 | C66: 17862 | D66: 18629 | E66: 20153 | F66: 68740 | G66: 70506 | H66: 73077 | I66: 78489 | J66: 79863 | K66: 79738
A67: Receivables | B67: 1085 | C67: 1310 | D67: 1816 | E67: 1149 | F67: 1758 | G67: 2236 | H67: 3079 | I67: 2997 | J67: 3819 | K67: 3379
A68: Inventory | B68: 2541 | C68: 2513 | D68: 2574 | E68: 2767 | F68: 3579 | G68: 4096 | H68: 4251 | I68: 4022 | J68: 4415 | K68: 4789
A69: Cash & Bank | B69: 1828 | C69: 3485 | D69: 3757 | E69: 5113 | F69: 4471 | G69: 3846 | H69: 4678 | I69: 7559 | J69: 7554 | K69: 3248
A70: No. of Equity Shares | B70: 2164349639 | C70: 2164528777 | D70: 2164704405 | E70: 2164704405 | F70: 2349567819 | G70: 2349591262 | H70: 2349591262 | I70: 2349591262 | J70: 2349591262 | K70: 2349591262
A71: New Bonus Shares
A72: Face value | B72: 1 | C72: 1 | D72: 1 | E72: 1 | F72: 1 | G72: 1 | H72: 1 | I72: 1 | J72: 1 | K72: 1
A74: other assets | B74: =B65-SUM(B67:B69) -> 1810 | C74: =C65-SUM(C67:C69) -> 2692 | D74: =D65-SUM(D67:D69) -> 2645 | E74: =E65-SUM(E67:E69) -> 3793 | F74: =F65-SUM(F67:F69) -> 4035 | G74: =G65-SUM(G67:G69) -> 4021 | H74: =H65-SUM(H67:H69) -> 4377 | I74: =I65-SUM(I67:I69) -> 4517 | ... K74: =K65-SUM(K67:K69) -> 5655
A80: CASH FLOW:
A81: Report Date | B81: 42825 | C81: 43190 | D81: 43555 | E81: 43921 | F81: 44286 | G81: 44651 | H81: 45016 | I81: 45382 | J81: 45747 | K81: 46112
A82: Cash from Operating Activity | B82: 5185 | C82: 6059 | D82: 5800 | E82: 7623 | F82: 9163 | G82: 9048 | H82: 9991 | I82: 15469 | J82: 11886 | K82: 10999
A83: Cash from Investing Activity | B83: -1173 | C83: -1063 | D83: -438 | E83: 1791 | F83: -1228 | G83: -1728 | H83: -1484 | I83: -5324 | J83: 6473 | K83: -3676
A84: Cash from Financing Activity | B84: -4214 | C84: -4975 | D84: -5390 | E84: -6819 | F84: -9309 | G84: -8015 | H84: -8953 | I84: -10034 | J84: -13101 | K84: -10810
A85: Net Cash Flow | B85: -202 | C85: 21 | D85: -28 | E85: 2595 | F85: -1374 | G85: -695 | H85: -446 | I85: 111 | J85: 5258 | K85: -3487
A90: PRICE: | B90: 872.61 | C90: 1276.11 | D90: 1633.53 | E90: 2199.83 | F90: 2327.12 | G90: 1960.7 | H90: 2450.44 | I90: 2167.14 | J90: 2161.88 | K90: 2055.2
A92: DERIVED:
A93: Adjusted Equity Shares in Cr | B93: 216.43 | C93: 216.45 | D93: 216.47 | E93: 216.48 | F93: 234.96 | G93: 234.96 | H93: 234.96 | I93: 234.96 | J93: 234.96 | K93: 234.96

Sheet Historical FS
B2: ="Historical Financial Statement for " &'Data Sheet'!B1 -> Historical Financial Statement for HINDUSTAN UNILEVER LTD
B3: Year | C3: ='Data Sheet'!B16 -> 42825 | D3: ='Data Sheet'!C16 -> 43190 | E3: ='Data Sheet'!D16 -> 43555 | F3: ='Data Sheet'!E16 -> 43921 | G3: ='Data Sheet'!F16 -> 44286 | H3: ='Data Sheet'!G16 -> 44651 | I3: ='Data Sheet'!H16 -> 45016 | J3: ='Data Sheet'!I16 -> 45382 | ... L3: ='Data Sheet'!K16 -> 46112 | M3: =L3+365 -> 46477 | N3: =M3+365 -> 46842 | O3: =N3+365 -> 47207 | P3: =O3+365 -> 47572 | Q3: =P3+365 -> 47937
A5: # | B5: Income Statement
B6: ='Data Sheet'!A17 -> Sales | C6: ='Data Sheet'!B17 -> 33162 | D6: ='Data Sheet'!C17 -> 35545 | E6: ='Data Sheet'!D17 -> 39310 | F6: ='Data Sheet'!E17 -> 39783 | G6: ='Data Sheet'!F17 -> 47028 | H6: ='Data Sheet'!G17 -> 52446 | I6: ='Data Sheet'!H17 -> 60580 | ... L6: ='Data Sheet'!K17 -> 64468 | M6: =FORECAST($M$3,C6:L6,$C$3:$L$3) -> 70982.404 | N6: =FORECAST($M$3,D6:M6,$C$3:$L$3) -> 75182.241 | O6: =FORECAST($M$3,E6:N6,$C$3:$L$3) -> 79176.45 | P6: =FORECAST($M$3,F6:O6,$C$3:$L$3) -> 83129.771 | Q6: =FORECAST($M$3,G6:P6,$C$3:$L$3) -> 86132.088
B7: Sales Growth | C7: - | D7: =D6/C6-1 -> 0.071859357 | E7: =E6/D6-1 -> 0.10592207 | F7: =F6/E6-1 -> 0.012032562 | G7: =G6/F6-1 -> 0.18211296 | H7: =H6/G6-1 -> 0.11520796 | I7: =I6/H6-1 -> 0.15509286 | J7: =J6/I6-1 -> 0.021723341 | K7: =K6/J6-1 -> -0.0091766835 | ... Q7: =Q6/P6-1 -> 0.036116025
B9: COGS | C9: =SUM('Data Sheet'!B18:B22) -> 18387 | D9: =SUM('Data Sheet'!C18:C22) -> 19458 | E9: =SUM('Data Sheet'!D18:D22) -> 21057 | F9: =SUM('Data Sheet'!E18:E22) -> 20830 | G9: =SUM('Data Sheet'!F18:F22) -> 26111 | H9: =SUM('Data Sheet'!G18:G22) -> 29110 | I9: =SUM('Data Sheet'!H18:H22) -> 35531 | J9: =SUM('Data Sheet'!I18:I22) -> 33673 | ... L9: =SUM('Data Sheet'!K18:K22) -> 36492 | M9: =FORECAST($M$3,C9:L9,$C$3:$L$3) -> 39882.336 | N9: =FORECAST($M$3,D9:M9,$C$3:$L$3) -> 42444.255 | O9: =FORECAST($M$3,E9:N9,$C$3:$L$3) -> 44883.444 | P9: =FORECAST($M$3,F9:O9,$C$3:$L$3) -> 47192.178 | Q9: =FORECAST($M$3,G9:P9,$C$3:$L$3) -> 48774.908
B11: Gross Profit | C11: =C6-C9 -> 14775 | D11: =D6-D9 -> 16087 | E11: =E6-E9 -> 18253 | F11: =F6-F9 -> 18953 | G11: =G6-G9 -> 20917 | H11: =H6-H9 -> 23336 | I11: =I6-I9 -> 25049 | J11: =J6-J9 -> 28223 | ... L11: =L6-L9 -> 27976 | M11: =FORECAST($M$3,C11:L11,$C$3:$L$3) -> 31100.068 | N11: =FORECAST($M$3,D11:M11,$C$3:$L$3) -> 32737.986 | O11: =FORECAST($M$3,E11:N11,$C$3:$L$3) -> 34293.006 | P11: =FORECAST($M$3,F11:O11,$C$3:$L$3) -> 35937.593 | Q11: =FORECAST($M$3,G11:P11,$C$3:$L$3) -> 37357.18
B12: Gross Profit Margins | C12: =C11/C6 -> 0.44554008 | D12: =D11/D6 -> 0.45258124 | E12: =E11/E6 -> 0.46433477 | F12: =F11/F6 -> 0.47640952 | G12: =G11/G6 -> 0.44477758 | H12: =H11/H6 -> 0.4449529 | I12: =I11/I6 -> 0.4134863 | J12: =J11/J6 -> 0.45597454 | ... Q12: =Q11/Q6 -> 0.43371966
C13: ='Historical FS'!C40/SUM('Historical FS'!D3) -> 0.0064135216
B14: Selling and General Expenses | C14: =SUM('Data Sheet'!B23:B24) -> 8159 | D14: =SUM('Data Sheet'!C23:C24) -> 8732 | E14: =SUM('Data Sheet'!D23:D24) -> 9349 | F14: =SUM('Data Sheet'!E23:E24) -> 9308 | G14: =SUM('Data Sheet'!F23:F24) -> 10101 | H14: =SUM('Data Sheet'!G23:G24) -> 10523 | I14: =SUM('Data Sheet'!H23:H24) -> 11052 | J14: =SUM('Data Sheet'!I23:I24) -> 13586 | ... L14: =SUM('Data Sheet'!K23:K24) -> 13795 | M14: =FORECAST($M$3,C14:L14,$C$3:$L$3) -> 14378.169 | N14: =FORECAST($M$3,D14:M14,$C$3:$L$3) -> 15123.927 | O14: =FORECAST($M$3,E14:N14,$C$3:$L$3) -> 15906.342 | P14: =FORECAST($M$3,F14:O14,$C$3:$L$3) -> 16740.151 | Q14: =FORECAST($M$3,G14:P14,$C$3:$L$3) -> 17459.517
B16: EBITDA | C16: =C11-C14 -> 6616 | D16: =D11-D14 -> 7355 | E16: =E11-E14 -> 8904 | F16: =F11-F14 -> 9645 | G16: =G11-G14 -> 10816 | H16: =H11-H14 -> 12813 | I16: =I11-I14 -> 13997 | J16: =J11-J14 -> 14637 | ... L16: =L11-L14 -> 14181 | M16: =FORECAST($M$3,C16:L16,$C$3:$L$3) -> 16721.899 | N16: =FORECAST($M$3,D16:M16,$C$3:$L$3) -> 17614.059 | O16: =FORECAST($M$3,E16:N16,$C$3:$L$3) -> 18386.663 | P16: =FORECAST($M$3,F16:O16,$C$3:$L$3) -> 19197.442 | Q16: =FORECAST($M$3,G16:P16,$C$3:$L$3) -> 19897.663
B17: EBITDA Margins | C17: =C16/C6 -> 0.19950546 | D17: =D16/D6 -> 0.2069208 | E17: =E16/E6 -> 0.22650725 | F17: =F16/F6 -> 0.24244024 | G17: =G16/G6 -> 0.22999064 | H17: =H16/H6 -> 0.24430843 | I17: =I16/I6 -> 0.23104985 | J17: =J16/J6 -> 0.23647732 | ... Q17: =Q16/Q6 -> 0.23101337
B19: D&A | C19: ='Data Sheet'!B26 -> 432 | D19: ='Data Sheet'!C26 -> 520 | E19: ='Data Sheet'!D26 -> 565 | F19: ='Data Sheet'!E26 -> 1002 | G19: ='Data Sheet'!F26 -> 1074 | H19: ='Data Sheet'!G26 -> 1091 | I19: ='Data Sheet'!H26 -> 1137 | J19: ='Data Sheet'!I26 -> 1216 | ... L19: ='Data Sheet'!K26 -> 1333 | M19: =FORECAST($M$3,C19:L19,$C$3:$L$3) -> 1526.1118 | N19: =FORECAST($M$3,D19:M19,$C$3:$L$3) -> 1610.1984 | O19: =FORECAST($M$3,E19:N19,$C$3:$L$3) -> 1678.4709 | P19: =FORECAST($M$3,F19:O19,$C$3:$L$3) -> 1713.4074 | Q19: =FORECAST($M$3,G19:P19,$C$3:$L$3) -> 1804.5766
B21: EBIT | C21: =C16-C19 -> 6184 | D21: =D16-D19 -> 6835 | E21: =E16-E19 -> 8339 | F21: =F16-F19 -> 8643 | G21: =G16-G19 -> 9742 | H21: =H16-H19 -> 11722 | I21: =I16-I19 -> 12860 | J21: =J16-J19 -> 13421 | ... L21: =L16-L19 -> 12848 | M21: =FORECAST($M$3,C21:L21,$C$3:$L$3) -> 15195.788 | N21: =FORECAST($M$3,D21:M21,$C$3:$L$3) -> 16003.861 | O21: =FORECAST($M$3,E21:N21,$C$3:$L$3) -> 16708.192 | P21: =FORECAST($M$3,F21:O21,$C$3:$L$3) -> 17484.035 | Q21: =FORECAST($M$3,G21:P21,$C$3:$L$3) -> 18093.087
B22: EBIT Margins | C22: =C21/C6 -> 0.1864785 | D22: =D21/D6 -> 0.19229146 | E22: =E21/E6 -> 0.21213432 | F22: =F21/F6 -> 0.2172536 | G22: =G21/G6 -> 0.20715319 | H22: =H21/H6 -> 0.22350608 | I22: =I21/I6 -> 0.21228128 | J22: =J21/J6 -> 0.21683146 | ... Q22: =Q21/Q6 -> 0.2100621
B24: Interest | C24: ='Data Sheet'!B27 -> 35 | D24: ='Data Sheet'!C27 -> 26 | E24: ='Data Sheet'!D27 -> 33 | F24: ='Data Sheet'!E27 -> 118 | G24: ='Data Sheet'!F27 -> 117 | H24: ='Data Sheet'!G27 -> 106 | I24: ='Data Sheet'!H27 -> 114 | J24: ='Data Sheet'!I27 -> 334 | ... L24: ='Data Sheet'!K27 -> 410 | M24: =FORECAST($M$3,C24:L24,$C$3:$L$3) -> 412.10221 | N24: =FORECAST($M$3,D24:M24,$C$3:$L$3) -> 474.65326 | O24: =FORECAST($M$3,E24:N24,$C$3:$L$3) -> 534.69462 | P24: =FORECAST($M$3,F24:O24,$C$3:$L$3) -> 590.72629 | Q24: =FORECAST($M$3,G24:P24,$C$3:$L$3) -> 658.40186
B26: EBT | C26: =C21-C24 -> 6149 | D26: =D21-D24 -> 6809 | E26: =E21-E24 -> 8306 | F26: =F21-F24 -> 8525 | G26: =G21-G24 -> 9625 | H26: =H21-H24 -> 11616 | I26: =I21-I24 -> 12746 | J26: =J21-J24 -> 13087 | ... L26: =L21-L24 -> 12438 | M26: =FORECAST($M$3,C26:L26,$C$3:$L$3) -> 14783.685 | N26: =FORECAST($M$3,D26:M26,$C$3:$L$3) -> 15529.208 | O26: =FORECAST($M$3,E26:N26,$C$3:$L$3) -> 16173.498 | P26: =FORECAST($M$3,F26:O26,$C$3:$L$3) -> 16893.308 | Q26: =FORECAST($M$3,G26:P26,$C$3:$L$3) -> 17434.685
B27: EBT Margins | C27: =C26/C6 -> 0.18542307 | D27: =D26/D6 -> 0.19155999 | E27: =E26/E6 -> 0.21129484 | F27: =F26/F6 -> 0.21428751 | G27: =G26/G6 -> 0.20466531 | H27: =H26/H6 -> 0.22148496 | I27: =I26/I6 -> 0.21039947 | J27: =J26/J6 -> 0.21143531 | ... Q27: =Q26/Q6 -> 0.202418
B29: Tax | C29: ='Data Sheet'!B29 -> 1977 | D29: ='Data Sheet'!C29 -> 2079 | E29: ='Data Sheet'!D29 -> 2544 | F29: ='Data Sheet'!E29 -> 2409 | G29: ='Data Sheet'!F29 -> 2606 | H29: ='Data Sheet'!G29 -> 2987 | I29: ='Data Sheet'!H29 -> 3201 | J29: ='Data Sheet'!I29 -> 3644 | ... L29: ='Data Sheet'!K29 -> 3160 | M29: =FORECAST($M$3,C29:L29,$C$3:$L$3) -> 3854.8744 | N29: =FORECAST($M$3,D29:M29,$C$3:$L$3) -> 4033.6585 | O29: =FORECAST($M$3,E29:N29,$C$3:$L$3) -> 4185.9915 | P29: =FORECAST($M$3,F29:O29,$C$3:$L$3) -> 4393.0207 | Q29: =FORECAST($M$3,G29:P29,$C$3:$L$3) -> 4537.3295
B31: Net Profit | C31: =C26-C29 -> 4172 | D31: =D26-D29 -> 4730 | E31: =E26-E29 -> 5762 | F31: =F26-F29 -> 6116 | G31: =G26-G29 -> 7019 | H31: =H26-H29 -> 8629 | I31: =I26-I29 -> 9545 | J31: =J26-J29 -> 9443 | ... L31: =L26-L29 -> 9278 | M31: =FORECAST($M$3,C31:L31,$C$3:$L$3) -> 10928.811 | N31: =FORECAST($M$3,D31:M31,$C$3:$L$3) -> 11495.549 | O31: =FORECAST($M$3,E31:N31,$C$3:$L$3) -> 11987.506 | P31: =FORECAST($M$3,F31:O31,$C$3:$L$3) -> 12500.288 | Q31: =FORECAST($M$3,G31:P31,$C$3:$L$3) -> 12897.356
B32: Net Profit Margins | C32: =C31/C6 -> 0.12580665 | D32: =D31/D6 -> 0.13307076 | E32: =E31/E6 -> 0.14657848 | F32: =F31/F6 -> 0.15373401 | G32: =G31/G6 -> 0.14925151 | H32: =H31/H6 -> 0.16453114 | I32: =I31/I6 -> 0.15756025 | J32: =J31/J6 -> 0.15256236 | ... Q32: =Q31/Q6 -> 0.14973927
A37: # | B37: Balance Sheet
B38: Equity Share Capital | C38: ='Data Sheet'!B57 -> 216 | D38: ='Data Sheet'!C57 -> 216 | E38: ='Data Sheet'!D57 -> 216 | F38: ='Data Sheet'!E57 -> 216 | G38: ='Data Sheet'!F57 -> 235 | H38: ='Data Sheet'!G57 -> 235 | I38: ='Data Sheet'!H57 -> 235 | J38: ='Data Sheet'!I57 -> 235 | ... L38: ='Data Sheet'!K57 -> 235 | M38: =FORECAST($M$3,C38:L38,$C$3:$L$3) -> 242.59678 | N38: =FORECAST($M$3,D38:M38,$C$3:$L$3) -> 245.63654 | O38: =FORECAST($M$3,E38:N38,$C$3:$L$3) -> 248.11695 | P38: =FORECAST($M$3,F38:O38,$C$3:$L$3) -> 249.6153 | Q38: =FORECAST($M$3,G38:P38,$C$3:$L$3) -> 249.57227
B39: Reserves | C39: ='Data Sheet'!B58 -> 6528 | D39: ='Data Sheet'!C58 -> 7065 | E39: ='Data Sheet'!D58 -> 7651 | F39: ='Data Sheet'!E58 -> 8013 | G39: ='Data Sheet'!F58 -> 47439 | H39: ='Data Sheet'!G58 -> 48826 | I39: ='Data Sheet'!H58 -> 50069 | J39: ='Data Sheet'!I58 -> 50983 | ... L39: ='Data Sheet'!K58 -> 48504 | M39: =FORECAST($M$3,C39:L39,$C$3:$L$3) -> 66307.82 | N39: =FORECAST($M$3,D39:M39,$C$3:$L$3) -> 72957.34 | O39: =FORECAST($M$3,E39:N39,$C$3:$L$3) -> 78420.603 | P39: =FORECAST($M$3,F39:O39,$C$3:$L$3) -> 81835.86 | Q39: =FORECAST($M$3,G39:P39,$C$3:$L$3) -> 81996.185
B40: Borrowings | C40: ='Data Sheet'!B59 -> 277 | D40: ='Data Sheet'!C59 -> 0 | E40: ='Data Sheet'!D59 -> 99 | F40: ='Data Sheet'!E59 -> 0 | G40: ='Data Sheet'!F59 -> 0 | H40: ='Data Sheet'!G59 -> 1043 | I40: ='Data Sheet'!H59 -> 1219 | J40: ='Data Sheet'!I59 -> 1484 | ... L40: ='Data Sheet'!K59 -> 1478 | M40: =FORECAST($M$3,C40:L40,$C$3:$L$3) -> 1856.8915 | N40: =FORECAST($M$3,D40:M40,$C$3:$L$3) -> 2190.2762 | O40: =FORECAST($M$3,E40:N40,$C$3:$L$3) -> 2477.8981 | P40: =FORECAST($M$3,F40:O40,$C$3:$L$3) -> 2760.8825 | Q40: =FORECAST($M$3,G40:P40,$C$3:$L$3) -> 2972.0985
B41: Other Liabilities | C41: ='Data Sheet'!B60-C42 -> 2499 | D41: ='Data Sheet'!C60-D42 -> 3411 | E41: ='Data Sheet'!D60-E42 -> 3457 | F41: ='Data Sheet'!E60-F42 -> 4389 | G41: ='Data Sheet'!F60-G42 -> 12264 | H41: ='Data Sheet'!G60-H42 -> 11334 | I41: ='Data Sheet'!H60-I42 -> 11980 | J41: ='Data Sheet'!I60-J42 -> 15301 | ... L41: ='Data Sheet'!K60-L42 -> 16196 | M41: =FORECAST($M$3,C41:L41,$C$3:$L$3) -> 19929.251 | N41: =FORECAST($M$3,D41:M41,$C$3:$L$3) -> 22012.28 | O41: =FORECAST($M$3,E41:N41,$C$3:$L$3) -> 24008.594 | P41: =FORECAST($M$3,F41:O41,$C$3:$L$3) -> 25576.954 | Q41: =FORECAST($M$3,G41:P41,$C$3:$L$3) -> 26651.242
B42: Trade Payables | C42: ='Manual Data'!D39 -> 6186 | D42: ='Manual Data'!E39 -> 7170 | E42: ='Manual Data'!F39 -> 7206 | F42: ='Manual Data'!G39 -> 7535 | G42: ='Manual Data'!H39 -> 8802 | H42: ='Manual Data'!I39 -> 9068 | I42: ='Manual Data'!J39 -> 9574 | J42: ='Manual Data'!K39 -> 10486 | ... L42: ='Manual Data'!M39 -> 13325 | M42: =FORECAST($M$3,C42:L42,$C$3:$L$3) -> 12934.192 | N42: =FORECAST($M$3,D42:M42,$C$3:$L$3) -> 13713.11 | O42: =FORECAST($M$3,E42:N42,$C$3:$L$3) -> 14615.924 | P42: =FORECAST($M$3,F42:O42,$C$3:$L$3) -> 15453.15 | Q42: =FORECAST($M$3,G42:P42,$C$3:$L$3) -> 16219.306
B44: Total Liablities | C44: =SUM(C38:C43) -> 15706 | D44: =SUM(D38:D43) -> 17862 | E44: =SUM(E38:E43) -> 18629 | F44: =SUM(F38:F43) -> 20153 | G44: =SUM(G38:G43) -> 68740 | H44: =SUM(H38:H43) -> 70506 | I44: =SUM(I38:I43) -> 73077 | J44: =SUM(J38:J43) -> 78489 | ... Q44: =SUM(Q38:Q43) -> 128088.4
B46: Net Block | C46: ='Data Sheet'!B62 -> 4419 | D46: ='Data Sheet'!C62 -> 4528 | E46: ='Data Sheet'!D62 -> 4715 | F46: ='Data Sheet'!E62 -> 5479 | G46: ='Data Sheet'!F62 -> 51443 | H46: ='Data Sheet'!G62 -> 51473 | I46: ='Data Sheet'!H62 -> 52678 | J46: ='Data Sheet'!I62 -> 53744 | ... L46: ='Data Sheet'!K62 -> 57428 | M46: =FORECAST($M$3,C46:L46,$C$3:$L$3) -> 74432.432 | N46: =FORECAST($M$3,D46:M46,$C$3:$L$3) -> 82703.451 | O46: =FORECAST($M$3,E46:N46,$C$3:$L$3) -> 89639.34 | P46: =FORECAST($M$3,F46:O46,$C$3:$L$3) -> 94191.227 | Q46: =FORECAST($M$3,G46:P46,$C$3:$L$3) -> 95107.224
B47: Capital Work in Progress | C47: ='Data Sheet'!B63 -> 229 | D47: ='Data Sheet'!C63 -> 461 | E47: ='Data Sheet'!D63 -> 406 | F47: ='Data Sheet'!E63 -> 597 | G47: ='Data Sheet'!F63 -> 745 | H47: ='Data Sheet'!G63 -> 1313 | I47: ='Data Sheet'!H63 -> 1132 | J47: ='Data Sheet'!I63 -> 1025 | ... L47: ='Data Sheet'!K63 -> 880 | M47: =FORECAST($M$3,C47:L47,$C$3:$L$3) -> 1278.3516 | N47: =FORECAST($M$3,D47:M47,$C$3:$L$3) -> 1330.9848 | O47: =FORECAST($M$3,E47:N47,$C$3:$L$3) -> 1396.5814 | P47: =FORECAST($M$3,F47:O47,$C$3:$L$3) -> 1415.7253 | Q47: =FORECAST($M$3,G47:P47,$C$3:$L$3) -> 1427.4112
B48: Investments | C48: ='Data Sheet'!B64 -> 3794 | D48: ='Data Sheet'!C64 -> 2873 | E48: ='Data Sheet'!D64 -> 2716 | F48: ='Data Sheet'!E64 -> 1255 | G48: ='Data Sheet'!F64 -> 2709 | H48: ='Data Sheet'!G64 -> 3521 | I48: ='Data Sheet'!H64 -> 2882 | J48: ='Data Sheet'!I64 -> 4625 | ... L48: ='Data Sheet'!K64 -> 4359 | M48: =FORECAST($M$3,C48:L48,$C$3:$L$3) -> 4150.2863 | N48: =FORECAST($M$3,D48:M48,$C$3:$L$3) -> 4652.4928 | O48: =FORECAST($M$3,E48:N48,$C$3:$L$3) -> 5086.2253 | P48: =FORECAST($M$3,F48:O48,$C$3:$L$3) -> 5532.7947 | Q48: =FORECAST($M$3,G48:P48,$C$3:$L$3) -> 5610.8479
B49: Other Assets | C49: ='Data Sheet'!B65-SUM('Data Sheet'!B67:B69) -> 1810 | D49: ='Data Sheet'!C65-SUM('Data Sheet'!C67:C69) -> 2692 | E49: ='Data Sheet'!D65-SUM('Data Sheet'!D67:D69) -> 2645 | F49: ='Data Sheet'!E65-SUM('Data Sheet'!E67:E69) -> 3793 | G49: ='Data Sheet'!F65-SUM('Data Sheet'!F67:F69) -> 4035 | H49: ='Data Sheet'!G65-SUM('Data Sheet'!G67:G69) -> 4021 | I49: ='Data Sheet'!H65-SUM('Data Sheet'!H67:H69) -> 4377 | J49: ='Data Sheet'!I65-SUM('Data Sheet'!I67:I69) -> 4517 | ... L49: ='Data Sheet'!K65-SUM('Data Sheet'!K67:K69) -> 5655 | M49: =FORECAST($M$3,C49:L49,$C$3:$L$3) -> 5889.7525 | N49: =FORECAST($M$3,D49:M49,$C$3:$L$3) -> 6163.9287 | O49: =FORECAST($M$3,E49:N49,$C$3:$L$3) -> 6510.9652 | P49: =FORECAST($M$3,F49:O49,$C$3:$L$3) -> 6752.8739 | Q49: =FORECAST($M$3,G49:P49,$C$3:$L$3) -> 7139.8831
B51: Total Non-Current Assets | C51: =SUM(C46:C50) -> 10252 | D51: =SUM(D46:D50) -> 10554 | E51: =SUM(E46:E50) -> 10482 | F51: =SUM(F46:F50) -> 11124 | G51: =SUM(G46:G50) -> 58932 | H51: =SUM(H46:H50) -> 60328 | I51: =SUM(I46:I50) -> 61069 | J51: =SUM(J46:J50) -> 63911 | ... Q51: =SUM(Q46:Q50) -> 109285.37
B52: Receivables | C52: ='Data Sheet'!B67 -> 1085 | D52: ='Data Sheet'!C67 -> 1310 | E52: ='Data Sheet'!D67 -> 1816 | F52: ='Data Sheet'!E67 -> 1149 | G52: ='Data Sheet'!F67 -> 1758 | H52: ='Data Sheet'!G67 -> 2236 | I52: ='Data Sheet'!H67 -> 3079 | J52: ='Data Sheet'!I67 -> 2997 | ... L52: ='Data Sheet'!K67 -> 3379 | M52: =FORECAST($M$3,C52:L52,$C$3:$L$3) -> 3941.7874 | N52: =FORECAST($M$3,D52:M52,$C$3:$L$3) -> 4299.3987 | O52: =FORECAST($M$3,E52:N52,$C$3:$L$3) -> 4669.4478 | P52: =FORECAST($M$3,F52:O52,$C$3:$L$3) -> 5123.2225 | Q52: =FORECAST($M$3,G52:P52,$C$3:$L$3) -> 5390.3826
B53: Inventory | C53: ='Data Sheet'!B68 -> 2541 | D53: ='Data Sheet'!C68 -> 2513 | E53: ='Data Sheet'!D68 -> 2574 | F53: ='Data Sheet'!E68 -> 2767 | G53: ='Data Sheet'!F68 -> 3579 | H53: ='Data Sheet'!G68 -> 4096 | I53: ='Data Sheet'!H68 -> 4251 | J53: ='Data Sheet'!I68 -> 4022 | ... L53: ='Data Sheet'!K68 -> 4789 | M53: =FORECAST($M$3,C53:L53,$C$3:$L$3) -> 5079.5218 | N53: =FORECAST($M$3,D53:M53,$C$3:$L$3) -> 5419.2054 | O53: =FORECAST($M$3,E53:N53,$C$3:$L$3) -> 5717.9675 | P53: =FORECAST($M$3,F53:O53,$C$3:$L$3) -> 5958.7304 | Q53: =FORECAST($M$3,G53:P53,$C$3:$L$3) -> 6137.7248
B54: Cash & Bank | C54: ='Data Sheet'!B69 -> 1828 | D54: ='Data Sheet'!C69 -> 3485 | E54: ='Data Sheet'!D69 -> 3757 | F54: ='Data Sheet'!E69 -> 5113 | G54: ='Data Sheet'!F69 -> 4471 | H54: ='Data Sheet'!G69 -> 3846 | I54: ='Data Sheet'!H69 -> 4678 | J54: ='Data Sheet'!I69 -> 7559 | ... L54: ='Data Sheet'!K69 -> 3248 | M54: =FORECAST($M$3,C54:L54,$C$3:$L$3) -> 6498.6198 | N54: =FORECAST($M$3,D54:M54,$C$3:$L$3) -> 6549.1808 | O54: =FORECAST($M$3,E54:N54,$C$3:$L$3) -> 6750.609 | P54: =FORECAST($M$3,F54:O54,$C$3:$L$3) -> 6901.8888 | Q54: =FORECAST($M$3,G54:P54,$C$3:$L$3) -> 7274.9294
B55: Total Current Assets | C55: =SUM(C52:C54) -> 5454 | D55: =SUM(D52:D54) -> 7308 | E55: =SUM(E52:E54) -> 8147 | F55: =SUM(F52:F54) -> 9029 | G55: =SUM(G52:G54) -> 9808 | H55: =SUM(H52:H54) -> 10178 | I55: =SUM(I52:I54) -> 12008 | J55: =SUM(J52:J54) -> 14578 | ... Q55: =SUM(Q52:Q54) -> 18803.037
B57: Total Assets | C57: =C51+C55 -> 15706 | D57: =D51+D55 -> 17862 | E57: =E51+E55 -> 18629 | F57: =F51+F55 -> 20153 | G57: =G51+G55 -> 68740 | H57: =H51+H55 -> 70506 | I57: =I51+I55 -> 73077 | J57: =J51+J55 -> 78489 | K57: =K51+K55 -> 79863 | L57: =SUM(L55,L51) -> 79738 | M57: =SUM(M55,M51) -> 101270.75 | N57: =SUM(N55,N51) -> 111118.64 | O57: =SUM(O55,O51) -> 119771.14 | P57: =SUM(P55,P51) -> 125876.46 | Q57: =SUM(Q55,Q51) -> 128088.4
A61: # | B61: Cash flow Satement
B62: Cash Flow from Operating Activity
B63: Profit from Operations | C63: =C21 -> 6184 | D63: =D21 -> 6835 | E63: =E21 -> 8339 | F63: =F21 -> 8643 | G63: =G21 -> 9742 | H63: =H21 -> 11722 | I63: =I21 -> 12860 | J63: =J21 -> 13421 | ... L63: =L21 -> 12848 | M63: =FORECAST($M$3,C63:L63,$C$3:$L$3) -> 15195.788 | N63: =FORECAST($M$3,D63:M63,$C$3:$L$3) -> 16003.861 | O63: =FORECAST($M$3,E63:N63,$C$3:$L$3) -> 16708.192 | P63: =FORECAST($M$3,F63:O63,$C$3:$L$3) -> 17484.035 | Q63: =FORECAST($M$3,G63:P63,$C$3:$L$3) -> 18093.087
B64: Receivables | C64: ='Manual Data'!D3 -> 173 | D64: ='Manual Data'!E3 -> 0 | E64: ='Manual Data'!F3 -> 0 | F64: ='Manual Data'!G3 -> 0 | G64: ='Manual Data'!H3 -> 0 | H64: ='Manual Data'!I3 -> 0 | I64: ='Manual Data'!J3 -> 0 | J64: ='Manual Data'!K3 -> 0 | ... L64: ='Manual Data'!M3 -> 0 | M64: =FORECAST($M$3,C64:L64,$C$3:$L$3) -> -34.585071 | N64: =FORECAST($M$3,D64:M64,$C$3:$L$3) -> -13.831044 | O64: =FORECAST($M$3,E64:N64,$C$3:$L$3) -> -17.058662 | P64: =FORECAST($M$3,F64:O64,$C$3:$L$3) -> -20.655806 | Q64: =FORECAST($M$3,G64:P64,$C$3:$L$3) -> -24.54896
B65: Inventory | C65: ='Manual Data'!D4 -> 37 | D65: ='Manual Data'!E4 -> -146 | E65: ='Manual Data'!F4 -> -195 | F65: ='Manual Data'!G4 -> -331 | G65: ='Manual Data'!H4 -> -543 | H65: ='Manual Data'!I4 -> -758 | I65: ='Manual Data'!J4 -> -339 | J65: ='Manual Data'!K4 -> 74 | ... L65: ='Manual Data'!M4 -> -692 | M65: =FORECAST($M$3,C65:L65,$C$3:$L$3) -> -631.64273 | N65: =FORECAST($M$3,D65:M65,$C$3:$L$3) -> -642.74483 | O65: =FORECAST($M$3,E65:N65,$C$3:$L$3) -> -662.36508 | P65: =FORECAST($M$3,F65:O65,$C$3:$L$3) -> -669.74566 | Q65: =FORECAST($M$3,G65:P65,$C$3:$L$3) -> -685.28235
B66: Payables | C66: ='Manual Data'!D5 -> 501 | D66: ='Manual Data'!E5 -> 0 | E66: ='Manual Data'!F5 -> 0 | F66: ='Manual Data'!G5 -> 0 | G66: ='Manual Data'!H5 -> 0 | H66: ='Manual Data'!I5 -> 0 | I66: ='Manual Data'!J5 -> 0 | J66: ='Manual Data'!K5 -> 0 | ... L66: ='Manual Data'!M5 -> 0 | M66: =FORECAST($M$3,C66:L66,$C$3:$L$3) -> -100.15677 | N66: =FORECAST($M$3,D66:M66,$C$3:$L$3) -> -40.054063 | O66: =FORECAST($M$3,E66:N66,$C$3:$L$3) -> -49.401097 | P66: =FORECAST($M$3,F66:O66,$C$3:$L$3) -> -59.818258 | Q66: =FORECAST($M$3,G66:P66,$C$3:$L$3) -> -71.092653
B67: Loan Advances | C67: ='Manual Data'!D6 -> 0 | D67: ='Manual Data'!E6 -> 0 | E67: ='Manual Data'!F6 -> 0 | F67: ='Manual Data'!G6 -> 0 | G67: ='Manual Data'!H6 -> 0 | H67: ='Manual Data'!I6 -> 0 | I67: ='Manual Data'!J6 -> 0 | J67: ='Manual Data'!K6 -> 0 | ... L67: ='Manual Data'!M6 -> 0 | M67: =FORECAST($M$3,C67:L67,$C$3:$L$3) -> 0 | N67: =FORECAST($M$3,D67:M67,$C$3:$L$3) -> 0 | O67: =FORECAST($M$3,E67:N67,$C$3:$L$3) -> 0 | P67: =FORECAST($M$3,F67:O67,$C$3:$L$3) -> 0 | Q67: =FORECAST($M$3,G67:P67,$C$3:$L$3) -> 0
B68: Operating Deposits | C68: ='Manual Data'!D7 -> -46 | D68: ='Manual Data'!E7 -> 0 | E68: ='Manual Data'!F7 -> 0 | F68: ='Manual Data'!G7 -> 0 | G68: ='Manual Data'!H7 -> 0 | H68: ='Manual Data'!I7 -> 0 | I68: ='Manual Data'!J7 -> 0 | J68: ='Manual Data'!K7 -> 0 | ... L68: ='Manual Data'!M7 -> 0 | M68: =FORECAST($M$3,C68:L68,$C$3:$L$3) -> 9.1960304 | N68: =FORECAST($M$3,D68:M68,$C$3:$L$3) -> 3.6776186 | O68: =FORECAST($M$3,E68:N68,$C$3:$L$3) -> 4.5358292 | P68: =FORECAST($M$3,F68:O68,$C$3:$L$3) -> 5.4922952 | Q68: =FORECAST($M$3,G68:P68,$C$3:$L$3) -> 6.5274691
B69: Other WC items | C69: ='Manual Data'!D8 -> -99 | D69: ='Manual Data'!E8 -> 982 | E69: ='Manual Data'!F8 -> -147 | F69: ='Manual Data'!G8 -> 742 | G69: ='Manual Data'!H8 -> 442 | H69: ='Manual Data'!I8 -> -242 | I69: ='Manual Data'!J8 -> -621 | J69: ='Manual Data'!K8 -> 1239 | ... L69: ='Manual Data'!M8 -> 1378 | M69: =FORECAST($M$3,C69:L69,$C$3:$L$3) -> 585.35922 | N69: =FORECAST($M$3,D69:M69,$C$3:$L$3) -> 561.57928 | O69: =FORECAST($M$3,E69:N69,$C$3:$L$3) -> 771.13322 | P69: =FORECAST($M$3,F69:O69,$C$3:$L$3) -> 791.42792 | Q69: =FORECAST($M$3,G69:P69,$C$3:$L$3) -> 995.83536
B70: Working capital changes | C70: ='Manual Data'!D9 -> 566 | D70: ='Manual Data'!E9 -> 836 | E70: ='Manual Data'!F9 -> -342 | F70: ='Manual Data'!G9 -> 411 | G70: ='Manual Data'!H9 -> -101 | H70: ='Manual Data'!I9 -> -1000 | I70: ='Manual Data'!J9 -> -960 | J70: ='Manual Data'!K9 -> 1313 | ... L70: ='Manual Data'!M9 -> 686 | M70: =FORECAST($M$3,C70:L70,$C$3:$L$3) -> -171.82931 | N70: =FORECAST($M$3,D70:M70,$C$3:$L$3) -> -131.37304 | O70: =FORECAST($M$3,E70:N70,$C$3:$L$3) -> 46.84421 | P70: =FORECAST($M$3,F70:O70,$C$3:$L$3) -> 46.700491 | Q70: =FORECAST($M$3,G70:P70,$C$3:$L$3) -> 221.43886
B71: Direct taxes | C71: ='Manual Data'!D10 -> -1859 | D71: ='Manual Data'!E10 -> -2264 | E71: ='Manual Data'!F10 -> -2767 | F71: ='Manual Data'!G10 -> -2505 | G71: ='Manual Data'!H10 -> -2407 | H71: ='Manual Data'!I10 -> -2784 | I71: ='Manual Data'!J10 -> -3138 | J71: ='Manual Data'!K10 -> -381 | ... L71: ='Manual Data'!M10 -> -4840 | M71: =FORECAST($M$3,C71:L71,$C$3:$L$3) -> -3094.3289 | N71: =FORECAST($M$3,D71:M71,$C$3:$L$3) -> -3147.3679 | O71: =FORECAST($M$3,E71:N71,$C$3:$L$3) -> -3246.9509 | P71: =FORECAST($M$3,F71:O71,$C$3:$L$3) -> -3461.0418 | Q71: =FORECAST($M$3,G71:P71,$C$3:$L$3) -> -3659.208
B72: Other operating items | C72: ='Manual Data'!D11 -> -21 | D72: ='Manual Data'!E11 -> 0 | E72: ='Manual Data'!F11 -> 0 | F72: ='Manual Data'!G11 -> 0 | G72: ='Manual Data'!H11 -> 0 | H72: ='Manual Data'!I11 -> 0 | I72: ='Manual Data'!J11 -> 0 | J72: ='Manual Data'!K11 -> 0 | ... L72: ='Manual Data'!M11 -> 0 | M72: =FORECAST($M$3,C72:L72,$C$3:$L$3) -> 4.1981878 | N72: =FORECAST($M$3,D72:M72,$C$3:$L$3) -> 1.6789128 | O72: =FORECAST($M$3,E72:N72,$C$3:$L$3) -> 2.0707047 | P72: =FORECAST($M$3,F72:O72,$C$3:$L$3) -> 2.5073521 | Q72: =FORECAST($M$3,G72:P72,$C$3:$L$3) -> 2.9799316
B73: Exceptional CF items | C73: ='Manual Data'!D12 -> -13 | D73: ='Manual Data'!E12 -> 2 | E73: ='Manual Data'!F12 -> 0 | F73: ='Manual Data'!G12 -> -6 | G73: ='Manual Data'!H12 -> -1 | H73: ='Manual Data'!I12 -> 3 | I73: ='Manual Data'!J12 -> 0 | J73: ='Manual Data'!K12 -> 0 | ... L73: ='Manual Data'!M12 -> 0 | M73: =FORECAST($M$3,C73:L73,$C$3:$L$3) -> 2.6649409 | N73: =FORECAST($M$3,D73:M73,$C$3:$L$3) -> 1.266118 | O73: =FORECAST($M$3,E73:N73,$C$3:$L$3) -> 2.26139 | P73: =FORECAST($M$3,F73:O73,$C$3:$L$3) -> 3.1697953 | Q73: =FORECAST($M$3,G73:P73,$C$3:$L$3) -> 2.6917975
B74: Cash Flow From Operating Activity | C74: =SUM(C63:C73) -> 5423 | D74: =SUM(D63:D73) -> 6245 | E74: =SUM(E63:E73) -> 4888 | F74: =SUM(F63:F73) -> 6954 | G74: =SUM(G63:G73) -> 7132 | H74: =SUM(H63:H73) -> 6941 | I74: =SUM(I63:I73) -> 7802 | J74: =SUM(J63:J73) -> 15666 | ... L74: =SUM(L63:L73) -> 9380 | M74: =FORECAST($M$3,C74:L74,$C$3:$L$3) -> 11764.663 | N74: =FORECAST($M$3,D74:M74,$C$3:$L$3) -> 12596.692 | O74: =FORECAST($M$3,E74:N74,$C$3:$L$3) -> 13559.262 | P74: =FORECAST($M$3,F74:O74,$C$3:$L$3) -> 14122.071 | Q74: =FORECAST($M$3,G74:P74,$C$3:$L$3) -> 14882.428
B76: Cash Flow From Investing Acitivity
B77: Fixed assets purchased | C77: ='Manual Data'!D16 -> -1113 | D77: ='Manual Data'!E16 -> -895 | E77: ='Manual Data'!F16 -> -767 | F77: ='Manual Data'!G16 -> -862 | G77: ='Manual Data'!H16 -> -4163 | H77: ='Manual Data'!I16 -> -1228 | I77: ='Manual Data'!J16 -> -1192 | J77: ='Manual Data'!K16 -> -1477 | ... L77: ='Manual Data'!M16 -> -1361 | M77: =FORECAST($M$3,C77:L77,$C$3:$L$3) -> -1649.9168 | N77: =FORECAST($M$3,D77:M77,$C$3:$L$3) -> -1651.2745 | O77: =FORECAST($M$3,E77:N77,$C$3:$L$3) -> -1558.7459 | P77: =FORECAST($M$3,F77:O77,$C$3:$L$3) -> -1345.2458 | Q77: =FORECAST($M$3,G77:P77,$C$3:$L$3) -> -1018.9017
B78: Fixed assets sold | C78: ='Manual Data'!D17 -> 176 | D78: ='Manual Data'!E17 -> 32 | E78: ='Manual Data'!F17 -> 13 | F78: ='Manual Data'!G17 -> 52 | G78: ='Manual Data'!H17 -> 97 | H78: ='Manual Data'!I17 -> 175 | I78: ='Manual Data'!J17 -> 181 | J78: ='Manual Data'!K17 -> 20 | ... L78: ='Manual Data'!M17 -> 29 | M78: =FORECAST($M$3,C78:L78,$C$3:$L$3) -> 46.932869 | N78: =FORECAST($M$3,D78:M78,$C$3:$L$3) -> 60.110193 | O78: =FORECAST($M$3,E78:N78,$C$3:$L$3) -> 48.76817 | P78: =FORECAST($M$3,F78:O78,$C$3:$L$3) -> 25.936937 | Q78: =FORECAST($M$3,G78:P78,$C$3:$L$3) -> 1.9827093
B79: Investments purchased | C79: ='Manual Data'!D18 -> -31214 | D79: ='Manual Data'!E18 -> -51855 | E79: ='Manual Data'!F18 -> -74365 | F79: ='Manual Data'!G18 -> -36090 | G79: ='Manual Data'!H18 -> -39920 | H79: ='Manual Data'!I18 -> -48522 | I79: ='Manual Data'!J18 -> -22649 | J79: ='Manual Data'!K18 -> -21337 | ... L79: ='Manual Data'!M18 -> -25529 | M79: =FORECAST($M$3,C79:L79,$C$3:$L$3) -> -19100.514 | N79: =FORECAST($M$3,D79:M79,$C$3:$L$3) -> -10107.598 | O79: =FORECAST($M$3,E79:N79,$C$3:$L$3) -> -3825.3927 | P79: =FORECAST($M$3,F79:O79,$C$3:$L$3) -> -3808.8543 | Q79: =FORECAST($M$3,G79:P79,$C$3:$L$3) -> 1711.0538
B80: Investments sold | C80: ='Manual Data'!D19 -> 30083 | D80: ='Manual Data'!E19 -> 52897 | E80: ='Manual Data'!F19 -> 74691 | F80: ='Manual Data'!G19 -> 37690 | G80: ='Manual Data'!H19 -> 38486 | H80: ='Manual Data'!I19 -> 47786 | I80: ='Manual Data'!J19 -> 23462 | J80: ='Manual Data'!K19 -> 19846 | ... L80: ='Manual Data'!M19 -> 25117 | M80: =FORECAST($M$3,C80:L80,$C$3:$L$3) -> 18915.775 | N80: =FORECAST($M$3,D80:M80,$C$3:$L$3) -> 9573.7013 | O80: =FORECAST($M$3,E80:N80,$C$3:$L$3) -> 3318.9204 | P80: =FORECAST($M$3,F80:O80,$C$3:$L$3) -> 3255.0467 | Q80: =FORECAST($M$3,G80:P80,$C$3:$L$3) -> -1936.4553
B81: Interest received | C81: ='Manual Data'!D20 -> 264 | D81: ='Manual Data'!E20 -> 297 | E81: ='Manual Data'!F20 -> 289 | F81: ='Manual Data'!G20 -> 351 | G81: ='Manual Data'!H20 -> 277 | H81: ='Manual Data'!I20 -> 161 | I81: ='Manual Data'!J20 -> 259 | J81: ='Manual Data'!K20 -> 425 | ... L81: ='Manual Data'!M20 -> 428 | M81: =FORECAST($M$3,C81:L81,$C$3:$L$3) -> 542.92111 | N81: =FORECAST($M$3,D81:M81,$C$3:$L$3) -> 591.41006 | O81: =FORECAST($M$3,E81:N81,$C$3:$L$3) -> 649.44619 | P81: =FORECAST($M$3,F81:O81,$C$3:$L$3) -> 709.0453 | Q81: =FORECAST($M$3,G81:P81,$C$3:$L$3) -> 784.95611
B82: Dividends received | C82: ='Manual Data'!D21 -> 14 | D82: ='Manual Data'!E21 -> 0 | E82: ='Manual Data'!F21 -> 1 | F82: ='Manual Data'!G21 -> 1 | G82: ='Manual Data'!H21 -> 1 | H82: ='Manual Data'!I21 -> 1 | I82: ='Manual Data'!J21 -> 2 | J82: ='Manual Data'!K21 -> 3 | ... L82: ='Manual Data'!M21 -> 5 | M82: =FORECAST($M$3,C82:L82,$C$3:$L$3) -> 0.53408672 | N82: =FORECAST($M$3,D82:M82,$C$3:$L$3) -> 2.6132401 | O82: =FORECAST($M$3,E82:N82,$C$3:$L$3) -> 2.6900572 | P82: =FORECAST($M$3,F82:O82,$C$3:$L$3) -> 2.8891427 | Q82: =FORECAST($M$3,G82:P82,$C$3:$L$3) -> 3.0559082
B83: Redemp and Cancellation of Shares | C83: ='Manual Data'!D22 -> 20 | D83: ='Manual Data'!E22 -> 73 | E83: ='Manual Data'!F22 -> 0 | F83: ='Manual Data'!G22 -> 0 | G83: ='Manual Data'!H22 -> 0 | H83: ='Manual Data'!I22 -> 0 | I83: ='Manual Data'!J22 -> 0 | J83: ='Manual Data'!K22 -> 0 | ... L83: ='Manual Data'!M22 -> 298 | M83: =FORECAST($M$3,C83:L83,$C$3:$L$3) -> 105.44462 | N83: =FORECAST($M$3,D83:M83,$C$3:$L$3) -> 126.90046 | O83: =FORECAST($M$3,E83:N83,$C$3:$L$3) -> 165.37119 | P83: =FORECAST($M$3,F83:O83,$C$3:$L$3) -> 196.12635 | Q83: =FORECAST($M$3,G83:P83,$C$3:$L$3) -> 228.20119
B84: Acquisition of companies | C84: ='Manual Data'!D23 -> 0 | D84: ='Manual Data'!E23 -> 0 | E84: ='Manual Data'!F23 -> 0 | F84: ='Manual Data'!G23 -> 0 | G84: ='Manual Data'!H23 -> 0 | H84: ='Manual Data'!I23 -> 0 | I84: ='Manual Data'!J23 -> -334 | J84: ='Manual Data'!K23 -> 0 | ... L84: ='Manual Data'!M23 -> 0 | M84: =FORECAST($M$3,C84:L84,$C$3:$L$3) -> -66.770076 | N84: =FORECAST($M$3,D84:M84,$C$3:$L$3) -> -71.225627 | O84: =FORECAST($M$3,E84:N84,$C$3:$L$3) -> -73.015664 | P84: =FORECAST($M$3,F84:O84,$C$3:$L$3) -> -70.77744 | Q84: =FORECAST($M$3,G84:P84,$C$3:$L$3) -> -62.707636
B85: Other investing items | C85: ='Manual Data'!D24 -> 597 | D85: ='Manual Data'!E24 -> -1612 | E85: ='Manual Data'!F24 -> -300 | F85: ='Manual Data'!G24 -> 649 | G85: ='Manual Data'!H24 -> 3994 | H85: ='Manual Data'!I24 -> -101 | I85: ='Manual Data'!J24 -> -1213 | J85: ='Manual Data'!K24 -> -2804 | ... L85: ='Manual Data'!M24 -> -2663 | M85: =FORECAST($M$3,C85:L85,$C$3:$L$3) -> 269.7553 | N85: =FORECAST($M$3,D85:M85,$C$3:$L$3) -> 376.15125 | O85: =FORECAST($M$3,E85:N85,$C$3:$L$3) -> -44.044218 | P85: =FORECAST($M$3,F85:O85,$C$3:$L$3) -> -412.72678 | Q85: =FORECAST($M$3,G85:P85,$C$3:$L$3) -> -693.30315
B86: Cash Flow From Investing Acitivity | C86: =SUM(C77:C85) -> -1173 | D86: =SUM(D77:D85) -> -1063 | E86: =SUM(E77:E85) -> -438 | F86: =SUM(F77:F85) -> 1791 | G86: =SUM(G77:G85) -> -1228 | H86: =SUM(H77:H85) -> -1728 | I86: =SUM(I77:I85) -> -1484 | J86: =SUM(J77:J85) -> -5324 | ... M86: =SUM(M77:M85) -> -935.83789 | N86: =FORECAST($M$3,D86:M86,$C$3:$L$3) -> -1099.2118 | O86: =FORECAST($M$3,E86:N86,$C$3:$L$3) -> -1316.0024 | P86: =FORECAST($M$3,F86:O86,$C$3:$L$3) -> -1448.56 | Q86: =FORECAST($M$3,G86:P86,$C$3:$L$3) -> -982.11808
B88: Cash Flow From Financing Activity
B89: Proceeds from shares | C89: ='Manual Data'!D29 -> 0 | D89: ='Manual Data'!E29 -> 0 | E89: ='Manual Data'!F29 -> 0 | F89: ='Manual Data'!G29 -> 0 | G89: ='Manual Data'!H29 -> 0 | H89: ='Manual Data'!I29 -> 0 | I89: ='Manual Data'!J29 -> 0 | J89: ='Manual Data'!K29 -> 0 | ... L89: ='Manual Data'!M29 -> 0 | M89: =FORECAST($M$3,C89:L89,$C$3:$L$3) -> 0 | N89: =FORECAST($M$3,D89:M89,$C$3:$L$3) -> 0 | O89: =FORECAST($M$3,E89:N89,$C$3:$L$3) -> 0 | P89: =FORECAST($M$3,F89:O89,$C$3:$L$3) -> 0 | Q89: =FORECAST($M$3,G89:P89,$C$3:$L$3) -> 0
B90: Proceeds from borrowings | C90: ='Manual Data'!D30 -> 460 | D90: ='Manual Data'!E30 -> 0 | E90: ='Manual Data'!F30 -> 99 | F90: ='Manual Data'!G30 -> 0 | G90: ='Manual Data'!H30 -> 188 | H90: ='Manual Data'!I30 -> 55 | I90: ='Manual Data'!J30 -> 286 | J90: ='Manual Data'!K30 -> 0 | ... L90: ='Manual Data'!M30 -> 0 | M90: =FORECAST($M$3,C90:L90,$C$3:$L$3) -> -21.518572 | N90: =FORECAST($M$3,D90:M90,$C$3:$L$3) -> 20.007003 | O90: =FORECAST($M$3,E90:N90,$C$3:$L$3) -> -12.4221 | P90: =FORECAST($M$3,F90:O90,$C$3:$L$3) -> -32.742837 | Q90: =FORECAST($M$3,G90:P90,$C$3:$L$3) -> -80.192402
B91: Repayment of borrowings | C91: ='Manual Data'!D31 -> -360 | D91: ='Manual Data'!E31 -> -277 | E91: ='Manual Data'!F31 -> 0 | F91: ='Manual Data'!G31 -> -99 | G91: ='Manual Data'!H31 -> -188 | H91: ='Manual Data'!I31 -> -55 | I91: ='Manual Data'!J31 -> -208 | J91: ='Manual Data'!K31 -> -85 | ... L91: ='Manual Data'!M31 -> -46 | M91: =FORECAST($M$3,C91:L91,$C$3:$L$3) -> 6.3685193 | N91: =FORECAST($M$3,D91:M91,$C$3:$L$3) -> 0.78946731 | O91: =FORECAST($M$3,E91:N91,$C$3:$L$3) -> -9.3014659 | P91: =FORECAST($M$3,F91:O91,$C$3:$L$3) -> 31.879734 | Q91: =FORECAST($M$3,G91:P91,$C$3:$L$3) -> 63.782223
B92: Interest paid fin | C92: ='Manual Data'!D32 -> -14 | D92: ='Manual Data'!E32 -> -6 | E92: ='Manual Data'!F32 -> -7 | F92: ='Manual Data'!G32 -> -90 | G92: ='Manual Data'!H32 -> -92 | H92: ='Manual Data'!I32 -> -82 | I92: ='Manual Data'!J32 -> -88 | J92: ='Manual Data'!K32 -> -110 | ... L92: ='Manual Data'!M32 -> -133 | M92: =FORECAST($M$3,C92:L92,$C$3:$L$3) -> -156.457 | N92: =FORECAST($M$3,D92:M92,$C$3:$L$3) -> -172.63267 | O92: =FORECAST($M$3,E92:N92,$C$3:$L$3) -> -183.65241 | P92: =FORECAST($M$3,F92:O92,$C$3:$L$3) -> -188.248 | Q92: =FORECAST($M$3,G92:P92,$C$3:$L$3) -> -205.031
B93: Dividends paid | C93: ='Manual Data'!D33 -> -3572 | D93: ='Manual Data'!E33 -> -3911 | E93: ='Manual Data'!F33 -> -4554 | F93: ='Manual Data'!G33 -> -5196 | G93: ='Manual Data'!H33 -> -8811 | H93: ='Manual Data'!I33 -> -7526 | I93: ='Manual Data'!J33 -> -8474 | J93: ='Manual Data'!K33 -> -9416 | ... L93: ='Manual Data'!M33 -> -10124 | M93: =FORECAST($M$3,C93:L93,$C$3:$L$3) -> -12463.513 | N93: =FORECAST($M$3,D93:M93,$C$3:$L$3) -> -13464.478 | O93: =FORECAST($M$3,E93:N93,$C$3:$L$3) -> -14362.639 | P93: =FORECAST($M$3,F93:O93,$C$3:$L$3) -> -15155.695 | Q93: =FORECAST($M$3,G93:P93,$C$3:$L$3) -> -15783.088
B94: Financial liabilities | C94: ='Manual Data'!D34 -> 0 | D94: ='Manual Data'!E34 -> 0 | E94: ='Manual Data'!F34 -> 0 | F94: ='Manual Data'!G34 -> -373 | G94: ='Manual Data'!H34 -> -406 | H94: ='Manual Data'!I34 -> -407 | I94: ='Manual Data'!J34 -> -467 | J94: ='Manual Data'!K34 -> -423 | ... L94: ='Manual Data'!M34 -> -507 | M94: =FORECAST($M$3,C94:L94,$C$3:$L$3) -> -656.28193 | N94: =FORECAST($M$3,D94:M94,$C$3:$L$3) -> -713.37683 | O94: =FORECAST($M$3,E94:N94,$C$3:$L$3) -> -749.57213 | P94: =FORECAST($M$3,F94:O94,$C$3:$L$3) -> -752.72476 | Q94: =FORECAST($M$3,G94:P94,$C$3:$L$3) -> -806.58547
B95: Other financing items | C95: ='Manual Data'!D35 -> -728 | D95: ='Manual Data'!E35 -> -781 | E95: ='Manual Data'!F35 -> -928 | F95: ='Manual Data'!G35 -> -1061 | G95: ='Manual Data'!H35 -> 0 | H95: ='Manual Data'!I35 -> 0 | I95: ='Manual Data'!J35 -> -2 | J95: ='Manual Data'!K35 -> 0 | ... L95: ='Manual Data'!M35 -> 0 | M95: =FORECAST($M$3,C95:L95,$C$3:$L$3) -> 311.05232 | N95: =FORECAST($M$3,D95:M95,$C$3:$L$3) -> 474.73728 | O95: =FORECAST($M$3,E95:N95,$C$3:$L$3) -> 620.35479 | P95: =FORECAST($M$3,F95:O95,$C$3:$L$3) -> 701.3874 | Q95: =FORECAST($M$3,G95:P95,$C$3:$L$3) -> 676.19123
B96: Cash Flow From Financing Activity | C96: =SUM(C89:C95) -> -4214 | D96: =SUM(D89:D95) -> -4975 | E96: =SUM(E89:E95) -> -5390 | F96: =SUM(F89:F95) -> -6819 | G96: =SUM(G89:G95) -> -9309 | H96: =SUM(H89:H95) -> -8015 | I96: =SUM(I89:I95) -> -8953 | J96: =SUM(J89:J95) -> -10034 | ... M96: =SUM(M89:M95) -> -12980.35 | N96: =FORECAST($M$3,D96:M96,$C$3:$L$3) -> -13854.954 | O96: =FORECAST($M$3,E96:N96,$C$3:$L$3) -> -14697.232 | P96: =FORECAST($M$3,F96:O96,$C$3:$L$3) -> -15396.144 | Q96: =FORECAST($M$3,G96:P96,$C$3:$L$3) -> -16134.923
B98: Net Cash flow | C98: =C74+C86+C96 -> 36 | D98: =D74+D86+D96 -> 207 | E98: =E74+E86+E96 -> -940 | F98: =F74+F86+F96 -> 1926 | G98: =G74+G86+G96 -> -3405 | H98: =H74+H86+H96 -> -2802 | I98: =I74+I86+I96 -> -2635 | J98: =J74+J86+J96 -> 308 | ... Q98: =Q74+Q86+Q96 -> -2234.6132
B105: CAGR | C105: =(L6/C6)^(1/9)-1 -> 0.076658974

Sheet Ratio Analysis
B2: ="Ratio Analysis for "&'Data Sheet'!B1 -> Ratio Analysis for HINDUSTAN UNILEVER LTD
B3: Year | C3: ='Historical FS'!C3 -> 42825 | D3: ='Historical FS'!D3 -> 43190 | E3: ='Historical FS'!E3 -> 43555 | F3: ='Historical FS'!F3 -> 43921 | G3: ='Historical FS'!G3 -> 44286 | H3: ='Historical FS'!H3 -> 44651 | I3: ='Historical FS'!I3 -> 45016 | J3: ='Historical FS'!J3 -> 45382 | ... Q3: ='Historical FS'!Q3 -> 47937
B4: Profitability Ratios
B5: Gross Profit Margin | C5: ='Historical FS'!C11/'Historical FS'!C6 -> 0.44554008 | D5: ='Historical FS'!D11/'Historical FS'!D6 -> 0.45258124 | E5: ='Historical FS'!E11/'Historical FS'!E6 -> 0.46433477 | F5: ='Historical FS'!F11/'Historical FS'!F6 -> 0.47640952 | G5: ='Historical FS'!G11/'Historical FS'!G6 -> 0.44477758 | H5: ='Historical FS'!H11/'Historical FS'!H6 -> 0.4449529 | I5: ='Historical FS'!I11/'Historical FS'!I6 -> 0.4134863 | J5: ='Historical FS'!J11/'Historical FS'!J6 -> 0.45597454 | ... Q5: ='Historical FS'!Q11/'Historical FS'!Q6 -> 0.43371966
B6: EBITDA Margins | C6: ='Historical FS'!C16/'Historical FS'!C6 -> 0.19950546 | D6: ='Historical FS'!D16/'Historical FS'!D6 -> 0.2069208 | E6: ='Historical FS'!E16/'Historical FS'!E6 -> 0.22650725 | F6: ='Historical FS'!F16/'Historical FS'!F6 -> 0.24244024 | G6: ='Historical FS'!G16/'Historical FS'!G6 -> 0.22999064 | H6: ='Historical FS'!H16/'Historical FS'!H6 -> 0.24430843 | I6: ='Historical FS'!I16/'Historical FS'!I6 -> 0.23104985 | J6: ='Historical FS'!J16/'Historical FS'!J6 -> 0.23647732 | ... Q6: ='Historical FS'!Q16/'Historical FS'!Q6 -> 0.23101337
B7: EBIT Margins | C7: ='Historical FS'!C21/'Historical FS'!C6 -> 0.1864785 | D7: ='Historical FS'!D21/'Historical FS'!D6 -> 0.19229146 | E7: ='Historical FS'!E21/'Historical FS'!E6 -> 0.21213432 | F7: ='Historical FS'!F21/'Historical FS'!F6 -> 0.2172536 | G7: ='Historical FS'!G21/'Historical FS'!G6 -> 0.20715319 | H7: ='Historical FS'!H21/'Historical FS'!H6 -> 0.22350608 | I7: ='Historical FS'!I21/'Historical FS'!I6 -> 0.21228128 | J7: ='Historical FS'!J21/'Historical FS'!J6 -> 0.21683146 | ... Q7: ='Historical FS'!Q21/'Historical FS'!Q6 -> 0.2100621
B8: Net Profit Margins | C8: ='Historical FS'!C31/'Historical FS'!C6 -> 0.12580665 | D8: ='Historical FS'!D31/'Historical FS'!D6 -> 0.13307076 | E8: ='Historical FS'!E31/'Historical FS'!E6 -> 0.14657848 | F8: ='Historical FS'!F31/'Historical FS'!F6 -> 0.15373401 | G8: ='Historical FS'!G31/'Historical FS'!G6 -> 0.14925151 | H8: ='Historical FS'!H31/'Historical FS'!H6 -> 0.16453114 | I8: ='Historical FS'!I31/'Historical FS'!I6 -> 0.15756025 | J8: ='Historical FS'!J31/'Historical FS'!J6 -> 0.15256236 | ... Q8: ='Historical FS'!Q31/'Historical FS'!Q6 -> 0.14973927
B9: Return on Assets | C9: ='Historical FS'!C31/'Historical FS'!C57 -> 0.26563097 | D9: ='Historical FS'!D31/'Historical FS'!D57 -> 0.26480797 | E9: ='Historical FS'!E31/'Historical FS'!E57 -> 0.3093027 | F9: ='Historical FS'!F31/'Historical FS'!F57 -> 0.30347839 | G9: ='Historical FS'!G31/'Historical FS'!G57 -> 0.1021094 | H9: ='Historical FS'!H31/'Historical FS'!H57 -> 0.12238675 | I9: ='Historical FS'!I31/'Historical FS'!I57 -> 0.13061565 | J9: ='Historical FS'!J31/'Historical FS'!J57 -> 0.12030985 | ... Q9: ='Historical FS'!Q31/'Historical FS'!Q57 -> 0.10069105
B10: Return on Equity | C10: ='Historical FS'!C31/SUM('Historical FS'!C38:C39) -> 0.61862396 | D10: ='Historical FS'!D31/SUM('Historical FS'!D38:D39) -> 0.64963604 | E10: ='Historical FS'!E31/SUM('Historical FS'!E38:E39) -> 0.73242659 | F10: ='Historical FS'!F31/SUM('Historical FS'!F38:F39) -> 0.74322518 | G10: ='Historical FS'!G31/SUM('Historical FS'!G38:G39) -> 0.1472291 | H10: ='Historical FS'!H31/SUM('Historical FS'!H38:H39) -> 0.17588308 | I10: ='Historical FS'!I31/SUM('Historical FS'!I38:I39) -> 0.18974634 | J10: ='Historical FS'!J31/SUM('Historical FS'!J38:J39) -> 0.18436878 | ... Q10: ='Historical FS'!Q31/SUM('Historical FS'!Q38:Q39) -> 0.15681484
B12: Solvency Ratios
B13: Debt/Equity | C13: ='Historical FS'!C40/SUM('Historical FS'!C38:C39) -> 0.041073547 | D13: ='Historical FS'!D40/SUM('Historical FS'!D38:D39) -> 0 | E13: ='Historical FS'!E40/SUM('Historical FS'!E38:E39) -> 0.012584213 | F13: ='Historical FS'!F40/SUM('Historical FS'!F38:F39) -> 0 | G13: ='Historical FS'!G40/SUM('Historical FS'!G38:G39) -> 0 | H13: ='Historical FS'!H40/SUM('Historical FS'!H38:H39) -> 0.021259249 | I13: ='Historical FS'!I40/SUM('Historical FS'!I38:I39) -> 0.024232665 | J13: ='Historical FS'!J40/SUM('Historical FS'!J38:J39) -> 0.028974189 | ... Q13: ='Historical FS'!Q40/SUM('Historical FS'!Q38:Q39) -> 0.0361368
B14: Debt Ratio | C14: ='Historical FS'!C40/'Historical FS'!C57 -> 0.017636572 | D14: ='Historical FS'!D40/'Historical FS'!D57 -> 0 | E14: ='Historical FS'!E40/'Historical FS'!E57 -> 0.0053142949 | F14: ='Historical FS'!F40/'Historical FS'!F57 -> 0 | G14: ='Historical FS'!G40/'Historical FS'!G57 -> 0 | H14: ='Historical FS'!H40/'Historical FS'!H57 -> 0.014793067 | I14: ='Historical FS'!I40/'Historical FS'!I57 -> 0.016681035 | J14: ='Historical FS'!J40/'Historical FS'!J57 -> 0.018907108 | ... Q14: ='Historical FS'!Q40/'Historical FS'!Q57 -> 0.023203494
B15: Interest Coverage Ratio | C15: ='Historical FS'!C21/'Historical FS'!C24 -> 176.68571 | D15: ='Historical FS'!D21/'Historical FS'!D24 -> 262.88462 | E15: ='Historical FS'!E21/'Historical FS'!E24 -> 252.69697 | F15: ='Historical FS'!F21/'Historical FS'!F24 -> 73.245763 | G15: ='Historical FS'!G21/'Historical FS'!G24 -> 83.264957 | H15: ='Historical FS'!H21/'Historical FS'!H24 -> 110.58491 | I15: ='Historical FS'!I21/'Historical FS'!I24 -> 112.80702 | J15: ='Historical FS'!J21/'Historical FS'!J24 -> 40.182635 | ... Q15: ='Historical FS'!Q21/'Historical FS'!Q24 -> 27.480309
B17: Efficiency Ratios
B18: Asset Turnover | C18: ='Historical FS'!C6/'Historical FS'!C57 -> 2.1114224 | D18: ='Historical FS'!D6/'Historical FS'!D57 -> 1.9899787 | E18: ='Historical FS'!E6/'Historical FS'!E57 -> 2.1101508 | F18: ='Historical FS'!F6/'Historical FS'!F57 -> 1.9740485 | G18: ='Historical FS'!G6/'Historical FS'!G57 -> 0.68414315 | H18: ='Historical FS'!H6/'Historical FS'!H57 -> 0.74385159 | I18: ='Historical FS'!I6/'Historical FS'!I57 -> 0.8289886 | J18: ='Historical FS'!J6/'Historical FS'!J57 -> 0.78859458 | ... Q18: ='Historical FS'!Q6/'Historical FS'!Q57 -> 0.67244251
B19: Inventory Turnover | C19: ='Historical FS'!C9/'Historical FS'!C53 -> 7.2361275 | D19: ='Historical FS'!D9/'Historical FS'!D53 -> 7.7429367 | E19: ='Historical FS'!E9/'Historical FS'!E53 -> 8.1806527 | F19: ='Historical FS'!F9/'Historical FS'!F53 -> 7.5280087 | G19: ='Historical FS'!G9/'Historical FS'!G53 -> 7.2956133 | H19: ='Historical FS'!H9/'Historical FS'!H53 -> 7.1069336 | I19: ='Historical FS'!I9/'Historical FS'!I53 -> 8.3582686 | J19: ='Historical FS'!J9/'Historical FS'!J53 -> 8.3722029 | ... Q19: ='Historical FS'!Q9/'Historical FS'!Q53 -> 7.9467407
B20: Receivables Turnover | C20: ='Historical FS'!C6/'Historical FS'!C52 -> 30.564055 | D20: ='Historical FS'!D6/'Historical FS'!D52 -> 27.133588 | E20: ='Historical FS'!E6/'Historical FS'!E52 -> 21.646476 | F20: ='Historical FS'!F6/'Historical FS'!F52 -> 34.624021 | G20: ='Historical FS'!G6/'Historical FS'!G52 -> 26.750853 | H20: ='Historical FS'!H6/'Historical FS'!H52 -> 23.455277 | I20: ='Historical FS'!I6/'Historical FS'!I52 -> 19.675219 | J20: ='Historical FS'!J6/'Historical FS'!J52 -> 20.652653 | ... Q20: ='Historical FS'!Q6/'Historical FS'!Q52 -> 15.978845
B21: Payable Turnover | C21: ='Historical FS'!C9/'Historical FS'!C42 -> 2.9723569 | D21: ='Historical FS'!D9/'Historical FS'!D42 -> 2.7138075 | E21: ='Historical FS'!E9/'Historical FS'!E42 -> 2.9221482 | F21: ='Historical FS'!F9/'Historical FS'!F42 -> 2.7644326 | G21: ='Historical FS'!G9/'Historical FS'!G42 -> 2.9664849 | H21: ='Historical FS'!H9/'Historical FS'!H42 -> 3.2101897 | I21: ='Historical FS'!I9/'Historical FS'!I42 -> 3.711197 | J21: ='Historical FS'!J9/'Historical FS'!J42 -> 3.211234 | ... Q21: ='Historical FS'!Q9/'Historical FS'!Q42 -> 3.0072131
B22: Fixed Asset Turnover | C22: ='Historical FS'!C6/'Historical FS'!C46 -> 7.5044128 | D22: ='Historical FS'!D6/'Historical FS'!D46 -> 7.8500442 | E22: ='Historical FS'!E6/'Historical FS'!E46 -> 8.3372216 | F22: ='Historical FS'!F6/'Historical FS'!F46 -> 7.2609965 | G22: ='Historical FS'!G6/'Historical FS'!G46 -> 0.91417686 | H22: ='Historical FS'!H6/'Historical FS'!H46 -> 1.0189031 | I22: ='Historical FS'!I6/'Historical FS'!I46 -> 1.1500057 | J22: ='Historical FS'!J6/'Historical FS'!J46 -> 1.151682 | ... Q22: ='Historical FS'!Q6/'Historical FS'!Q46 -> 0.90563139
B24: Liquidity Ratios
B25: Current Ratio | I25: ='Historical FS'!I55/'Manual Data'!J37 -> 0.99833721 | J25: ='Historical FS'!J55/'Manual Data'!K37 -> 1.1319202 | K25: ='Historical FS'!K55/'Manual Data'!L37 -> 0.95470763 | L25: ='Historical FS'!L55/'Manual Data'!M37 -> 0.73419513 | M25: =FORECAST($M$3,I25:L25,$I$3:$L$3) -> 0.71265255 | N25: =FORECAST($M$3,J25:M25,$I$3:$L$3) -> 0.51395587 | O25: =FORECAST($M$3,K25:N25,$I$3:$L$3) -> 0.39307923 | P25: =FORECAST($M$3,L25:O25,$I$3:$L$3) -> 0.28317841 | Q25: =FORECAST($M$3,M25:P25,$I$3:$L$3) -> 0.12354986
B26: Quick Ratio | I26: =('Historical FS'!I55-'Historical FS'!I53)/'Manual Data'!J37 -> 0.64491187 | J26: =('Historical FS'!J55-'Historical FS'!J53)/'Manual Data'!K37 -> 0.81962885 | K26: =('Historical FS'!K55-'Historical FS'!K53)/'Manual Data'!L37 -> 0.68773054 | L26: =('Historical FS'!L55-'Historical FS'!L53)/'Manual Data'!M37 -> 0.42620104 | M26: =FORECAST($M$3,I26:L26,$I$3:$L$3) -> 0.44787963 | N26: =FORECAST($M$3,J26:M26,$I$3:$L$3) -> 0.25133004 | O26: =FORECAST($M$3,K26:N26,$I$3:$L$3) -> 0.13152443 | P26: =FORECAST($M$3,L26:O26,$I$3:$L$3) -> 0.044305515 | Q26: =FORECAST($M$3,M26:P26,$I$3:$L$3) -> -0.11373023
B27: Cash Ratio | I27: ='Historical FS'!I54/'Manual Data'!J37 -> 0.38892584 | J27: ='Historical FS'!J54/'Manual Data'!K37 -> 0.58692445 | K27: ='Historical FS'!K54/'Manual Data'!L37 -> 0.45679386 | L27: ='Historical FS'!L54/'Manual Data'!M37 -> 0.20888803 | M27: =FORECAST($M$3,I27:L27,$I$3:$L$3) -> 0.24308074 | N27: =FORECAST($M$3,J27:M27,$I$3:$L$3) -> 0.054208948 | O27: =FORECAST($M$3,K27:N27,$I$3:$L$3) -> -0.05254159 | P27: =FORECAST($M$3,L27:O27,$I$3:$L$3) -> -0.12967875 | Q27: =FORECAST($M$3,M27:P27,$I$3:$L$3) -> -0.2773639
B29: Market Ratios
B30: Earning per Share | C30: ='Historical FS'!C31/'Data Sheet'!B93 -> 19.27644 | D30: ='Historical FS'!D31/'Data Sheet'!C93 -> 21.852622 | E30: ='Historical FS'!E31/'Data Sheet'!D93 -> 26.618007 | F30: ='Historical FS'!F31/'Data Sheet'!E93 -> 28.252033 | G30: ='Historical FS'!G31/'Data Sheet'!F93 -> 29.87317 | H30: ='Historical FS'!H31/'Data Sheet'!G93 -> 36.7254 | I30: ='Historical FS'!I31/'Data Sheet'!H93 -> 40.623936 | J30: ='Historical FS'!J31/'Data Sheet'!I93 -> 40.18982 | ... L30: ='Historical FS'!L31/'Data Sheet'!K93 -> 39.487572 | M30: =FORECAST($M$3,C30:L30,$C$3:$L$3) -> 45.840573 | N30: =FORECAST($M$3,D30:M30,$C$3:$L$3) -> 47.884842 | O30: =FORECAST($M$3,E30:N30,$C$3:$L$3) -> 49.663889 | P30: =FORECAST($M$3,F30:O30,$C$3:$L$3) -> 51.689134 | Q30: =FORECAST($M$3,G30:P30,$C$3:$L$3) -> 53.422917
B31: P/E ratio | C31: ='Data Sheet'!B90/'Ratio Analysis'!C30 -> 45.268212 | D31: ='Data Sheet'!C90/'Ratio Analysis'!D30 -> 58.396197 | E31: ='Data Sheet'!D90/'Ratio Analysis'!E30 -> 61.369358 | F31: ='Data Sheet'!E90/'Ratio Analysis'!F30 -> 77.864486 | G31: ='Data Sheet'!F90/'Ratio Analysis'!G30 -> 77.900002 | H31: ='Data Sheet'!G90/'Ratio Analysis'!H30 -> 53.388118 | I31: ='Data Sheet'!H90/'Ratio Analysis'!I30 -> 60.320103 | J31: ='Data Sheet'!I90/'Ratio Analysis'!J30 -> 53.922611 | ... L31: ='Data Sheet'!K90/'Ratio Analysis'!L30 -> 52.046755 | M31: =FORECAST($M$3,C31:L31,$C$3:$L$3) -> 57.320478 | N31: =FORECAST($M$3,D31:M31,$C$3:$L$3) -> 52.553253 | O31: =FORECAST($M$3,E31:N31,$C$3:$L$3) -> 48.575271 | P31: =FORECAST($M$3,F31:O31,$C$3:$L$3) -> 44.19323 | Q31: =FORECAST($M$3,G31:P31,$C$3:$L$3) -> 43.30499
B32: Book Value per Share | C32: =SUM('Historical FS'!C38:C39)/'Data Sheet'!B93 -> 31.16019 | D32: =SUM('Historical FS'!D38:D39)/'Data Sheet'!C93 -> 33.638254 | E32: =SUM('Historical FS'!E38:E39)/'Data Sheet'!D93 -> 36.342218 | F32: =SUM('Historical FS'!F38:F39)/'Data Sheet'!E93 -> 38.012749 | G32: =SUM('Historical FS'!G38:G39)/'Data Sheet'!F93 -> 202.90262 | H32: =SUM('Historical FS'!H38:H39)/'Data Sheet'!G93 -> 208.80575 | I32: =SUM('Historical FS'!I38:I39)/'Data Sheet'!H93 -> 214.09602 | J32: =SUM('Historical FS'!J38:J39)/'Data Sheet'!I93 -> 217.98604 | ... L32: =SUM('Historical FS'!L38:L39)/'Data Sheet'!K93 -> 207.43531 | M32: =FORECAST($M$3,C32:L32,$C$3:$L$3) -> 282.20645 | N32: =FORECAST($M$3,D32:M32,$C$3:$L$3) -> 310.0307 | O32: =FORECAST($M$3,E32:N32,$C$3:$L$3) -> 332.89261 | P32: =FORECAST($M$3,F32:O32,$C$3:$L$3) -> 347.20776 | Q32: =FORECAST($M$3,G32:P32,$C$3:$L$3) -> 347.92603
B34: Operating Cycle Ratios
B35: (in days)
B36: Inventory Days | C36: =365/C19 -> 50.441344 | D36: =365/D19 -> 47.139737 | E36: =365/E19 -> 44.617467 | F36: =365/F19 -> 48.485598 | G36: =365/G19 -> 50.030064 | H36: =365/H19 -> 51.358296 | I36: =365/I19 -> 43.669331 | J36: =365/J19 -> 43.59665 | ... L36: =365/L19 -> 47.900499 | M36: =FORECAST($M$3,C36:L36,$C$3:$L$3) -> 46.262294 | N36: =FORECAST($M$3,D36:M36,$C$3:$L$3) -> 46.554475 | O36: =FORECAST($M$3,E36:N36,$C$3:$L$3) -> 46.360877 | P36: =FORECAST($M$3,F36:O36,$C$3:$L$3) -> 45.456326 | Q36: =FORECAST($M$3,G36:P36,$C$3:$L$3) -> 45.106549
B37: Receivable Days | C37: =365/C20 -> 11.942133 | D37: =365/D20 -> 13.451962 | E37: =365/E20 -> 16.861867 | F37: =365/F20 -> 10.541814 | G37: =365/G20 -> 13.644425 | H37: =365/H20 -> 15.56153 | I37: =365/I20 -> 18.551255 | J37: =365/J20 -> 17.673275 | ... L37: =365/L20 -> 19.130964 | M37: =FORECAST($M$3,C37:L37,$C$3:$L$3) -> 21.328641 | N37: =FORECAST($M$3,D37:M37,$C$3:$L$3) -> 22.372934 | O37: =FORECAST($M$3,E37:N37,$C$3:$L$3) -> 23.61056 | P37: =FORECAST($M$3,F37:O37,$C$3:$L$3) -> 25.658048 | Q37: =FORECAST($M$3,G37:P37,$C$3:$L$3) -> 26.389474
B38: Payable Days | C38: =365/C21 -> 122.79817 | D38: =365/D21 -> 134.49738 | E38: =365/E21 -> 124.90811 | F38: =365/F21 -> 132.03433 | G38: =365/G21 -> 123.04125 | H38: =365/H21 -> 113.70045 | I38: =365/I21 -> 98.351017 | J38: =365/J21 -> 113.66347 | ... L38: =365/L21 -> 133.27921 | M38: =FORECAST($M$3,C38:L38,$C$3:$L$3) -> 116.6044 | N38: =FORECAST($M$3,D38:M38,$C$3:$L$3) -> 114.75402 | O38: =FORECAST($M$3,E38:N38,$C$3:$L$3) -> 115.69433 | P38: =FORECAST($M$3,F38:O38,$C$3:$L$3) -> 115.7697 | Q38: =FORECAST($M$3,G38:P38,$C$3:$L$3) -> 118.39404
B40: Cash Conversion Cycle | C40: =SUM(C36:C37)-C38 -> -60.414696 | D40: =SUM(D36:D37)-D38 -> -73.90568 | E40: =SUM(E36:E37)-E38 -> -63.428772 | F40: =SUM(F36:F37)-F38 -> -73.006913 | G40: =SUM(G36:G37)-G38 -> -59.366758 | H40: =SUM(H36:H37)-H38 -> -46.780621 | I40: =SUM(I36:I37)-I38 -> -36.130432 | J40: =SUM(J36:J37)-J38 -> -52.393545 | ... L40: =SUM(L36:L37)-L38 -> -66.247749 | M40: =FORECAST($M$3,C40:L40,$C$3:$L$3) -> -49.013466 | N40: =FORECAST($M$3,D40:M40,$C$3:$L$3) -> -45.826607 | O40: =FORECAST($M$3,E40:N40,$C$3:$L$3) -> -45.722896 | P40: =FORECAST($M$3,F40:O40,$C$3:$L$3) -> -44.655326 | Q40: =FORECAST($M$3,G40:P40,$C$3:$L$3) -> -46.898017

Sheet DCF Modelling
B2: ="WACC Calculation for "& 'Data Sheet'!B1 -> WACC Calculation for HINDUSTAN UNILEVER LTD | G2: ="Discounted Cash flow for "&'Data Sheet'!B1 -> Discounted Cash flow for HINDUSTAN UNILEVER LTD
H3: 1 | I3: 2 | J3: 3 | K3: 4 | L3: 5 | M3: 6 | N3: 7 | O3: 8 | P3: 9 | Q3: 10
B4: Equity | E4: =510848 -> 510848 | G4: EBIT | H4: ='Historical FS'!C21 -> 6184 | I4: ='Historical FS'!D21 -> 6835 | J4: ='Historical FS'!E21 -> 8339 | K4: ='Historical FS'!F21 -> 8643 | L4: ='Historical FS'!G21 -> 9742 | M4: ='Historical FS'!H21 -> 11722 | N4: ='Historical FS'!I21 -> 12860 | O4: ='Historical FS'!J21 -> 13421 | ... Q4: ='Historical FS'!L21 -> 12848
B5: Debt | E5: 1478 | G5: Tax Rate | H5: 0.2541 | I5: 0.2541 | J5: 0.2541 | K5: 0.2541 | L5: 0.2541 | M5: 0.2541 | N5: 0.2541 | O5: 0.2541 | P5: 0.2541 | Q5: 0.2541
B6: Rf | E6: 0.0677 | G6: Depricitaion | H6: ='Historical FS'!C19 -> 432 | I6: ='Historical FS'!D19 -> 520 | J6: ='Historical FS'!E19 -> 565 | K6: ='Historical FS'!F19 -> 1002 | L6: ='Historical FS'!G19 -> 1074 | M6: ='Historical FS'!H19 -> 1091 | N6: ='Historical FS'!I19 -> 1137 | O6: ='Historical FS'!J19 -> 1216 | ... Q6: ='Historical FS'!L19 -> 1333
B7: Rm | E7: =E6+E8 -> 0.1095 | G7: Capex | H7: ='Historical FS'!C77 -> -1113 | I7: ='Historical FS'!D77 -> -895 | J7: ='Historical FS'!E77 -> -767 | K7: ='Historical FS'!F77 -> -862 | L7: ='Historical FS'!G77 -> -4163 | M7: ='Historical FS'!H77 -> -1228 | N7: ='Historical FS'!I77 -> -1192 | O7: ='Historical FS'!J77 -> -1477 | ... Q7: ='Historical FS'!L77 -> -1361
B8: ERP | E8: 0.0418 | G8: Non-Cash WC | H8: =SUM('Historical FS'!C52:C53)-'Historical FS'!C42 -> -2560 | I8: =SUM('Historical FS'!D52:D53)-'Historical FS'!D42 -> -3347 | J8: =SUM('Historical FS'!E52:E53)-'Historical FS'!E42 -> -2816 | K8: =SUM('Historical FS'!F52:F53)-'Historical FS'!F42 -> -3619 | L8: =SUM('Historical FS'!G52:G53)-'Historical FS'!G42 -> -3465 | M8: =SUM('Historical FS'!H52:H53)-'Historical FS'!H42 -> -2736 | N8: =SUM('Historical FS'!I52:I53)-'Historical FS'!I42 -> -2244 | O8: =SUM('Historical FS'!J52:J53)-'Historical FS'!J42 -> -3467 | ... Q8: =SUM('Historical FS'!L52:L53)-'Historical FS'!L42 -> -5157
B9: Beta | E9: 0.78
B10: Tax Rate | E10: ='Historical FS'!L29/'Historical FS'!L26 -> 0.25406014 | G10: FCF | H10: =H4*(1-H5)+H6+H7+H8 -> 1371.6456 | I10: =I4*(1-I5)+I6+I7+I8 -> 1376.2265 | J10: =J4*(1-J5)+J6+J7+J8 -> 3202.0601 | K10: =K4*(1-K5)+K6+K7+K8 -> 2967.8137 | L10: =L4*(1-L5)+L6+L7+L8 -> 712.5578 | M10: =M4*(1-M5)+M6+M7+M8 -> 5870.4398 | N10: =N4*(1-N5)+N6+N7+N8 -> 7293.274 | O10: =O4*(1-O5)+O6+O7+O8 -> 6282.7239 | ... Q10: =Q4*(1-Q5)+Q6+Q7+Q8 -> 4398.3232
B12: kd | E12: ='Historical FS'!L81/'DCF Modelling'!E5 -> 0.28958051 | G12: Growth rate | H12: 0.04
B13: dw | E13: =E5/SUM(E4:E5) -> 0.0028848819 | G13: WACC | H13: =E17 -> 0.1006378
B14: ew | E14: =E4/SUM(E4:E5) -> 0.99711512 | G14: Terminal Value | H14: =(Q10*(1+H12))/(H13-H12) -> 75435.724
B15: ke | E15: =E6+(E7-E6)*E9 -> 0.100304
G16: Discount Factor | H16: =1/((1+$H$13)^H3) -> 0.90856411 | I16: =1/((1+$H$13)^I3) -> 0.82548874 | J16: =1/((1+$H$13)^J3) -> 0.75000944 | K16: =1/((1+$H$13)^K3) -> 0.68143166 | L16: =1/((1+$H$13)^L3) -> 0.61912435 | M16: =1/((1+$H$13)^M3) -> 0.56251416 | N16: =1/((1+$H$13)^N3) -> 0.51108018 | O16: =1/((1+$H$13)^O3) -> 0.46434911 | ... Q16: =1/((1+$H$13)^Q3) -> 0.38331496
B17: wacc | E17: =(E14*E15)+(E12*E13)*(1-E10) -> 0.1006378 | G17: Pv of FCF | H17: =H10*H16 -> 1246.228 | I17: =I10*I16 -> 1136.0595 | J17: =J10*J16 -> 2401.5753 | K17: =K10*K16 -> 2022.3622 | L17: =L10*L16 -> 441.16189 | M17: =M10*M16 -> 3302.2055 | N17: =N10*N16 -> 3727.4478 | O17: =O10*O16 -> 2917.3772 | ... Q17: =Q10*Q16 -> 1685.9431
G18: PV of Tv | Q18: =H14*Q16 -> 28915.642
G20: Enterprise Value | H20: =SUM(H17:Q18) -> 50639.189
G21: Equity Value | H21: =H20-'Historical FS'!C40-'Historical FS'!C54 -> 48534.189
G23: No. of Shares | H23: ='Data Sheet'!K93/10 -> 23.496
G24: Share Price | H24: =H21/H23 -> 2065.6362

Sheet Comp Analysis
B2: ="Comp Analysis for "&'Data Sheet'!B1 -> Comp Analysis for HINDUSTAN UNILEVER LTD
C3: Market Data | I3: Financials | Q3: Valuation
B4: Name | C4: Share price | D4: Share Outstanding | E4: Market Cap | F4: Net Debt | G4: Enterprise Value | I4: Revenue | J4: EBITDA | K4: EBIT | L4: Net Income | O4: EV/Revenue | Q4: EV/EBITDA | S4: P/E
B6: Hind. Unilever Ltd | C6: 2174.2 | D6: 234.96 | E6: =C6*D6 -> 510850.03 | F6: ='Historical FS'!K40-'Historical FS'!K54 -> -5906 | G6: =E6+F6 -> 504944.03 | I6: ='Historical FS'!L6 -> 64468 | J6: ='Historical FS'!L16 -> 14181 | K6: ='Historical FS'!L21 -> 12848 | L6: ='Historical FS'!L31 -> 9278 | O6: =G6/I6 -> 7.8324755 | Q6: =G6/J6 -> 35.607082 | S6: =E6/L6 -> 55.060361
B7: ITC | C7: 290 | D7: 1252.95 | E7: =C7*D7 -> 363355.5 | F7: -3727 | G7: =E7+F7 -> 359628.5 | I7: 78868.4 | J7: 28829.09 | K7: 28118.56 | L7: 20689.47 | O7: =G7/I7 -> 4.5598554 | Q7: =G7/J7 -> 12.474501 | S7: =E7/L7 -> 17.56234
B8: Hindustan Foods | C8: 559.75 | D8: 12.12 | E8: =C8*D8 -> 6784.17 | F8: 808 | G8: =E8+F8 -> 7592.17 | I8: 4251.04 | J8: 372.02 | K8: 281.94 | L8: 149.03 | O8: =G8/I8 -> 1.7859559 | Q8: =G8/J8 -> 20.407962 | S8: =E8/L8 -> 45.522177
B9: Godavari Bioref. | C9: 280.85 | D9: 5.12 | E9: =C9*D9 -> 1437.952 | F9: 459 | G9: =E9+F9 -> 1896.952 | I9: 1987.94 | J9: 108.19 | K9: 53.7 | L9: 3.53 | O9: =G9/I9 -> 0.95423001 | Q9: =G9/J9 -> 17.533524 | S9: =E9/L9 -> 407.35184
B11: High | O11: =MAX(O6:O9) -> 7.8324755 | Q11: =MAX(Q6:Q9) -> 35.607082 | S11: =MAX(S6:S9) -> 407.35184
B12: Third Quartile | O12: =QUARTILE(O6:O9,3) -> 5.3780104 | Q12: =QUARTILE(Q6:Q9,3) -> 24.207742 | S12: =QUARTILE(S6:S9,3) -> 143.13323
B13: Median | O13: =MEDIAN(O6:O9) -> 3.1729057 | Q13: =MEDIAN(Q6:Q9) -> 18.970743 | S13: =MEDIAN(S6:S9) -> 50.291269
B14: Average | O14: =AVERAGE(O6:O9) -> 3.7831292 | Q14: =AVERAGE(Q6:Q9) -> 21.505767 | S14: =AVERAGE(S6:S9) -> 131.37418
B15: First Quartile | O15: =QUARTILE(O6:O9,1) -> 1.5780244 | Q15: =QUARTILE(Q6:Q9,1) -> 16.268768 | S15: =QUARTILE(S6:S9,1) -> 38.532217
B16: Low | O16: =MIN(O6:O9) -> 0.95423001 | Q16: =MIN(Q6:Q9) -> 12.474501 | S16: =MIN(S6:S9) -> 17.56234
B19: =B6 -> Hind. Unilever Ltd | O19: EV/Revenue | Q19: EV/EBITDA | S19: P/E
B20: Implied Enterprise Value | O20: =$I$6*O13 -> 204550.88 | Q20: =J6*Q13 -> 269024.11 | S20: =S22+S21 -> 460696.39
B21: Net Debt | O21: =$F$6 -> -5906 | Q21: =$F$6 -> -5906 | S21: =$F$6 -> -5906
B22: Implied Market Value | O22: =O20-O21 -> 210456.88 | Q22: =Q20-Q21 -> 274930.11 | S22: =S13*L6 -> 466602.39
B23: Shares Outstanding | O23: =$D$6 -> 234.96 | Q23: =$D$6 -> 234.96 | S23: =$D$6 -> 234.96
B24: Implied Value per Share | O24: =O22/O23 -> 895.71366 | Q24: =Q22/Q23 -> 1170.1145 | S24: =S22/S23 -> 1985.8801
O25: =IF($O$24>C6,"Undervalued","Overvalued") -> Overvalued | Q25: =IF($O$24>E6,"Undervalued","Overvalued") -> Overvalued | S25: =IF($O$24>G6,"Undervalued","Overvalued") -> Overvalued

Sheet Common Size Statement
B2: ="Common Size Income Statment for "&'Data Sheet'!B1 -> Common Size Income Statment for HINDUSTAN UNILEVER LTD | N2: ="Common Size Income Statment for "&'Comparables Data'!A1 -> Common Size Income Statment for ITC LTD | Z2: ="Common Size Income Statment for "&'Comparables Data'!O1 -> Common Size Income Statment for HINDUSTAN FOODS LTD | AJ2: ="Common Size Income Statment for "&'Comparables Data'!Z1 -> Common Size Income Statment for GODAVARI BIOREFINERIES LTD
B3: Year | C3: ='Historical FS'!C3 -> 42825 | D3: ='Historical FS'!D3 -> 43190 | E3: ='Historical FS'!E3 -> 43555 | F3: ='Historical FS'!F3 -> 43921 | G3: ='Historical FS'!G3 -> 44286 | H3: ='Historical FS'!H3 -> 44651 | I3: ='Historical FS'!I3 -> 45016 | J3: ='Historical FS'!J3 -> 45382 | ... L3: ='Historical FS'!L3 -> 46112 | N3: Year | O3: =C3 -> 42825 | P3: =D3 -> 43190 | Q3: =E3 -> 43555 | R3: =F3 -> 43921 | S3: =G3 -> 44286 | T3: =H3 -> 44651 | U3: =I3 -> 45016 | V3: =J3 -> 45382 | ... X3: =L3 -> 46112 | Z3: Year | AA3: =Q3 -> 43555 | AB3: =R3 -> 43921 | AC3: =S3 -> 44286 | AD3: =T3 -> 44651 | AE3: =U3 -> 45016 | AF3: =V3 -> 45382 | AG3: =W3 -> 45747 | AH3: =X3 -> 46112 | AJ3: Year | AK3: =AB3 -> 43921 | AL3: =AC3 -> 44286 | AM3: =AD3 -> 44651 | AN3: =AE3 -> 45016 | AO3: =AF3 -> 45382 | AP3: =AG3 -> 45747 | AQ3: =AH3 -> 46112
B4: ='Data Sheet'!A17 -> Sales | C4: ='Data Sheet'!B17/'Data Sheet'!$B$17 -> 1 | D4: ='Data Sheet'!C17/'Data Sheet'!$C$17 -> 1 | E4: ='Data Sheet'!D17/'Data Sheet'!$D$17 -> 1 | F4: ='Data Sheet'!E17/'Data Sheet'!$E$17 -> 1 | G4: ='Data Sheet'!F17/'Data Sheet'!$F$17 -> 1 | H4: ='Data Sheet'!G17/'Data Sheet'!$G$17 -> 1 | I4: ='Data Sheet'!H17/'Data Sheet'!$H$17 -> 1 | J4: ='Data Sheet'!I17/'Data Sheet'!$I$17 -> 1 | K4: ='Data Sheet'!J17/'Data Sheet'!$J$17 -> 1 | L4: ='Data Sheet'!K17/'Data Sheet'!$K$17 -> 1 | N4: ='Comparables Data'!A3 -> Sales | O4: ='Comparables Data'!B3/'Comparables Data'!B$3 -> 1 | P4: ='Comparables Data'!C3/'Comparables Data'!C$3 -> 1 | Q4: ='Comparables Data'!D3/'Comparables Data'!D$3 -> 1 | R4: ='Comparables Data'!E3/'Comparables Data'!E$3 -> 1 | S4: ='Comparables Data'!F3/'Comparables Data'!F$3 -> 1 | T4: ='Comparables Data'!G3/'Comparables Data'!G$3 -> 1 | U4: ='Comparables Data'!H3/'Comparables Data'!H$3 -> 1 | V4: ='Comparables Data'!I3/'Comparables Data'!I$3 -> 1 | ... X4: ='Comparables Data'!K3/'Comparables Data'!K$3 -> 1 | Z4: ='Comparables Data'!M3 -> Sales | AA4: ='Comparables Data'!P3/'Comparables Data'!P$3 -> 1 | AB4: ='Comparables Data'!Q3/'Comparables Data'!Q$3 -> 1 | AC4: ='Comparables Data'!R3/'Comparables Data'!R$3 -> 1 | AD4: ='Comparables Data'!S3/'Comparables Data'!S$3 -> 1 | AE4: ='Comparables Data'!T3/'Comparables Data'!T$3 -> 1 | AF4: ='Comparables Data'!U3/'Comparables Data'!U$3 -> 1 | AG4: ='Comparables Data'!V3/'Comparables Data'!V$3 -> 1 | AH4: ='Comparables Data'!W3/'Comparables Data'!W$3 -> 1 | AJ4: ='Comparables Data'!Y3 -> Sales | AK4: ='Comparables Data'!AC3/'Comparables Data'!AC$3 -> 1 | AL4: ='Comparables Data'!AD3/'Comparables Data'!AD$3 -> 1 | AM4: ='Comparables Data'!AE3/'Comparables Data'!AE$3 -> 1 | AN4: ='Comparables Data'!AF3/'Comparables Data'!AF$3 -> 1 | AO4: ='Comparables Data'!AG3/'Comparables Data'!AG$3 -> 1 | AP4: ='Comparables Data'!AH3/'Comparables Data'!AH$3 -> 1 | AQ4: ='Comparables Data'!AI3/'Comparables Data'!AI$3 -> 1
B5: ='Data Sheet'!A18 -> Raw Material Cost | C5: ='Data Sheet'!B18/'Data Sheet'!$B$17 -> 0.41028888 | D5: ='Data Sheet'!C18/'Data Sheet'!$C$17 -> 0.400422 | E5: ='Data Sheet'!D18/'Data Sheet'!$D$17 -> 0.4030781 | F5: ='Data Sheet'!E18/'Data Sheet'!$E$17 -> 0.39456552 | G5: ='Data Sheet'!F18/'Data Sheet'!$F$17 -> 0.42827677 | H5: ='Data Sheet'!G18/'Data Sheet'!$G$17 -> 0.43608664 | I5: ='Data Sheet'!H18/'Data Sheet'!$H$17 -> 0.46924728 | J5: ='Data Sheet'!I18/'Data Sheet'!$I$17 -> 0.4333398 | K5: ='Data Sheet'!J18/'Data Sheet'!$J$17 -> 0.43376598 | L5: ='Data Sheet'!K18/'Data Sheet'!$K$17 -> 0.45228641 | N5: ='Comparables Data'!A4 -> Raw Material Cost | O5: ='Comparables Data'!B4/'Comparables Data'!B$3 -> 0.36140887 | P5: ='Comparables Data'!C4/'Comparables Data'!C$3 -> 0.3412677 | Q5: ='Comparables Data'!D4/'Comparables Data'!D$3 -> 0.36457743 | R5: ='Comparables Data'!E4/'Comparables Data'!E$3 -> 0.36544727 | S5: ='Comparables Data'!F4/'Comparables Data'!F$3 -> 0.42179833 | T5: ='Comparables Data'!G4/'Comparables Data'!G$3 -> 0.44638924 | U5: ='Comparables Data'!H4/'Comparables Data'!H$3 -> 0.41405473 | V5: ='Comparables Data'!I4/'Comparables Data'!I$3 -> 0.4025878 | ... X5: ='Comparables Data'!K4/'Comparables Data'!K$3 -> 0.44502412 | Z5: ='Comparables Data'!M4 -> Raw Material Cost | AA5: ='Comparables Data'!P4/'Comparables Data'!P$3 -> 0.69382611 | AB5: ='Comparables Data'!Q4/'Comparables Data'!Q$3 -> 0.74470786 | AC5: ='Comparables Data'!R4/'Comparables Data'!R$3 -> 0.76814657 | AD5: ='Comparables Data'!S4/'Comparables Data'!S$3 -> 0.77290819 | AE5: ='Comparables Data'!T4/'Comparables Data'!T$3 -> 0.69152044 | AF5: ='Comparables Data'!U4/'Comparables Data'!U$3 -> 0.68803976 | AG5: ='Comparables Data'!V4/'Comparables Data'!V$3 -> 0.64658089 | AH5: ='Comparables Data'!W4/'Comparables Data'!W$3 -> 0.78795307 | AJ5: ='Comparables Data'!Y4 -> Raw Material Cost | AK5: ='Comparables Data'!AC4/'Comparables Data'!AC$3 -> 0.60972484 | AL5: ='Comparables Data'!AD4/'Comparables Data'!AD$3 -> 0.71183939 | AM5: ='Comparables Data'!AE4/'Comparables Data'!AE$3 -> 0.72255086 | AN5: ='Comparables Data'!AF4/'Comparables Data'!AF$3 -> 0.65702416 | AO5: ='Comparables Data'!AG4/'Comparables Data'!AG$3 -> 0.91627882 | AP5: ='Comparables Data'!AH4/'Comparables Data'!AH$3 -> 0.6740008 | AQ5: ='Comparables Data'!AI4/'Comparables Data'!AI$3 -> 0.76358944
B6: ='Data Sheet'!A19 -> Change in Inventory | C6: ='Data Sheet'!B19/'Data Sheet'!$B$17 -> -0.0043423195 | D6: ='Data Sheet'!C19/'Data Sheet'!$C$17 -> 0.0020256014 | E6: ='Data Sheet'!D19/'Data Sheet'!$D$17 -> -0.00030526584 | F6: ='Data Sheet'!E19/'Data Sheet'!$E$17 -> 0.0027147274 | G6: ='Data Sheet'!F19/'Data Sheet'!$F$17 -> 0.0086118908 | H6: ='Data Sheet'!G19/'Data Sheet'!$G$17 -> 0.00041947908 | I6: ='Data Sheet'!H19/'Data Sheet'!$H$17 -> 0.0012380324 | J6: ='Data Sheet'!I19/'Data Sheet'!$I$17 -> 0.00017771746 | K6: ='Data Sheet'!J19/'Data Sheet'!$J$17 -> 0.0020382207 | L6: ='Data Sheet'!K19/'Data Sheet'!$K$17 -> 0.0066544642 | N6: ='Comparables Data'!A5 -> Change in Inventory | O6: ='Comparables Data'!B5/'Comparables Data'!B$3 -> -0.013855582 | P6: ='Comparables Data'!C5/'Comparables Data'!C$3 -> -0.023654432 | Q6: ='Comparables Data'!D5/'Comparables Data'!D$3 -> 0.0042033878 | R6: ='Comparables Data'!E5/'Comparables Data'!E$3 -> 0.014236946 | S6: ='Comparables Data'!F5/'Comparables Data'!F$3 -> 0.013099947 | T6: ='Comparables Data'!G5/'Comparables Data'!G$3 -> 0.011311818 | U6: ='Comparables Data'!H5/'Comparables Data'!H$3 -> 0.0050563297 | V6: ='Comparables Data'!I5/'Comparables Data'!I$3 -> 0.0054138009 | ... X6: ='Comparables Data'!K5/'Comparables Data'!K$3 -> 0.032338173 | Z6: ='Comparables Data'!M5 -> Change in Inventory | AA6: ='Comparables Data'!P5/'Comparables Data'!P$3 -> 0.014636824 | AB6: ='Comparables Data'!Q5/'Comparables Data'!Q$3 -> 0.039396295 | AC6: ='Comparables Data'!R5/'Comparables Data'!R$3 -> 0.00667941 | AD6: ='Comparables Data'!S5/'Comparables Data'!S$3 -> 0.01749424 | AE6: ='Comparables Data'!T5/'Comparables Data'!T$3 -> 0.0054654694 | AF6: ='Comparables Data'!U5/'Comparables Data'!U$3 -> 0.021719165 | AG6: ='Comparables Data'!V5/'Comparables Data'!V$3 -> 0.01060493 | AH6: ='Comparables Data'!W5/'Comparables Data'!W$3 -> 0.0051399187 | AJ6: ='Comparables Data'!Y5 -> Change in Inventory | AK6: ='Comparables Data'!AC5/'Comparables Data'!AC$3 -> -0.1248398 | AL6: ='Comparables Data'!AD5/'Comparables Data'!AD$3 -> 0.024503143 | AM6: ='Comparables Data'!AE5/'Comparables Data'!AE$3 -> 0.024395975 | AN6: ='Comparables Data'!AF5/'Comparables Data'!AF$3 -> -0.029935126 | AO6: ='Comparables Data'!AG5/'Comparables Data'!AG$3 -> 0.21843633 | AP6: ='Comparables Data'!AH5/'Comparables Data'!AH$3 -> -0.066627456 | AQ6: ='Comparables Data'!AI5/'Comparables Data'!AI$3 -> 0.045957121
B7: ='Data Sheet'!A20 -> Power and Fuel | C7: ='Data Sheet'!B20/'Data Sheet'!$B$17 -> 0.008895724 | D7: ='Data Sheet'!C20/'Data Sheet'!$C$17 -> 0.0082993389 | E7: ='Data Sheet'!D20/'Data Sheet'!$D$17 -> 0.0078351564 | F7: ='Data Sheet'!E20/'Data Sheet'!$E$17 -> 0.0075157731 | G7: ='Data Sheet'!F20/'Data Sheet'!$F$17 -> 0.0072084715 | H7: ='Data Sheet'!G20/'Data Sheet'!$G$17 -> 0.0060633795 | I7: ='Data Sheet'!H20/'Data Sheet'!$H$17 -> 0.0063387257 | J7: ='Data Sheet'!I20/'Data Sheet'!$I$17 -> 0.0072056353 | K7: ='Data Sheet'!J20/'Data Sheet'!$J$17 -> 0.0065712236 | L7: ='Data Sheet'!K20/'Data Sheet'!$K$17 -> 0.0066079295 | N7: ='Comparables Data'!A6 -> Power and Fuel | O7: ='Comparables Data'!B6/'Comparables Data'!B$3 -> 0.013662913 | P7: ='Comparables Data'!C6/'Comparables Data'!C$3 -> 0.015040643 | Q7: ='Comparables Data'!D6/'Comparables Data'!D$3 -> 0.01544759 | R7: ='Comparables Data'!E6/'Comparables Data'!E$3 -> 0.015810617 | S7: ='Comparables Data'!F6/'Comparables Data'!F$3 -> 0.014202116 | T7: ='Comparables Data'!G6/'Comparables Data'!G$3 -> 0.01467189 | U7: ='Comparables Data'!H6/'Comparables Data'!H$3 -> 0.017376718 | V7: ='Comparables Data'!I6/'Comparables Data'!I$3 -> 0.014027275 | ... X7: ='Comparables Data'!K6/'Comparables Data'!K$3 -> 0 | Z7: ='Comparables Data'!M6 -> Power and Fuel | AA7: ='Comparables Data'!P6/'Comparables Data'!P$3 -> 0.017930109 | AB7: ='Comparables Data'!Q6/'Comparables Data'!Q$3 -> 0.012488664 | AC7: ='Comparables Data'!R6/'Comparables Data'!R$3 -> 0.009593537 | AD7: ='Comparables Data'!S6/'Comparables Data'!S$3 -> 0.010112249 | AE7: ='Comparables Data'!T6/'Comparables Data'!T$3 -> 0.012162594 | AF7: ='Comparables Data'!U6/'Comparables Data'!U$3 -> 0.014491544 | AG7: ='Comparables Data'!V6/'Comparables Data'!V$3 -> 0.017399941 | AH7: ='Comparables Data'!W6/'Comparables Data'!W$3 -> 0 | AJ7: ='Comparables Data'!Y6 -> Power and Fuel | AK7: ='Comparables Data'!AC6/'Comparables Data'!AC$3 -> 0.053969777 | AL7: ='Comparables Data'!AD6/'Comparables Data'!AD$3 -> 0.054473823 | AM7: ='Comparables Data'!AE6/'Comparables Data'!AE$3 -> 0.058590285 | AN7: ='Comparables Data'!AF6/'Comparables Data'!AF$3 -> 0.072547141 | AO7: ='Comparables Data'!AG6/'Comparables Data'!AG$3 -> 0.047507811 | AP7: ='Comparables Data'!AH6/'Comparables Data'!AH$3 -> 0.038358508 | AQ7: ='Comparables Data'!AI6/'Comparables Data'!AI$3 -> 0
B8: ='Data Sheet'!A21 -> Other Mfr. Exp | C8: ='Data Sheet'!B21/'Data Sheet'!$B$17 -> 0.087057475 | D8: ='Data Sheet'!C21/'Data Sheet'!$C$17 -> 0.08434379 | E8: ='Data Sheet'!D21/'Data Sheet'!$D$17 -> 0.077359451 | F8: ='Data Sheet'!E21/'Data Sheet'!$E$17 -> 0.073046276 | G8: ='Data Sheet'!F21/'Data Sheet'!$F$17 -> 0.060984945 | H8: ='Data Sheet'!G21/'Data Sheet'!$G$17 -> 0.063951493 | I8: ='Data Sheet'!H21/'Data Sheet'!$H$17 -> 0.062578409 | J8: ='Data Sheet'!I21/'Data Sheet'!$I$17 -> 0.05468851 | K8: ='Data Sheet'!J21/'Data Sheet'!$J$17 -> 0.060119358 | L8: ='Data Sheet'!K21/'Data Sheet'!$K$17 -> 0.051250233 | N8: ='Comparables Data'!A7 -> Other Mfr. Exp | O8: ='Comparables Data'!B7/'Comparables Data'!B$3 -> 0.039373264 | P8: ='Comparables Data'!C7/'Comparables Data'!C$3 -> 0.039071609 | Q8: ='Comparables Data'!D7/'Comparables Data'!D$3 -> 0.038705549 | R8: ='Comparables Data'!E7/'Comparables Data'!E$3 -> 0.038638973 | S8: ='Comparables Data'!F7/'Comparables Data'!F$3 -> 0.032222131 | T8: ='Comparables Data'!G7/'Comparables Data'!G$3 -> 0.031126792 | U8: ='Comparables Data'!H7/'Comparables Data'!H$3 -> 0.032823348 | V8: ='Comparables Data'!I7/'Comparables Data'!I$3 -> 0.032146292 | ... X8: ='Comparables Data'!K7/'Comparables Data'!K$3 -> 0 | Z8: ='Comparables Data'!M7 -> Other Mfr. Exp | AA8: ='Comparables Data'!P7/'Comparables Data'!P$3 -> 0.16541644 | AB8: ='Comparables Data'!Q7/'Comparables Data'!Q$3 -> 0.15750745 | AC8: ='Comparables Data'!R7/'Comparables Data'!R$3 -> 0.13179933 | AD8: ='Comparables Data'!S7/'Comparables Data'!S$3 -> 0.14506152 | AE8: ='Comparables Data'!T7/'Comparables Data'!T$3 -> 0.20172971 | AF8: ='Comparables Data'!U7/'Comparables Data'!U$3 -> 0.19254658 | AG8: ='Comparables Data'!V7/'Comparables Data'!V$3 -> 0.18143127 | AH8: ='Comparables Data'!W7/'Comparables Data'!W$3 -> 0 | AJ8: ='Comparables Data'!Y7 -> Other Mfr. Exp | AK8: ='Comparables Data'!AC7/'Comparables Data'!AC$3 -> 0.045711544 | AL8: ='Comparables Data'!AD7/'Comparables Data'!AD$3 -> 0.04976043 | AM8: ='Comparables Data'!AE7/'Comparables Data'!AE$3 -> 0.053655872 | AN8: ='Comparables Data'!AF7/'Comparables Data'!AF$3 -> 0.052479538 | AO8: ='Comparables Data'!AG7/'Comparables Data'!AG$3 -> 0.058387236 | AP8: ='Comparables Data'!AH7/'Comparables Data'!AH$3 -> 0.052955487 | AQ8: ='Comparables Data'!AI7/'Comparables Data'!AI$3 -> 0
B9: ='Data Sheet'!A22 -> Employee Cost | C9: ='Data Sheet'!B22/'Data Sheet'!$B$17 -> 0.052560159 | D9: ='Data Sheet'!C22/'Data Sheet'!$C$17 -> 0.052328035 | E9: ='Data Sheet'!D22/'Data Sheet'!$D$17 -> 0.047697787 | F9: ='Data Sheet'!E22/'Data Sheet'!$E$17 -> 0.045748184 | G9: ='Data Sheet'!F22/'Data Sheet'!$F$17 -> 0.050140342 | H9: ='Data Sheet'!G22/'Data Sheet'!$G$17 -> 0.048526103 | I9: ='Data Sheet'!H22/'Data Sheet'!$H$17 -> 0.047111258 | J9: ='Data Sheet'!I22/'Data Sheet'!$I$17 -> 0.048613804 | K9: ='Data Sheet'!J22/'Data Sheet'!$J$17 -> 0.04813462 | L9: ='Data Sheet'!K22/'Data Sheet'!$K$17 -> 0.04924924 | N9: ='Comparables Data'!A8 -> Employee Cost | O9: ='Comparables Data'!B8/'Comparables Data'!B$3 -> 0.084917788 | P9: ='Comparables Data'!C8/'Comparables Data'!C$3 -> 0.086559074 | Q9: ='Comparables Data'!D8/'Comparables Data'!D$3 -> 0.086427727 | R9: ='Comparables Data'!E8/'Comparables Data'!E$3 -> 0.086980969 | S9: ='Comparables Data'!F8/'Comparables Data'!F$3 -> 0.090612283 | T9: ='Comparables Data'!G8/'Comparables Data'!G$3 -> 0.080642874 | U9: ='Comparables Data'!H8/'Comparables Data'!H$3 -> 0.080884073 | V9: ='Comparables Data'!I8/'Comparables Data'!I$3 -> 0.081677779 | ... X9: ='Comparables Data'!K8/'Comparables Data'!K$3 -> 0.085985008 | Z9: ='Comparables Data'!M8 -> Employee Cost | AA9: ='Comparables Data'!P8/'Comparables Data'!P$3 -> 0.037689821 | AB9: ='Comparables Data'!Q8/'Comparables Data'!Q$3 -> 0.031493717 | AC9: ='Comparables Data'!R8/'Comparables Data'!R$3 -> 0.022130054 | AD9: ='Comparables Data'!S8/'Comparables Data'!S$3 -> 0.020048037 | AE9: ='Comparables Data'!T8/'Comparables Data'!T$3 -> 0.021473136 | AF9: ='Comparables Data'!U8/'Comparables Data'!U$3 -> 0.030075761 | AG9: ='Comparables Data'!V8/'Comparables Data'!V$3 -> 0.062451254 | AH9: ='Comparables Data'!W8/'Comparables Data'!W$3 -> 0.059399582 | AJ9: ='Comparables Data'!Y8 -> Employee Cost | AK9: ='Comparables Data'!AC8/'Comparables Data'!AC$3 -> 0.057883014 | AL9: ='Comparables Data'!AD8/'Comparables Data'!AD$3 -> 0.055774069 | AM9: ='Comparables Data'!AE8/'Comparables Data'!AE$3 -> 0.058513919 | AN9: ='Comparables Data'!AF8/'Comparables Data'!AF$3 -> 0.057984107 | AO9: ='Comparables Data'!AG8/'Comparables Data'!AG$3 -> 0.070227134 | AP9: ='Comparables Data'!AH8/'Comparables Data'!AH$3 -> 0.067215613 | AQ9: ='Comparables Data'!AI8/'Comparables Data'!AI$3 -> 0.068020162
B10: ='Data Sheet'!A23 -> Selling and admin | C10: ='Data Sheet'!B23/'Data Sheet'!$B$17 -> 0.20170677 | D10: ='Data Sheet'!C23/'Data Sheet'!$C$17 -> 0.20402307 | E10: ='Data Sheet'!D23/'Data Sheet'!$D$17 -> 0.19832104 | F10: ='Data Sheet'!E23/'Data Sheet'!$E$17 -> 0.1915391 | G10: ='Data Sheet'!F23/'Data Sheet'!$F$17 -> 0.16811261 | H10: ='Data Sheet'!G23/'Data Sheet'!$G$17 -> 0.15566487 | I10: ='Data Sheet'!H23/'Data Sheet'!$H$17 -> 0.14501486 | J10: ='Data Sheet'!I23/'Data Sheet'!$I$17 -> 0.17416311 | K10: ='Data Sheet'!J23/'Data Sheet'!$J$17 -> 0.16542199 | L10: ='Data Sheet'!K23/'Data Sheet'!$K$17 -> 0.16665633 | N10: ='Comparables Data'!A9 -> Selling and admin | O10: ='Comparables Data'!B9/'Comparables Data'!B$3 -> 0.09773146 | P10: ='Comparables Data'!C9/'Comparables Data'!C$3 -> 0.091023394 | Q10: ='Comparables Data'!D9/'Comparables Data'!D$3 -> 0.094051086 | R10: ='Comparables Data'!E9/'Comparables Data'!E$3 -> 0.090885585 | S10: ='Comparables Data'!F9/'Comparables Data'!F$3 -> 0.086012776 | T10: ='Comparables Data'!G9/'Comparables Data'!G$3 -> 0.080112406 | U10: ='Comparables Data'!H9/'Comparables Data'!H$3 -> 0.079020821 | V10: ='Comparables Data'!I9/'Comparables Data'!I$3 -> 0.078202536 | ... X10: ='Comparables Data'!K9/'Comparables Data'!K$3 -> 0 | Z10: ='Comparables Data'!M9 -> Selling and admin | AA10: ='Comparables Data'!P9/'Comparables Data'!P$3 -> 0.026325954 | AB10: ='Comparables Data'!Q9/'Comparables Data'!Q$3 -> 0.018551626 | AC10: ='Comparables Data'!R9/'Comparables Data'!R$3 -> 0.012788978 | AD10: ='Comparables Data'!S9/'Comparables Data'!S$3 -> 0.011200431 | AE10: ='Comparables Data'!T9/'Comparables Data'!T$3 -> 0.010180399 | AF10: ='Comparables Data'!U9/'Comparables Data'!U$3 -> 0.013050376 | AG10: ='Comparables Data'!V9/'Comparables Data'!V$3 -> 0.017742216 | AH10: ='Comparables Data'!W9/'Comparables Data'!W$3 -> 0 | AJ10: ='Comparables Data'!Y9 -> Selling and admin | AK10: ='Comparables Data'!AC9/'Comparables Data'!AC$3 -> 0.034814789 | AL10: ='Comparables Data'!AD9/'Comparables Data'!AD$3 -> 0.04437741 | AM10: ='Comparables Data'!AE9/'Comparables Data'!AE$3 -> 0.048727333 | AN10: ='Comparables Data'!AF9/'Comparables Data'!AF$3 -> 0.056073143 | AO10: ='Comparables Data'!AG9/'Comparables Data'!AG$3 -> 0.046274612 | AP10: ='Comparables Data'!AH9/'Comparables Data'!AH$3 -> 0.043881834 | AQ10: ='Comparables Data'!AI9/'Comparables Data'!AI$3 -> 0
B11: ='Data Sheet'!A24 -> Other Expenses | C11: ='Data Sheet'!B24/'Data Sheet'!$B$17 -> 0.044327845 | D11: ='Data Sheet'!C24/'Data Sheet'!$C$17 -> 0.041637361 | E11: ='Data Sheet'!D24/'Data Sheet'!$D$17 -> 0.039506487 | F11: ='Data Sheet'!E24/'Data Sheet'!$E$17 -> 0.042430184 | G11: ='Data Sheet'!F24/'Data Sheet'!$F$17 -> 0.046674322 | H11: ='Data Sheet'!G24/'Data Sheet'!$G$17 -> 0.044979598 | I11: ='Data Sheet'!H24/'Data Sheet'!$H$17 -> 0.037421591 | J11: ='Data Sheet'!I24/'Data Sheet'!$I$17 -> 0.045334109 | K11: ='Data Sheet'!J24/'Data Sheet'!$J$17 -> 0.048362901 | L11: ='Data Sheet'!K24/'Data Sheet'!$K$17 -> 0.047325805 | N11: ='Comparables Data'!A10 -> Other Expenses | O11: ='Comparables Data'!B10/'Comparables Data'!B$3 -> 0.027339154 | P11: ='Comparables Data'!C10/'Comparables Data'!C$3 -> 0.023153154 | Q11: ='Comparables Data'!D10/'Comparables Data'!D$3 -> 0.021511358 | R11: ='Comparables Data'!E10/'Comparables Data'!E$3 -> 0.024806379 | S11: ='Comparables Data'!F10/'Comparables Data'!F$3 -> 0.021811726 | T11: ='Comparables Data'!G10/'Comparables Data'!G$3 -> 0.018302555 | U11: ='Comparables Data'!H10/'Comparables Data'!H$3 -> 0.018451465 | V11: ='Comparables Data'!I10/'Comparables Data'!I$3 -> 0.025996166 | ... X11: ='Comparables Data'!K10/'Comparables Data'!K$3 -> 0.15495572 | Z11: ='Comparables Data'!M10 -> Other Expenses | AA11: ='Comparables Data'!P10/'Comparables Data'!P$3 -> 0.0072574251 | AB11: ='Comparables Data'!Q10/'Comparables Data'!Q$3 -> 0.003381267 | AC11: ='Comparables Data'!R10/'Comparables Data'!R$3 -> 0.0034623291 | AD11: ='Comparables Data'!S10/'Comparables Data'!S$3 -> 0.0029508357 | AE11: ='Comparables Data'!T10/'Comparables Data'!T$3 -> 0.00167813 | AF11: ='Comparables Data'!U10/'Comparables Data'!U$3 -> 0.002954939 | AG11: ='Comparables Data'!V10/'Comparables Data'!V$3 -> 0.0023931231 | AH11: ='Comparables Data'!W10/'Comparables Data'!W$3 -> 0.072410516 | AJ11: ='Comparables Data'!Y10 -> Other Expenses | AK11: ='Comparables Data'!AC10/'Comparables Data'!AC$3 -> 0.0022410307 | AL11: ='Comparables Data'!AD10/'Comparables Data'!AD$3 -> 0.0058056002 | AM11: ='Comparables Data'!AE10/'Comparables Data'!AE$3 -> 0.0035539525 | AN11: ='Comparables Data'!AF10/'Comparables Data'!AF$3 -> 0.00076934913 | AO11: ='Comparables Data'!AG10/'Comparables Data'!AG$3 -> 0.00045652084 | AP11: ='Comparables Data'!AH10/'Comparables Data'!AH$3 -> 0.001411576 | AQ11: ='Comparables Data'!AI10/'Comparables Data'!AI$3 -> 0.15040192
B12: ='Data Sheet'!A25 -> Other Income | C12: ='Data Sheet'!B25/'Data Sheet'!$B$17 -> 0.018273928 | D12: ='Data Sheet'!C25/'Data Sheet'!$C$17 -> 0.0099310733 | E12: ='Data Sheet'!D25/'Data Sheet'!$D$17 -> 0.0081912999 | F12: ='Data Sheet'!E25/'Data Sheet'!$E$17 -> 0.010657819 | G12: ='Data Sheet'!F25/'Data Sheet'!$F$17 -> 0.0036148677 | H12: ='Data Sheet'!G25/'Data Sheet'!$G$17 -> 0.0041757236 | I12: ='Data Sheet'!H25/'Data Sheet'!$H$17 -> 0.0073951799 | J12: ='Data Sheet'!I25/'Data Sheet'!$I$17 -> 0.013199561 | K12: ='Data Sheet'!J25/'Data Sheet'!$J$17 -> 0.022094313 | L12: ='Data Sheet'!K25/'Data Sheet'!$K$17 -> 0.076363467 | N12: ='Comparables Data'!A11 -> Other Income | O12: ='Comparables Data'!B11/'Comparables Data'!B$3 -> 0.041120615 | P12: ='Comparables Data'!C11/'Comparables Data'!C$3 -> 0.051550395 | Q12: ='Comparables Data'!D11/'Comparables Data'!D$3 -> 0.043038024 | R12: ='Comparables Data'!E11/'Comparables Data'!E$3 -> 0.04894579 | S12: ='Comparables Data'!F11/'Comparables Data'!F$3 -> 0.052315944 | T12: ='Comparables Data'!G11/'Comparables Data'!G$3 -> 0.031490386 | U12: ='Comparables Data'!H11/'Comparables Data'!H$3 -> 0.029577957 | V12: ='Comparables Data'!I11/'Comparables Data'!I$3 -> 0.049026275 | ... X12: ='Comparables Data'!K11/'Comparables Data'!K$3 -> 0.031840129 | Z12: ='Comparables Data'!M11 -> Other Income | AA12: ='Comparables Data'!P11/'Comparables Data'!P$3 -> 0.0013213799 | AB12: ='Comparables Data'!Q11/'Comparables Data'!Q$3 -> 0.0015675606 | AC12: ='Comparables Data'!R11/'Comparables Data'!R$3 -> 0.0019187074 | AD12: ='Comparables Data'!S11/'Comparables Data'!S$3 -> 0.0018087349 | AE12: ='Comparables Data'!T11/'Comparables Data'!T$3 -> 0.0017358639 | AF12: ='Comparables Data'!U11/'Comparables Data'!U$3 -> 0.0026028148 | AG12: ='Comparables Data'!V11/'Comparables Data'!V$3 -> 0.0040820563 | AH12: ='Comparables Data'!W11/'Comparables Data'!W$3 -> 0.0021359479 | AJ12: ='Comparables Data'!Y11 -> Other Income | AK12: ='Comparables Data'!AC11/'Comparables Data'!AC$3 -> 0.0093547613 | AL12: ='Comparables Data'!AD11/'Comparables Data'!AD$3 -> 0.0053375115 | AM12: ='Comparables Data'!AE11/'Comparables Data'!AE$3 -> 0.0037478045 | AN12: ='Comparables Data'!AF11/'Comparables Data'!AF$3 -> 0.0035588602 | AO12: ='Comparables Data'!AG11/'Comparables Data'!AG$3 -> 0.0084011692 | AP12: ='Comparables Data'!AH11/'Comparables Data'!AH$3 -> 0.0087795749 | AQ12: ='Comparables Data'!AI11/'Comparables Data'!AI$3 -> -0.0095224202
B13: ='Data Sheet'!A26 -> Depreciation | C13: ='Data Sheet'!B26/'Data Sheet'!$B$17 -> 0.013026959 | D13: ='Data Sheet'!C26/'Data Sheet'!$C$17 -> 0.014629343 | E13: ='Data Sheet'!D26/'Data Sheet'!$D$17 -> 0.014372933 | F13: ='Data Sheet'!E26/'Data Sheet'!$E$17 -> 0.025186638 | G13: ='Data Sheet'!F26/'Data Sheet'!$F$17 -> 0.022837459 | H13: ='Data Sheet'!G26/'Data Sheet'!$G$17 -> 0.020802349 | I13: ='Data Sheet'!H26/'Data Sheet'!$H$17 -> 0.01876857 | J13: ='Data Sheet'!I26/'Data Sheet'!$I$17 -> 0.019645858 | K13: ='Data Sheet'!J26/'Data Sheet'!$J$17 -> 0.020431124 | L13: ='Data Sheet'!K26/'Data Sheet'!$K$17 -> 0.020676925 | N13: ='Comparables Data'!A12 -> Depreciation | O13: ='Comparables Data'!B12/'Comparables Data'!B$3 -> 0.026954751 | P13: ='Comparables Data'!C12/'Comparables Data'!C$3 -> 0.028453629 | Q13: ='Comparables Data'!D12/'Comparables Data'!D$3 -> 0.028891645 | R13: ='Comparables Data'!E12/'Comparables Data'!E$3 -> 0.033306066 | S13: ='Comparables Data'!F12/'Comparables Data'!F$3 -> 0.033407941 | T13: ='Comparables Data'!G12/'Comparables Data'!G$3 -> 0.028566628 | U13: ='Comparables Data'!H12/'Comparables Data'!H$3 -> 0.025508104 | V13: ='Comparables Data'!I12/'Comparables Data'!I$3 -> 0.022346631 | ... X13: ='Comparables Data'!K12/'Comparables Data'!K$3 -> 0.021688408 | Z13: ='Comparables Data'!M12 -> Depreciation | AA13: ='Comparables Data'!P12/'Comparables Data'!P$3 -> 0.015165376 | AB13: ='Comparables Data'!Q12/'Comparables Data'!Q$3 -> 0.014613292 | AC13: ='Comparables Data'!R12/'Comparables Data'!R$3 -> 0.012406679 | AD13: ='Comparables Data'!S12/'Comparables Data'!S$3 -> 0.012014117 | AE13: ='Comparables Data'!T12/'Comparables Data'!T$3 -> 0.014398818 | AF13: ='Comparables Data'!U12/'Comparables Data'!U$3 -> 0.019893201 | AG13: ='Comparables Data'!V12/'Comparables Data'!V$3 -> 0.022368547 | AH13: ='Comparables Data'!W12/'Comparables Data'!W$3 -> 0.021190109 | AJ13: ='Comparables Data'!Y12 -> Depreciation | AK13: ='Comparables Data'!AC12/'Comparables Data'!AC$3 -> 0.030805606 | AL13: ='Comparables Data'!AD12/'Comparables Data'!AD$3 -> 0.030640306 | AM13: ='Comparables Data'!AE12/'Comparables Data'!AE$3 -> 0.028214271 | AN13: ='Comparables Data'!AF12/'Comparables Data'!AF$3 -> 0.024857422 | AO13: ='Comparables Data'!AG12/'Comparables Data'!AG$3 -> 0.03553155 | AP13: ='Comparables Data'!AH12/'Comparables Data'!AH$3 -> 0.026766475 | AQ13: ='Comparables Data'!AI12/'Comparables Data'!AI$3 -> 0.027410284
B14: ='Data Sheet'!A27 -> Interest | C14: ='Data Sheet'!B27/'Data Sheet'!$B$17 -> 0.0010554249 | D14: ='Data Sheet'!C27/'Data Sheet'!$C$17 -> 0.00073146715 | E14: ='Data Sheet'!D27/'Data Sheet'!$D$17 -> 0.00083948105 | F14: ='Data Sheet'!E27/'Data Sheet'!$E$17 -> 0.002966091 | G14: ='Data Sheet'!F27/'Data Sheet'!$F$17 -> 0.0024878796 | H14: ='Data Sheet'!G27/'Data Sheet'!$G$17 -> 0.0020211265 | I14: ='Data Sheet'!H27/'Data Sheet'!$H$17 -> 0.0018818092 | J14: ='Data Sheet'!I27/'Data Sheet'!$I$17 -> 0.0053961484 | K14: ='Data Sheet'!J27/'Data Sheet'!$J$17 -> 0.0062124967 | L14: ='Data Sheet'!K27/'Data Sheet'!$K$17 -> 0.0063597444 | N14: ='Comparables Data'!A13 -> Interest | O14: ='Comparables Data'!B13/'Comparables Data'!B$3 -> 0.0011464286 | P14: ='Comparables Data'!C13/'Comparables Data'!C$3 -> 0.0026470151 | Q14: ='Comparables Data'!D13/'Comparables Data'!D$3 -> 0.0014770505 | R14: ='Comparables Data'!E13/'Comparables Data'!E$3 -> 0.0016477787 | S14: ='Comparables Data'!F13/'Comparables Data'!F$3 -> 0.0011768778 | T14: ='Comparables Data'!G13/'Comparables Data'!G$3 -> 0.00098920694 | U14: ='Comparables Data'!H13/'Comparables Data'!H$3 -> 0.0010966027 | V14: ='Comparables Data'!I13/'Comparables Data'!I$3 -> 0.00057572329 | ... X14: ='Comparables Data'!K13/'Comparables Data'!K$3 -> 0.0010799002 | Z14: ='Comparables Data'!M13 -> Interest | AA14: ='Comparables Data'!P13/'Comparables Data'!P$3 -> 0.015287349 | AB14: ='Comparables Data'!Q13/'Comparables Data'!Q$3 -> 0.014418966 | AC14: ='Comparables Data'!R13/'Comparables Data'!R$3 -> 0.013604068 | AD14: ='Comparables Data'!S13/'Comparables Data'!S$3 -> 0.0099700995 | AE14: ='Comparables Data'!T13/'Comparables Data'!T$3 -> 0.013836875 | AF14: ='Comparables Data'!U13/'Comparables Data'!U$3 -> 0.020648272 | AG14: ='Comparables Data'!V13/'Comparables Data'!V$3 -> 0.022817432 | AH14: ='Comparables Data'!W13/'Comparables Data'!W$3 -> 0.019359968 | AJ14: ='Comparables Data'!Y13 -> Interest | AK14: ='Comparables Data'!AC13/'Comparables Data'!AC$3 -> 0.047109619 | AL14: ='Comparables Data'!AD13/'Comparables Data'!AD$3 -> 0.047055917 | AM14: ='Comparables Data'!AE13/'Comparables Data'!AE$3 -> 0.035504279 | AN14: ='Comparables Data'!AF13/'Comparables Data'!AF$3 -> 0.036129628 | AO14: ='Comparables Data'!AG13/'Comparables Data'!AG$3 -> 0.04479833 | AP14: ='Comparables Data'!AH13/'Comparables Data'!AH$3 -> 0.038385243 | AQ14: ='Comparables Data'!AI13/'Comparables Data'!AI$3 -> 0.024714026
B15: ='Data Sheet'!A28 -> Profit before tax | C15: ='Data Sheet'!B28/'Data Sheet'!$B$17 -> 0.19501236 | D15: ='Data Sheet'!C28/'Data Sheet'!$C$17 -> 0.20554227 | E15: ='Data Sheet'!D28/'Data Sheet'!$D$17 -> 0.2188756 | F15: ='Data Sheet'!E28/'Data Sheet'!$E$17 -> 0.23037478 | G15: ='Data Sheet'!F28/'Data Sheet'!$F$17 -> 0.22550396 | H15: ='Data Sheet'!G28/'Data Sheet'!$G$17 -> 0.22649964 | I15: ='Data Sheet'!H28/'Data Sheet'!$H$17 -> 0.22027072 | J15: ='Data Sheet'!I28/'Data Sheet'!$I$17 -> 0.22499031 | K15: ='Data Sheet'!J28/'Data Sheet'!$J$17 -> 0.23511284 | L15: ='Data Sheet'!K28/'Data Sheet'!$K$17 -> 0.28260532 | N15: ='Comparables Data'!A14 -> Profit before tax | O15: ='Comparables Data'!B14/'Comparables Data'!B$3 -> 0.3747304 | P15: ='Comparables Data'!C14/'Comparables Data'!C$3 -> 0.40067974 | Q15: ='Comparables Data'!D14/'Comparables Data'!D$3 -> 0.39615197 | R15: ='Comparables Data'!E14/'Comparables Data'!E$3 -> 0.4056591 | S15: ='Comparables Data'!F14/'Comparables Data'!F$3 -> 0.36417171 | T15: ='Comparables Data'!G14/'Comparables Data'!G$3 -> 0.34200062 | U15: ='Comparables Data'!H14/'Comparables Data'!H$3 -> 0.36541842 | V15: ='Comparables Data'!I14/'Comparables Data'!I$3 -> 0.39687988 | ... X15: ='Comparables Data'!K14/'Comparables Data'!K$3 -> 0.35544515 | Z15: ='Comparables Data'!M14 -> Profit before tax | AA15: ='Comparables Data'!P14/'Comparables Data'!P$3 -> 0.037059625 | AB15: ='Comparables Data'!Q14/'Comparables Data'!Q$3 -> 0.04380101 | AC15: ='Comparables Data'!R14/'Comparables Data'!R$3 -> 0.03466657 | AD15: ='Comparables Data'!S14/'Comparables Data'!S$3 -> 0.035037498 | AE15: ='Comparables Data'!T14/'Comparables Data'!T$3 -> 0.040221236 | AF15: ='Comparables Data'!U14/'Comparables Data'!U$3 -> 0.042621546 | AG15: ='Comparables Data'!V14/'Comparables Data'!V$3 -> 0.041502309 | AH15: ='Comparables Data'!W14/'Comparables Data'!W$3 -> 0.046962626 | AJ15: ='Comparables Data'!Y14 -> Profit before tax | AK15: ='Comparables Data'!AC14/'Comparables Data'!AC$3 -> 0.0022547373 | AL15: ='Comparables Data'!AD14/'Comparables Data'!AD$3 -> 0.030113707 | AM15: ='Comparables Data'!AE14/'Comparables Data'!AE$3 -> 0.018833011 | AN15: ='Comparables Data'!AF14/'Comparables Data'!AF$3 -> 0.015759248 | AO15: ='Comparables Data'!AG14/'Comparables Data'!AG$3 -> 0.0073754795 | AP15: ='Comparables Data'!AH14/'Comparables Data'!AH$3 -> -0.00082341933 | AQ15: ='Comparables Data'!AI14/'Comparables Data'!AI$3 -> 0.0022988621
... B17: ='Data Sheet'!A30 -> Net profit | C17: ='Data Sheet'!B30/'Data Sheet'!$B$17 -> 0.13497377 | D17: ='Data Sheet'!C30/'Data Sheet'!$C$17 -> 0.1466873 | E17: ='Data Sheet'!D30/'Data Sheet'!$D$17 -> 0.15400661 | F17: ='Data Sheet'!E30/'Data Sheet'!$E$17 -> 0.16962019 | G17: ='Data Sheet'!F30/'Data Sheet'!$F$17 -> 0.1700051 | H17: ='Data Sheet'!G30/'Data Sheet'!$G$17 -> 0.16929794 | I17: ='Data Sheet'!H30/'Data Sheet'!$H$17 -> 0.16705183 | J17: ='Data Sheet'!I30/'Data Sheet'!$I$17 -> 0.16603658 | K17: ='Data Sheet'!J30/'Data Sheet'!$J$17 -> 0.1736401 | L17: ='Data Sheet'!K30/'Data Sheet'!$K$17 -> 0.23329404 | N17: ='Comparables Data'!A16 -> Net profit | O17: ='Comparables Data'!B16/'Comparables Data'!B$3 -> 0.24058961 | P17: ='Comparables Data'!C16/'Comparables Data'!C$3 -> 0.25941254 | Q17: ='Comparables Data'!D16/'Comparables Data'!D$3 -> 0.2604973 | R17: ='Comparables Data'!E16/'Comparables Data'!E$3 -> 0.30991988 | S17: ='Comparables Data'!F16/'Comparables Data'!F$3 -> 0.26719187 | T17: ='Comparables Data'!G16/'Comparables Data'!G$3 -> 0.25134431 | U17: ='Comparables Data'!H16/'Comparables Data'!H$3 -> 0.27061368 | V17: ='Comparables Data'!I16/'Comparables Data'!I$3 -> 0.30116584 | ... X17: ='Comparables Data'!K16/'Comparables Data'!K$3 -> 0.26232902 | Z17: ='Comparables Data'!M16 -> Net profit | AA17: ='Comparables Data'!P16/'Comparables Data'!P$3 -> 0.024211746 | AB17: ='Comparables Data'!Q16/'Comparables Data'!Q$3 -> 0.028384506 | AC17: ='Comparables Data'!R16/'Comparables Data'!R$3 -> 0.024813359 | AD17: ='Comparables Data'!S16/'Comparables Data'!S$3 -> 0.021891084 | AE17: ='Comparables Data'!T16/'Comparables Data'!T$3 -> 0.027373534 | AF17: ='Comparables Data'!U16/'Comparables Data'!U$3 -> 0.03376762 | AG17: ='Comparables Data'!V16/'Comparables Data'!V$3 -> 0.030759908 | AH17: ='Comparables Data'!W16/'Comparables Data'!W$3 -> 0.035057304 | AJ17: ='Comparables Data'!Y16 -> Net profit | AK17: ='Comparables Data'!AC16/'Comparables Data'!AC$3 -> 0.0027824418 | AL17: ='Comparables Data'!AD16/'Comparables Data'!AD$3 -> 0.017650845 | AM17: ='Comparables Data'!AE16/'Comparables Data'!AE$3 -> 0.011219916 | AN17: ='Comparables Data'!AF16/'Comparables Data'!AF$3 -> 0.009748398 | AO17: ='Comparables Data'!AG16/'Comparables Data'!AG$3 -> 0.0072924757 | AP17: ='Comparables Data'!AH16/'Comparables Data'!AH$3 -> -0.012517043 | AQ17: ='Comparables Data'!AI16/'Comparables Data'!AI$3 -> 0.0017757075
B18: ='Data Sheet'!A31 -> Dividend Amount | C18: ='Data Sheet'!B31/'Data Sheet'!$B$17 -> 0.11072915 | D18: ='Data Sheet'!C31/'Data Sheet'!$C$17 -> 0.12153608 | E18: ='Data Sheet'!D31/'Data Sheet'!$D$17 -> 0.12088527 | F18: ='Data Sheet'!E31/'Data Sheet'!$E$17 -> 0.13573637 | G18: ='Data Sheet'!F31/'Data Sheet'!$F$17 -> 0.20237943 | H18: ='Data Sheet'!G31/'Data Sheet'!$G$17 -> 0.15234718 | I18: ='Data Sheet'!H31/'Data Sheet'!$H$17 -> 0.15128755 | J18: ='Data Sheet'!I31/'Data Sheet'!$I$17 -> 0.15946103 | K18: ='Data Sheet'!J31/'Data Sheet'!$J$17 -> 0.20308831 | L18: ='Data Sheet'!K31/'Data Sheet'!$K$17 -> 0.14945399 | N18: ='Comparables Data'!A17 -> Dividend Amount | O18: ='Comparables Data'!B17/'Comparables Data'!B$3 -> 0.13491568 | P18: ='Comparables Data'!C17/'Comparables Data'!C$3 -> 0.14465738 | Q18: ='Comparables Data'!D17/'Comparables Data'!D$3 -> 0.14581633 | R18: ='Comparables Data'!E17/'Comparables Data'!E$3 -> 0.25262525 | S18: ='Comparables Data'!F17/'Comparables Data'!F$3 -> 0.2686286 | T18: ='Comparables Data'!G17/'Comparables Data'!G$3 -> 0.23368633 | U18: ='Comparables Data'!H17/'Comparables Data'!H$3 -> 0.27162526 | V18: ='Comparables Data'!I17/'Comparables Data'!I$3 -> 0.25270087 | ... X18: ='Comparables Data'!K17/'Comparables Data'!K$3 -> 0.23035563
B21: ="Common Size Balance Sheet for "&'Data Sheet'!B1 -> Common Size Balance Sheet for HINDUSTAN UNILEVER LTD | N21: ="Common Size Balance Sheet for "&'Comparables Data'!A1 -> Common Size Balance Sheet for ITC LTD | Z21: ="Common Size Balance Sheet for "&'Comparables Data'!O1 -> Common Size Balance Sheet for HINDUSTAN FOODS LTD | AJ21: ="Common Size Balance Sheet for "&'Comparables Data'!Z1 -> Common Size Balance Sheet for GODAVARI BIOREFINERIES LTD
B22: Year | C22: =C3 -> 42825 | D22: =D3 -> 43190 | E22: =E3 -> 43555 | F22: =F3 -> 43921 | G22: =G3 -> 44286 | H22: =H3 -> 44651 | I22: =I3 -> 45016 | J22: =J3 -> 45382 | ... L22: =L3 -> 46112 | N22: Year | O22: =C22 -> 42825 | P22: =D22 -> 43190 | Q22: =E22 -> 43555 | R22: =F22 -> 43921 | S22: =G22 -> 44286 | T22: =H22 -> 44651 | U22: =I22 -> 45016 | V22: =J22 -> 45382 | ... X22: =L22 -> 46112 | Z22: Year | AA22: =Q22 -> 43555 | AB22: =R22 -> 43921 | AC22: =S22 -> 44286 | AD22: =T22 -> 44651 | AE22: =U22 -> 45016 | AF22: =V22 -> 45382 | AG22: =W22 -> 45747 | AH22: =X22 -> 46112 | AJ22: Year | AK22: =AB22 -> 43921 | AL22: =AC22 -> 44286 | AM22: =AD22 -> 44651 | AN22: =AE22 -> 45016 | AO22: =AF22 -> 45382 | AP22: =AG22 -> 45747 | AQ22: =AH22 -> 46112
B23: ='Data Sheet'!A57 -> Equity Share Capital | C23: ='Data Sheet'!B57/'Data Sheet'!$B$61 -> 0.013752706 | D23: ='Data Sheet'!C57/'Data Sheet'!$B$61 -> 0.013752706 | E23: ='Data Sheet'!D57/'Data Sheet'!$B$61 -> 0.013752706 | F23: ='Data Sheet'!E57/'Data Sheet'!$B$61 -> 0.013752706 | G23: ='Data Sheet'!F57/'Data Sheet'!$B$61 -> 0.014962435 | H23: ='Data Sheet'!G57/'Data Sheet'!$B$61 -> 0.014962435 | I23: ='Data Sheet'!H57/'Data Sheet'!$B$61 -> 0.014962435 | J23: ='Data Sheet'!I57/'Data Sheet'!$B$61 -> 0.014962435 | ... L23: ='Data Sheet'!K57/'Data Sheet'!$B$61 -> 0.014962435 | N23: ='Comparables Data'!A21 -> Equity Share Capital | O23: ='Comparables Data'!B21/'Comparables Data'!B$25 -> 0.021731243 | P23: ='Comparables Data'!C21/'Comparables Data'!C$25 -> 0.018997716 | Q23: ='Comparables Data'!D21/'Comparables Data'!D$25 -> 0.017087767 | R23: ='Comparables Data'!E21/'Comparables Data'!E$25 -> 0.015899729 | S23: ='Comparables Data'!F21/'Comparables Data'!F$25 -> 0.016687464 | T23: ='Comparables Data'!G21/'Comparables Data'!G$25 -> 0.015963647 | U23: ='Comparables Data'!H21/'Comparables Data'!H$25 -> 0.014479624 | V23: ='Comparables Data'!I21/'Comparables Data'!I$25 -> 0.013606714 | ... X23: ='Comparables Data'!K21/'Comparables Data'!K$25 -> 0.013358761 | Z23: ='Comparables Data'!M21 -> Equity Share Capital | AA23: ='Comparables Data'!P21/'Comparables Data'!P$25 -> 0.050670473 | AB23: ='Comparables Data'!Q21/'Comparables Data'!Q$25 -> 0.039323342 | AC23: ='Comparables Data'!R21/'Comparables Data'!R$25 -> 0.030529075 | AD23: ='Comparables Data'!S21/'Comparables Data'!S$25 -> 0.022907355 | AE23: ='Comparables Data'!T21/'Comparables Data'!T$25 -> 0.016894423 | AF23: ='Comparables Data'!U21/'Comparables Data'!U$25 -> 0.011904453 | AG23: ='Comparables Data'!V21/'Comparables Data'!V$25 -> 0.0094656919 | AH23: ='Comparables Data'!W21/'Comparables Data'!W$25 -> 0.0075306187 | AJ23: ='Comparables Data'!Y21 -> Equity Share Capital | AK23: ='Comparables Data'!AC21/'Comparables Data'!AC$25 -> 0.029237075 | AL23: ='Comparables Data'!AD21/'Comparables Data'!AD$25 -> 0.029090657 | AM23: ='Comparables Data'!AE21/'Comparables Data'!AE$25 -> 0.024193269 | AN23: ='Comparables Data'!AF21/'Comparables Data'!AF$25 -> 0.024054786 | AO23: ='Comparables Data'!AG21/'Comparables Data'!AG$25 -> 0.021059503 | AP23: ='Comparables Data'!AH21/'Comparables Data'!AH$25 -> 0.026177823 | AQ23: ='Comparables Data'!AI21/'Comparables Data'!AI$25 -> 0.024938482
B24: ='Data Sheet'!A58 -> Reserves | C24: ='Data Sheet'!B58/'Data Sheet'!$B$61 -> 0.41563734 | D24: ='Data Sheet'!C58/'Data Sheet'!$B$61 -> 0.44982809 | E24: ='Data Sheet'!D58/'Data Sheet'!$B$61 -> 0.48713867 | F24: ='Data Sheet'!E58/'Data Sheet'!$B$61 -> 0.51018719 | G24: ='Data Sheet'!F58/'Data Sheet'!$B$61 -> 3.020438 | H24: ='Data Sheet'!G58/'Data Sheet'!$B$61 -> 3.1087482 | I24: ='Data Sheet'!H58/'Data Sheet'!$B$61 -> 3.18789 | J24: ='Data Sheet'!I58/'Data Sheet'!$B$61 -> 3.2460843 | ... L24: ='Data Sheet'!K58/'Data Sheet'!$B$61 -> 3.0882465 | N24: ='Comparables Data'!A22 -> Reserves | O24: ='Comparables Data'!B22/'Comparables Data'!B$25 -> 0.80857868 | P24: ='Comparables Data'!C22/'Comparables Data'!C$25 -> 0.79839629 | Q24: ='Comparables Data'!D22/'Comparables Data'!D$25 -> 0.80730116 | R24: ='Comparables Data'!E22/'Comparables Data'!E$25 -> 0.8283976 | S24: ='Comparables Data'!F22/'Comparables Data'!F$25 -> 0.80146219 | T24: ='Comparables Data'!G22/'Comparables Data'!G$25 -> 0.79308804 | U24: ='Comparables Data'!H22/'Comparables Data'!H$25 -> 0.791235 | V24: ='Comparables Data'!I22/'Comparables Data'!I$25 -> 0.79842355 | ... X24: ='Comparables Data'!K22/'Comparables Data'!K$25 -> 0.75970297 | Z24: ='Comparables Data'!M22 -> Reserves | AA24: ='Comparables Data'!P22/'Comparables Data'!P$25 -> 0.19107539 | AB24: ='Comparables Data'!Q22/'Comparables Data'!Q$25 -> 0.30601721 | AC24: ='Comparables Data'!R22/'Comparables Data'!R$25 -> 0.28724691 | AD24: ='Comparables Data'!S22/'Comparables Data'!S$25 -> 0.28516863 | AE24: ='Comparables Data'!T22/'Comparables Data'!T$25 -> 0.26335821 | AF24: ='Comparables Data'!U22/'Comparables Data'!U$25 -> 0.32383644 | AG24: ='Comparables Data'!V22/'Comparables Data'!V$25 -> 0.34943307 | AH24: ='Comparables Data'!W22/'Comparables Data'!W$25 -> 0.35957287 | AJ24: ='Comparables Data'!Y22 -> Reserves | AK24: ='Comparables Data'!AC22/'Comparables Data'!AC$25 -> 0.26852239 | AL24: ='Comparables Data'!AD22/'Comparables Data'!AD$25 -> 0.28575987 | AM24: ='Comparables Data'!AE22/'Comparables Data'!AE$25 -> 0.24865881 | AN24: ='Comparables Data'!AF22/'Comparables Data'!AF$25 -> 0.25667041 | AO24: ='Comparables Data'!AG22/'Comparables Data'!AG$25 -> 0.23034898 | AP24: ='Comparables Data'!AH22/'Comparables Data'!AH$25 -> 0.37378842 | AQ24: ='Comparables Data'!AI22/'Comparables Data'!AI$25 -> 0.35917164
B25: ='Data Sheet'!A59 -> Borrowings | C25: ='Data Sheet'!B59/'Data Sheet'!$B$61 -> 0.017636572 | D25: ='Data Sheet'!C59/'Data Sheet'!$B$61 -> 0 | E25: ='Data Sheet'!D59/'Data Sheet'!$B$61 -> 0.0063033236 | F25: ='Data Sheet'!E59/'Data Sheet'!$B$61 -> 0 | G25: ='Data Sheet'!F59/'Data Sheet'!$B$61 -> 0 | H25: ='Data Sheet'!G59/'Data Sheet'!$B$61 -> 0.066407742 | I25: ='Data Sheet'!H59/'Data Sheet'!$B$61 -> 0.077613651 | J25: ='Data Sheet'!I59/'Data Sheet'!$B$61 -> 0.094486184 | ... L25: ='Data Sheet'!K59/'Data Sheet'!$B$61 -> 0.094104164 | N25: ='Comparables Data'!A23 -> Borrowings | O25: ='Comparables Data'!B23/'Comparables Data'!B$25 -> 0.00081791367 | P25: ='Comparables Data'!C23/'Comparables Data'!C$25 -> 0.00055914552 | Q25: ='Comparables Data'!D23/'Comparables Data'!D$25 -> 0.00018734569 | R25: ='Comparables Data'!E23/'Comparables Data'!E$25 -> 0.0035887635 | S25: ='Comparables Data'!F23/'Comparables Data'!F$25 -> 0.0036717355 | T25: ='Comparables Data'!G23/'Comparables Data'!G$25 -> 0.0032312547 | U25: ='Comparables Data'!H23/'Comparables Data'!H$25 -> 0.0035656132 | V25: ='Comparables Data'!I23/'Comparables Data'!I$25 -> 0.0033069959 | ... X25: ='Comparables Data'!K23/'Comparables Data'!K$25 -> 0.025578411 | Z25: ='Comparables Data'!M23 -> Borrowings | AA25: ='Comparables Data'!P23/'Comparables Data'!P$25 -> 0.37373699 | AB25: ='Comparables Data'!Q23/'Comparables Data'!Q$25 -> 0.30618415 | AC25: ='Comparables Data'!R23/'Comparables Data'!R$25 -> 0.31364304 | AD25: ='Comparables Data'!S23/'Comparables Data'!S$25 -> 0.3557497 | AE25: ='Comparables Data'!T23/'Comparables Data'!T$25 -> 0.38643651 | AF25: ='Comparables Data'!U23/'Comparables Data'!U$25 -> 0.377513 | AG25: ='Comparables Data'!V23/'Comparables Data'!V$25 -> 0.35942642 | AH25: ='Comparables Data'!W23/'Comparables Data'!W$25 -> 0.34289837 | AJ25: ='Comparables Data'!Y23 -> Borrowings | AK25: ='Comparables Data'!AC23/'Comparables Data'!AC$25 -> 0.41064358 | AL25: ='Comparables Data'!AD23/'Comparables Data'!AD$25 -> 0.39482555 | AM25: ='Comparables Data'!AE23/'Comparables Data'!AE$25 -> 0.36665436 | AN25: ='Comparables Data'!AF23/'Comparables Data'!AF$25 -> 0.42207144 | AO25: ='Comparables Data'!AG23/'Comparables Data'!AG$25 -> 0.32869194 | AP25: ='Comparables Data'!AH23/'Comparables Data'!AH$25 -> 0.25051021 | AQ25: ='Comparables Data'!AI23/'Comparables Data'!AI$25 -> 0.25862346
B26: ='Data Sheet'!A60 -> Other Liabilities | C26: ='Data Sheet'!B60/'Data Sheet'!$B$61 -> 0.55297339 | D26: ='Data Sheet'!C60/'Data Sheet'!$B$61 -> 0.67369158 | E26: ='Data Sheet'!D60/'Data Sheet'!$B$61 -> 0.67891252 | F26: ='Data Sheet'!E60/'Data Sheet'!$B$61 -> 0.75920031 | G26: ='Data Sheet'!F60/'Data Sheet'!$B$61 -> 1.3412709 | H26: ='Data Sheet'!G60/'Data Sheet'!$B$61 -> 1.298994 | I26: ='Data Sheet'!H60/'Data Sheet'!$B$61 -> 1.3723418 | J26: ='Data Sheet'!I60/'Data Sheet'!$B$61 -> 1.6418566 | ... L26: ='Data Sheet'!K60/'Data Sheet'!$B$61 -> 1.8796002 | N26: ='Comparables Data'!A24 -> Other Liabilities | O26: ='Comparables Data'!B24/'Comparables Data'!B$25 -> 0.16887216 | P26: ='Comparables Data'!C24/'Comparables Data'!C$25 -> 0.18204685 | Q26: ='Comparables Data'!D24/'Comparables Data'!D$25 -> 0.17542373 | R26: ='Comparables Data'!E24/'Comparables Data'!E$25 -> 0.1521139 | S26: ='Comparables Data'!F24/'Comparables Data'!F$25 -> 0.17817861 | T26: ='Comparables Data'!G24/'Comparables Data'!G$25 -> 0.18771706 | U26: ='Comparables Data'!H24/'Comparables Data'!H$25 -> 0.19071976 | V26: ='Comparables Data'!I24/'Comparables Data'!I$25 -> 0.18466275 | ... X26: ='Comparables Data'!K24/'Comparables Data'!K$25 -> 0.20135985 | Z26: ='Comparables Data'!M24 -> Other Liabilities | AA26: ='Comparables Data'!P24/'Comparables Data'!P$25 -> 0.38451715 | AB26: ='Comparables Data'!Q24/'Comparables Data'!Q$25 -> 0.34847529 | AC26: ='Comparables Data'!R24/'Comparables Data'!R$25 -> 0.36858097 | AD26: ='Comparables Data'!S24/'Comparables Data'!S$25 -> 0.33617432 | AE26: ='Comparables Data'!T24/'Comparables Data'!T$25 -> 0.33331086 | AF26: ='Comparables Data'!U24/'Comparables Data'!U$25 -> 0.2867461 | AG26: ='Comparables Data'!V24/'Comparables Data'!V$25 -> 0.28167482 | AH26: ='Comparables Data'!W24/'Comparables Data'!W$25 -> 0.28999814 | AJ26: ='Comparables Data'!Y24 -> Other Liabilities | AK26: ='Comparables Data'!AC24/'Comparables Data'!AC$25 -> 0.29159695 | AL26: ='Comparables Data'!AD24/'Comparables Data'!AD$25 -> 0.29032392 | AM26: ='Comparables Data'!AE24/'Comparables Data'!AE$25 -> 0.36049356 | AN26: ='Comparables Data'!AF24/'Comparables Data'!AF$25 -> 0.29720336 | AO26: ='Comparables Data'!AG24/'Comparables Data'!AG$25 -> 0.41989957 | AP26: ='Comparables Data'!AH24/'Comparables Data'!AH$25 -> 0.34952355 | AQ26: ='Comparables Data'!AI24/'Comparables Data'!AI$25 -> 0.35726641
B28: Total Liablities | C28: ='Data Sheet'!B61/'Data Sheet'!B$61 -> 1 | D28: ='Data Sheet'!C61/'Data Sheet'!C$61 -> 1 | E28: ='Data Sheet'!D61/'Data Sheet'!D$61 -> 1 | F28: ='Data Sheet'!E61/'Data Sheet'!E$61 -> 1 | G28: ='Data Sheet'!F61/'Data Sheet'!F$61 -> 1 | H28: ='Data Sheet'!G61/'Data Sheet'!G$61 -> 1 | I28: ='Data Sheet'!H61/'Data Sheet'!H$61 -> 1 | J28: ='Data Sheet'!I61/'Data Sheet'!I$61 -> 1 | ... L28: ='Data Sheet'!K61/'Data Sheet'!K$61 -> 1 | N28: Total Liabilities | O28: ='Comparables Data'!B25/'Comparables Data'!B$25 -> 1 | P28: ='Comparables Data'!C25/'Comparables Data'!C$25 -> 1 | Q28: ='Comparables Data'!D25/'Comparables Data'!D$25 -> 1 | R28: ='Comparables Data'!E25/'Comparables Data'!E$25 -> 1 | S28: ='Comparables Data'!F25/'Comparables Data'!F$25 -> 1 | T28: ='Comparables Data'!G25/'Comparables Data'!G$25 -> 1 | U28: ='Comparables Data'!H25/'Comparables Data'!H$25 -> 1 | V28: ='Comparables Data'!I25/'Comparables Data'!I$25 -> 1 | ... X28: ='Comparables Data'!K25/'Comparables Data'!K$25 -> 1 | Z28: Total Liabilities | AA28: ='Comparables Data'!P25/'Comparables Data'!P$25 -> 1 | AB28: ='Comparables Data'!Q25/'Comparables Data'!Q$25 -> 1 | AC28: ='Comparables Data'!R25/'Comparables Data'!R$25 -> 1 | AD28: ='Comparables Data'!S25/'Comparables Data'!S$25 -> 1 | AE28: ='Comparables Data'!T25/'Comparables Data'!T$25 -> 1 | AF28: ='Comparables Data'!U25/'Comparables Data'!U$25 -> 1 | AG28: ='Comparables Data'!V25/'Comparables Data'!V$25 -> 1 | AH28: ='Comparables Data'!W25/'Comparables Data'!W$25 -> 1 | AJ28: Total Liabilities | AK28: ='Comparables Data'!AC25/'Comparables Data'!AC$25 -> 1 | AL28: ='Comparables Data'!AD25/'Comparables Data'!AD$25 -> 1 | AM28: ='Comparables Data'!AE25/'Comparables Data'!AE$25 -> 1 | AN28: ='Comparables Data'!AF25/'Comparables Data'!AF$25 -> 1 | AO28: ='Comparables Data'!AG25/'Comparables Data'!AG$25 -> 1 | AP28: ='Comparables Data'!AH25/'Comparables Data'!AH$25 -> 1 | AQ28: ='Comparables Data'!AI25/'Comparables Data'!AI$25 -> 1
B30: ='Data Sheet'!A62 -> Net Block | C30: ='Data Sheet'!B62/'Data Sheet'!B$66 -> 0.28135744 | D30: ='Data Sheet'!C62/'Data Sheet'!C$66 -> 0.25349905 | E30: ='Data Sheet'!D62/'Data Sheet'!D$66 -> 0.25310001 | F30: ='Data Sheet'!E62/'Data Sheet'!E$66 -> 0.27187019 | G30: ='Data Sheet'!F62/'Data Sheet'!F$66 -> 0.74837067 | H30: ='Data Sheet'!G62/'Data Sheet'!G$66 -> 0.73005134 | I30: ='Data Sheet'!H62/'Data Sheet'!H$66 -> 0.72085608 | J30: ='Data Sheet'!I62/'Data Sheet'!I$66 -> 0.68473289 | ... L30: ='Data Sheet'!K62/'Data Sheet'!K$66 -> 0.72020868 | N30: ='Comparables Data'!A26 -> Net Block | O30: ='Comparables Data'!B26/'Comparables Data'!B$30 -> 0.2843284 | P30: ='Comparables Data'!C26/'Comparables Data'!C$30 -> 0.25721877 | Q30: ='Comparables Data'!D26/'Comparables Data'!D$30 -> 0.27006481 | R30: ='Comparables Data'!E26/'Comparables Data'!E$30 -> 0.28085797 | S30: ='Comparables Data'!F26/'Comparables Data'!F$30 -> 0.31586551 | T30: ='Comparables Data'!G26/'Comparables Data'!G$30 -> 0.31389688 | U30: ='Comparables Data'!H26/'Comparables Data'!H$30 -> 0.30118817 | V30: ='Comparables Data'!I26/'Comparables Data'!I$30 -> 0.30320454 | ... X30: ='Comparables Data'!K26/'Comparables Data'!K$30 -> 0.24037134 | Z30: ='Comparables Data'!M26 -> Net Block | AA30: ='Comparables Data'!P26/'Comparables Data'!P$30 -> 0.50016903 | AB30: ='Comparables Data'!Q26/'Comparables Data'!Q$30 -> 0.46327348 | AC30: ='Comparables Data'!R26/'Comparables Data'!R$30 -> 0.39005213 | AD30: ='Comparables Data'!S26/'Comparables Data'!S$30 -> 0.43377692 | AE30: ='Comparables Data'!T26/'Comparables Data'!T$30 -> 0.41480865 | AF30: ='Comparables Data'!U26/'Comparables Data'!U$30 -> 0.47201077 | AG30: ='Comparables Data'!V26/'Comparables Data'!V$30 -> 0.40765311 | AH30: ='Comparables Data'!W26/'Comparables Data'!W$30 -> 0.41026118 | AJ30: ='Comparables Data'!Y26 -> Net Block | AK30: ='Comparables Data'!AC26/'Comparables Data'!AC$30 -> 0.51235291 | AL30: ='Comparables Data'!AD26/'Comparables Data'!AD$30 -> 0.49096206 | AM30: ='Comparables Data'!AE26/'Comparables Data'!AE$30 -> 0.38473874 | AN30: ='Comparables Data'!AF26/'Comparables Data'!AF$30 -> 0.49692576 | AO30: ='Comparables Data'!AG26/'Comparables Data'!AG$30 -> 0.42669345 | AP30: ='Comparables Data'!AH26/'Comparables Data'!AH$30 -> 0.44110501 | AQ30: ='Comparables Data'!AI26/'Comparables Data'!AI$30 -> 0.43102449
B31: ='Data Sheet'!A63 -> Capital Work in Progress | C31: ='Data Sheet'!B63/'Data Sheet'!B$66 -> 0.014580415 | D31: ='Data Sheet'!C63/'Data Sheet'!C$66 -> 0.02580898 | E31: ='Data Sheet'!D63/'Data Sheet'!D$66 -> 0.021793977 | F31: ='Data Sheet'!E63/'Data Sheet'!E$66 -> 0.029623381 | G31: ='Data Sheet'!F63/'Data Sheet'!F$66 -> 0.01083794 | H31: ='Data Sheet'!G63/'Data Sheet'!G$66 -> 0.018622529 | I31: ='Data Sheet'!H63/'Data Sheet'!H$66 -> 0.01549051 | J31: ='Data Sheet'!I63/'Data Sheet'!I$66 -> 0.013059155 | ... L31: ='Data Sheet'!K63/'Data Sheet'!K$66 -> 0.011036143 | N31: ='Comparables Data'!A27 -> Capital Work in Progress | O31: ='Comparables Data'!B27/'Comparables Data'!B$30 -> 0.066726335 | P31: ='Comparables Data'!C27/'Comparables Data'!C$30 -> 0.085744934 | Q31: ='Comparables Data'!D27/'Comparables Data'!D$30 -> 0.057659261 | R31: ='Comparables Data'!E27/'Comparables Data'!E$30 -> 0.042121697 | S31: ='Comparables Data'!F27/'Comparables Data'!F$30 -> 0.054382439 | T31: ='Comparables Data'!G27/'Comparables Data'!G$30 -> 0.04178376 | U31: ='Comparables Data'!H27/'Comparables Data'!H$30 -> 0.03499087 | V31: ='Comparables Data'!I27/'Comparables Data'!I$30 -> 0.031178814 | ... X31: ='Comparables Data'!K27/'Comparables Data'!K$30 -> 0.01598648 | Z31: ='Comparables Data'!M27 -> Capital Work in Progress | AA31: ='Comparables Data'!P27/'Comparables Data'!P$30 -> 0.0012770912 | AB31: ='Comparables Data'!Q27/'Comparables Data'!Q$30 -> 0.047410595 | AC31: ='Comparables Data'!R27/'Comparables Data'!R$30 -> 0.07699951 | AD31: ='Comparables Data'!S27/'Comparables Data'!S$30 -> 0.088541243 | AE31: ='Comparables Data'!T27/'Comparables Data'!T$30 -> 0.093739699 | AF31: ='Comparables Data'!U27/'Comparables Data'!U$30 -> 0.0045414629 | AG31: ='Comparables Data'!V27/'Comparables Data'!V$30 -> 0.048138078 | AH31: ='Comparables Data'!W27/'Comparables Data'!W$30 -> 0.047364126 | AJ31: ='Comparables Data'!Y27 -> Capital Work in Progress | AK31: ='Comparables Data'!AC27/'Comparables Data'!AC$30 -> 0.011634878 | AL31: ='Comparables Data'!AD27/'Comparables Data'!AD$30 -> 0.0059998613 | AM31: ='Comparables Data'!AE27/'Comparables Data'!AE$30 -> 0.029044614 | AN31: ='Comparables Data'!AF27/'Comparables Data'!AF$30 -> 0.0097733321 | AO31: ='Comparables Data'!AG27/'Comparables Data'!AG$30 -> 0.014451419 | AP31: ='Comparables Data'!AH27/'Comparables Data'!AH$30 -> 0.019119324 | AQ31: ='Comparables Data'!AI27/'Comparables Data'!AI$30 -> 0.063023511
B32: ='Data Sheet'!A64 -> Investments | C32: ='Data Sheet'!B64/'Data Sheet'!B$66 -> 0.24156373 | D32: ='Data Sheet'!C64/'Data Sheet'!C$66 -> 0.16084425 | E32: ='Data Sheet'!D64/'Data Sheet'!D$66 -> 0.14579419 | F32: ='Data Sheet'!E64/'Data Sheet'!E$66 -> 0.062273607 | G32: ='Data Sheet'!F64/'Data Sheet'!F$66 -> 0.039409369 | H32: ='Data Sheet'!G64/'Data Sheet'!G$66 -> 0.049939012 | I32: ='Data Sheet'!H64/'Data Sheet'!H$66 -> 0.039437853 | J32: ='Data Sheet'!I64/'Data Sheet'!I$66 -> 0.058925455 | ... L32: ='Data Sheet'!K64/'Data Sheet'!K$66 -> 0.054666533 | N32: ='Comparables Data'!A28 -> Investments | O32: ='Comparables Data'!B28/'Comparables Data'!B$30 -> 0.3145243 | P32: ='Comparables Data'!C28/'Comparables Data'!C$30 -> 0.3432839 | Q32: ='Comparables Data'!D28/'Comparables Data'!D$30 -> 0.34909151 | R32: ='Comparables Data'!E28/'Comparables Data'!E$30 -> 0.37075504 | S32: ='Comparables Data'!F28/'Comparables Data'!F$30 -> 0.33718294 | T32: ='Comparables Data'!G28/'Comparables Data'!G$30 -> 0.32179133 | U32: ='Comparables Data'!H28/'Comparables Data'!H$30 -> 0.34270874 | V32: ='Comparables Data'!I28/'Comparables Data'!I$30 -> 0.33910271 | ... X32: ='Comparables Data'!K28/'Comparables Data'!K$30 -> 0.40651948 | Z32: ='Comparables Data'!M28 -> Investments | AA32: ='Comparables Data'!P28/'Comparables Data'!P$30 -> 0 | AB32: ='Comparables Data'!Q28/'Comparables Data'!Q$30 -> 0.0043589553 | AC32: ='Comparables Data'!R28/'Comparables Data'!R$30 -> 0.00059042078 | AD32: ='Comparables Data'!S28/'Comparables Data'!S$30 -> 0 | AE32: ='Comparables Data'!T28/'Comparables Data'!T$30 -> 0 | AF32: ='Comparables Data'!U28/'Comparables Data'!U$30 -> 0 | AG32: ='Comparables Data'!V28/'Comparables Data'!V$30 -> 0 | AH32: ='Comparables Data'!W28/'Comparables Data'!W$30 -> 0.0016636681 | AJ32: ='Comparables Data'!Y28 -> Investments | AK32: ='Comparables Data'!AC28/'Comparables Data'!AC$30 -> 3.4855836e-05 | AL32: ='Comparables Data'!AD28/'Comparables Data'!AD$30 -> 3.4681279e-05 | AM32: ='Comparables Data'!AE28/'Comparables Data'!AE$30 -> 0 | AN32: ='Comparables Data'!AF28/'Comparables Data'!AF$30 -> 0 | AO32: ='Comparables Data'!AG28/'Comparables Data'!AG$30 -> 0 | AP32: ='Comparables Data'!AH28/'Comparables Data'!AH$30 -> 0 | AQ32: ='Comparables Data'!AI28/'Comparables Data'!AI$30 -> 2.4363503e-05
B33: ='Data Sheet'!A65 -> Other Assets | C33: ='Data Sheet'!B74/'Data Sheet'!B$66 -> 0.11524258 | D33: ='Data Sheet'!C74/'Data Sheet'!C$66 -> 0.15071101 | E33: ='Data Sheet'!D74/'Data Sheet'!D$66 -> 0.14198293 | F33: ='Data Sheet'!E74/'Data Sheet'!E$66 -> 0.18821019 | G33: ='Data Sheet'!F74/'Data Sheet'!F$66 -> 0.058699447 | H33: ='Data Sheet'!G74/'Data Sheet'!G$66 -> 0.057030607 | I33: ='Data Sheet'!H74/'Data Sheet'!H$66 -> 0.059895726 | J33: ='Data Sheet'!I74/'Data Sheet'!I$66 -> 0.057549466 | ... L33: ='Data Sheet'!K74/'Data Sheet'!K$66 -> 0.070919762 | N33: ='Comparables Data'!A29 -> Other Assets | O33: ='Comparables Data'!B35/'Comparables Data'!B$30 -> 0.09187718 | P33: ='Comparables Data'!C35/'Comparables Data'!C$30 -> 0.11019074 | Q33: ='Comparables Data'!D35/'Comparables Data'!D$30 -> 0.099500495 | R33: ='Comparables Data'!E35/'Comparables Data'!E$30 -> 0.064136617 | S33: ='Comparables Data'!F35/'Comparables Data'!F$30 -> 0.054530891 | T33: ='Comparables Data'!G35/'Comparables Data'!G$30 -> 0.089608376 | U33: ='Comparables Data'!H35/'Comparables Data'!H$30 -> 0.092668776 | V33: ='Comparables Data'!I35/'Comparables Data'!I$30 -> 0.049726132 | ... X33: ='Comparables Data'!K35/'Comparables Data'!K$30 -> 0.064663355 | Z33: ='Comparables Data'!M29 -> Other Assets | AA33: ='Comparables Data'!P35/'Comparables Data'!P$30 -> 0.13728731 | AB33: ='Comparables Data'!Q35/'Comparables Data'!Q$30 -> 0.13961641 | AC33: ='Comparables Data'!R35/'Comparables Data'!R$30 -> 0.13303188 | AD33: ='Comparables Data'!S35/'Comparables Data'!S$30 -> 0.11872206 | AE33: ='Comparables Data'!T35/'Comparables Data'!T$30 -> 0.12519105 | AF33: ='Comparables Data'!U35/'Comparables Data'!U$30 -> 0.15012289 | AG33: ='Comparables Data'!V35/'Comparables Data'!V$30 -> 0.12298552 | AH33: ='Comparables Data'!W35/'Comparables Data'!W$30 -> 0.13867682 | AJ33: ='Comparables Data'!Y29 -> Other Assets | AK33: ='Comparables Data'!AC35/'Comparables Data'!AC$30 -> 0.090750655 | AL33: ='Comparables Data'!AD35/'Comparables Data'!AD$30 -> 0.063973087 | AM33: ='Comparables Data'!AE35/'Comparables Data'!AE$30 -> 0.083361215 | AN33: ='Comparables Data'!AF35/'Comparables Data'!AF$30 -> 0.053873773 | AO33: ='Comparables Data'!AG35/'Comparables Data'!AG$30 -> 0.042872207 | AP33: ='Comparables Data'!AH35/'Comparables Data'!AH$30 -> 0.074676869 | AQ33: ='Comparables Data'!AI35/'Comparables Data'!AI$30 -> 0.056883908
B34: ='Data Sheet'!A67 -> Receivables | C34: ='Data Sheet'!B67/'Data Sheet'!B$66 -> 0.06908188 | D34: ='Data Sheet'!C67/'Data Sheet'!C$66 -> 0.073340052 | E34: ='Data Sheet'!D67/'Data Sheet'!D$66 -> 0.09748242 | F34: ='Data Sheet'!E67/'Data Sheet'!E$66 -> 0.057013844 | G34: ='Data Sheet'!F67/'Data Sheet'!F$66 -> 0.025574629 | H34: ='Data Sheet'!G67/'Data Sheet'!G$66 -> 0.031713613 | I34: ='Data Sheet'!H67/'Data Sheet'!H$66 -> 0.04213364 | J34: ='Data Sheet'!I67/'Data Sheet'!I$66 -> 0.038183695 | ... L34: ='Data Sheet'!K67/'Data Sheet'!K$66 -> 0.042376282 | N34: ='Comparables Data'!A31 -> Receivables | O34: ='Comparables Data'!B31/'Comparables Data'!B$30 -> 0.044264121 | P34: ='Comparables Data'!C31/'Comparables Data'!C$30 -> 0.041753631 | Q34: ='Comparables Data'!D31/'Comparables Data'!D$30 -> 0.056249428 | R34: ='Comparables Data'!E31/'Comparables Data'!E$30 -> 0.033145196 | S34: ='Comparables Data'!F31/'Comparables Data'!F$30 -> 0.033916408 | T34: ='Comparables Data'!G31/'Comparables Data'!G$30 -> 0.031891541 | U34: ='Comparables Data'!H31/'Comparables Data'!H$30 -> 0.034441768 | V34: ='Comparables Data'!I31/'Comparables Data'!I$30 -> 0.043876249 | ... X34: ='Comparables Data'!K31/'Comparables Data'!K$30 -> 0.041824933 | Z34: ='Comparables Data'!M31 -> Receivables | AA34: ='Comparables Data'!P31/'Comparables Data'!P$30 -> 0.16004958 | AB34: ='Comparables Data'!Q31/'Comparables Data'!Q$30 -> 0.069502152 | AC34: ='Comparables Data'!R31/'Comparables Data'!R$30 -> 0.071556119 | AD34: ='Comparables Data'!S31/'Comparables Data'!S$30 -> 0.073334011 | AE34: ='Comparables Data'!T31/'Comparables Data'!T$30 -> 0.078283736 | AF34: ='Comparables Data'!U31/'Comparables Data'!U$30 -> 0.091333288 | AG34: ='Comparables Data'!V31/'Comparables Data'!V$30 -> 0.084309105 | AH34: ='Comparables Data'!W31/'Comparables Data'!W$30 -> 0.080271985 | AJ34: ='Comparables Data'!Y31 -> Receivables | AK34: ='Comparables Data'!AC31/'Comparables Data'!AC$30 -> 0.087627572 | AL34: ='Comparables Data'!AD31/'Comparables Data'!AD$30 -> 0.11732677 | AM34: ='Comparables Data'!AE31/'Comparables Data'!AE$30 -> 0.099640043 | AN34: ='Comparables Data'!AF31/'Comparables Data'!AF$30 -> 0.11588052 | AO34: ='Comparables Data'!AG31/'Comparables Data'!AG$30 -> 0.095305046 | AP34: ='Comparables Data'!AH31/'Comparables Data'!AH$30 -> 0.070697513 | AQ34: ='Comparables Data'!AI31/'Comparables Data'!AI$30 -> 0.05535388
B35: ='Data Sheet'!A68 -> Inventory | C35: ='Data Sheet'!B68/'Data Sheet'!B$66 -> 0.1617853 | D35: ='Data Sheet'!C68/'Data Sheet'!C$66 -> 0.14068973 | E35: ='Data Sheet'!D68/'Data Sheet'!D$66 -> 0.13817167 | F35: ='Data Sheet'!E68/'Data Sheet'!E$66 -> 0.13729966 | G35: ='Data Sheet'!F68/'Data Sheet'!F$66 -> 0.052065755 | H35: ='Data Sheet'!G68/'Data Sheet'!G$66 -> 0.058094347 | I35: ='Data Sheet'!H68/'Data Sheet'!H$66 -> 0.058171518 | J35: ='Data Sheet'!I68/'Data Sheet'!I$66 -> 0.051242849 | ... L35: ='Data Sheet'!K68/'Data Sheet'!K$66 -> 0.060059194 | N35: ='Comparables Data'!A32 -> Inventory | O35: ='Comparables Data'!B32/'Comparables Data'!B$30 -> 0.14519399 | P35: ='Comparables Data'!C32/'Comparables Data'!C$30 -> 0.11667166 | Q35: ='Comparables Data'!D32/'Comparables Data'!D$30 -> 0.10955764 | R35: ='Comparables Data'!E32/'Comparables Data'!E$30 -> 0.11485246 | S35: ='Comparables Data'!F32/'Comparables Data'!F$30 -> 0.14095788 | T35: ='Comparables Data'!G32/'Comparables Data'!G$30 -> 0.14073459 | U35: ='Comparables Data'!H32/'Comparables Data'!H$30 -> 0.13714352 | V35: ='Comparables Data'!I32/'Comparables Data'!I$30 -> 0.15424815 | ... X35: ='Comparables Data'!K32/'Comparables Data'!K$30 -> 0.19855515 | Z35: ='Comparables Data'!M32 -> Inventory | AA35: ='Comparables Data'!P32/'Comparables Data'!P$30 -> 0.18420163 | AB35: ='Comparables Data'!Q32/'Comparables Data'!Q$30 -> 0.20353539 | AC35: ='Comparables Data'!R32/'Comparables Data'!R$30 -> 0.24348377 | AD35: ='Comparables Data'!S32/'Comparables Data'!S$30 -> 0.24153799 | AE35: ='Comparables Data'!T32/'Comparables Data'!T$30 -> 0.25016482 | AF35: ='Comparables Data'!U32/'Comparables Data'!U$30 -> 0.25637961 | AG35: ='Comparables Data'!V32/'Comparables Data'!V$30 -> 0.30323243 | AH35: ='Comparables Data'!W32/'Comparables Data'!W$30 -> 0.30546899 | AJ35: ='Comparables Data'!Y32 -> Inventory | AK35: ='Comparables Data'!AC32/'Comparables Data'!AC$30 -> 0.26688417 | AL35: ='Comparables Data'!AD32/'Comparables Data'!AD$30 -> 0.29386141 | AM35: ='Comparables Data'!AE32/'Comparables Data'!AE$30 -> 0.37625322 | AN35: ='Comparables Data'!AF32/'Comparables Data'!AF$30 -> 0.29786294 | AO35: ='Comparables Data'!AG32/'Comparables Data'!AG$30 -> 0.40432337 | AP35: ='Comparables Data'!AH32/'Comparables Data'!AH$30 -> 0.37835087 | AQ35: ='Comparables Data'!AI32/'Comparables Data'!AI$30 -> 0.37802412
B36: ='Data Sheet'!A69 -> Cash & Bank | C36: ='Data Sheet'!B69/'Data Sheet'!B$66 -> 0.11638864 | D36: ='Data Sheet'!C69/'Data Sheet'!C$66 -> 0.19510693 | E36: ='Data Sheet'!D69/'Data Sheet'!D$66 -> 0.20167481 | F36: ='Data Sheet'!E69/'Data Sheet'!E$66 -> 0.25370913 | G36: ='Data Sheet'!F69/'Data Sheet'!F$66 -> 0.065042188 | H36: ='Data Sheet'!G69/'Data Sheet'!G$66 -> 0.054548549 | I36: ='Data Sheet'!H69/'Data Sheet'!H$66 -> 0.064014669 | J36: ='Data Sheet'!I69/'Data Sheet'!I$66 -> 0.096306489 | ... L36: ='Data Sheet'!K69/'Data Sheet'!K$66 -> 0.040733402 | N36: ='Comparables Data'!A33 -> Cash & Bank | O36: ='Comparables Data'!B33/'Comparables Data'!B$30 -> 0.053085674 | P36: ='Comparables Data'!C33/'Comparables Data'!C$30 -> 0.045136368 | Q36: ='Comparables Data'!D33/'Comparables Data'!D$30 -> 0.057876855 | R36: ='Comparables Data'!E33/'Comparables Data'!E$30 -> 0.094131023 | S36: ='Comparables Data'!F33/'Comparables Data'!F$30 -> 0.063163937 | T36: ='Comparables Data'!G33/'Comparables Data'!G$30 -> 0.060293523 | U36: ='Comparables Data'!H33/'Comparables Data'!H$30 -> 0.056858155 | V36: ='Comparables Data'!I33/'Comparables Data'!I$30 -> 0.078663408 | ... X36: ='Comparables Data'!K33/'Comparables Data'!K$30 -> 0.032079258 | Z36: ='Comparables Data'!M33 -> Cash & Bank | AA36: ='Comparables Data'!P33/'Comparables Data'!P$30 -> 0.017015363 | AB36: ='Comparables Data'!Q33/'Comparables Data'!Q$30 -> 0.072303012 | AC36: ='Comparables Data'!R33/'Comparables Data'!R$30 -> 0.084286167 | AD36: ='Comparables Data'!S33/'Comparables Data'!S$30 -> 0.044087769 | AE36: ='Comparables Data'!T33/'Comparables Data'!T$30 -> 0.037812041 | AF36: ='Comparables Data'!U33/'Comparables Data'!U$30 -> 0.02561198 | AG36: ='Comparables Data'!V33/'Comparables Data'!V$30 -> 0.033681751 | AH36: ='Comparables Data'!W33/'Comparables Data'!W$30 -> 0.016293234 | AJ36: ='Comparables Data'!Y33 -> Cash & Bank | AK36: ='Comparables Data'!AC33/'Comparables Data'!AC$30 -> 0.030714963 | AL36: ='Comparables Data'!AD33/'Comparables Data'!AD$30 -> 0.027842131 | AM36: ='Comparables Data'!AE33/'Comparables Data'!AE$30 -> 0.02696217 | AN36: ='Comparables Data'!AF33/'Comparables Data'!AF$30 -> 0.025683674 | AO36: ='Comparables Data'!AG33/'Comparables Data'!AG$30 -> 0.016354507 | AP36: ='Comparables Data'!AH33/'Comparables Data'!AH$30 -> 0.016050412 | AQ36: ='Comparables Data'!AI33/'Comparables Data'!AI$30 -> 0.015665733
B38: Total Assets | C38: ='Data Sheet'!B66/'Data Sheet'!B$66 -> 1 | D38: ='Data Sheet'!C66/'Data Sheet'!C$66 -> 1 | E38: ='Data Sheet'!D66/'Data Sheet'!D$66 -> 1 | F38: ='Data Sheet'!E66/'Data Sheet'!E$66 -> 1 | G38: ='Data Sheet'!F66/'Data Sheet'!F$66 -> 1 | H38: ='Data Sheet'!G66/'Data Sheet'!G$66 -> 1 | I38: ='Data Sheet'!H66/'Data Sheet'!H$66 -> 1 | J38: ='Data Sheet'!I66/'Data Sheet'!I$66 -> 1 | ... L38: ='Data Sheet'!K66/'Data Sheet'!K$66 -> 1 | N38: Total Assets | O38: ='Comparables Data'!B30/'Comparables Data'!B$30 -> 1 | P38: ='Comparables Data'!C30/'Comparables Data'!C$30 -> 1 | Q38: ='Comparables Data'!D30/'Comparables Data'!D$30 -> 1 | R38: ='Comparables Data'!E30/'Comparables Data'!E$30 -> 1 | S38: ='Comparables Data'!F30/'Comparables Data'!F$30 -> 1 | T38: ='Comparables Data'!G30/'Comparables Data'!G$30 -> 1 | U38: ='Comparables Data'!H30/'Comparables Data'!H$30 -> 1 | V38: ='Comparables Data'!I30/'Comparables Data'!I$30 -> 1 | ... X38: ='Comparables Data'!K30/'Comparables Data'!K$30 -> 1 | Z38: Total Assets | AA38: ='Comparables Data'!P30/'Comparables Data'!P$30 -> 1 | AB38: ='Comparables Data'!Q30/'Comparables Data'!Q$30 -> 1 | AC38: ='Comparables Data'!R30/'Comparables Data'!R$30 -> 1 | AD38: ='Comparables Data'!S30/'Comparables Data'!S$30 -> 1 | AE38: ='Comparables Data'!T30/'Comparables Data'!T$30 -> 1 | AF38: ='Comparables Data'!U30/'Comparables Data'!U$30 -> 1 | AG38: ='Comparables Data'!V30/'Comparables Data'!V$30 -> 1 | AH38: ='Comparables Data'!W30/'Comparables Data'!W$30 -> 1 | AJ38: Total Assets | AK38: ='Comparables Data'!AC30/'Comparables Data'!AC$30 -> 1 | AL38: ='Comparables Data'!AD30/'Comparables Data'!AD$30 -> 1 | AM38: ='Comparables Data'!AE30/'Comparables Data'!AE$30 -> 1 | AN38: ='Comparables Data'!AF30/'Comparables Data'!AF$30 -> 1 | AO38: ='Comparables Data'!AG30/'Comparables Data'!AG$30 -> 1 | AP38: ='Comparables Data'!AH30/'Comparables Data'!AH$30 -> 1 | AQ38: ='Comparables Data'!AI30/'Comparables Data'!AI$30 -> 1

Sheet Trend Analysis
B2: ="Trend Analysis for "&'Data Sheet'!B1 -> Trend Analysis for HINDUSTAN UNILEVER LTD
B3: Year | C3: Revenue | D3: YOY Growth
B4: ='Historical FS'!C3 -> 42825 | C4: =TRANSPOSE('Historical FS'!C6:Q6) -> 33162 | D4: 0
B5: ='Historical FS'!D3 -> 43190 | C5: ='Historical FS'!D6 -> 35545 | D5: =(C5-C4)/C4 -> 0.071859357
B6: ='Historical FS'!E3 -> 43555 | C6: ='Historical FS'!E6 -> 39310 | D6: =(C6-C5)/C5 -> 0.10592207
B7: ='Historical FS'!F3 -> 43921 | C7: ='Historical FS'!F6 -> 39783 | D7: =(C7-C6)/C6 -> 0.012032562
B8: ='Historical FS'!G3 -> 44286 | C8: ='Historical FS'!G6 -> 47028 | D8: =(C8-C7)/C7 -> 0.18211296
B9: ='Historical FS'!H3 -> 44651 | C9: ='Historical FS'!H6 -> 52446 | D9: =(C9-C8)/C8 -> 0.11520796
B10: ='Historical FS'!I3 -> 45016 | C10: ='Historical FS'!I6 -> 60580 | D10: =(C10-C9)/C9 -> 0.15509286
B11: ='Historical FS'!J3 -> 45382 | C11: ='Historical FS'!J6 -> 61896 | D11: =(C11-C10)/C10 -> 0.021723341
B12: ='Historical FS'!K3 -> 45747 | C12: ='Historical FS'!K6 -> 61328 | D12: =(C12-C11)/C11 -> -0.0091766835
B13: ='Historical FS'!L3 -> 46112 | C13: ='Historical FS'!L6 -> 64468 | D13: =(C13-C12)/C12 -> 0.051200104
B14: ='Historical FS'!M3 -> 46477 | C14: ='Historical FS'!M6 -> 70982.404 | D14: =(C14-C13)/C13 -> 0.10104865
B15: ='Historical FS'!N3 -> 46842 | C15: ='Historical FS'!N6 -> 75182.241 | D15: =(C15-C14)/C14 -> 0.059167301
B16: ='Historical FS'!O3 -> 47207 | C16: ='Historical FS'!O6 -> 79176.45 | D16: =(C16-C15)/C15 -> 0.053127024
B17: ='Historical FS'!P3 -> 47572 | C17: ='Historical FS'!P6 -> 83129.771 | D17: =(C17-C16)/C16 -> 0.049930513
B18: ='Historical FS'!Q3 -> 47937 | C18: ='Historical FS'!Q6 -> 86132.088 | D18: =(C18-C17)/C17 -> 0.036116025

Sheet Comparables Data
A1: ITC LTD | B1: profit and loss | M1: PROFIT & LOSS | O1: HINDUSTAN FOODS LTD | Y1: PROFIT & LOSS | Z1: GODAVARI BIOREFINERIES LTD
A2: Report Date | B2: 42825 | C2: 43190 | D2: 43555 | E2: 43921 | F2: 44286 | G2: 44651 | H2: 45016 | I2: 45382 | J2: 45747 | K2: 46112 | M2: Report Date | P2: 43555 | Q2: 43921 | R2: 44286 | S2: 44651 | T2: 45016 | U2: 45382 | V2: 45747 | W2: 46112 | Y2: Report Date | AC2: 43921 | AD2: 44286 | AE2: 44651 | AF2: 45016 | AG2: 45382 | AH2: 45747 | AI2: 46112
A3: Sales | B3: 42767.6 | C3: 43448.94 | D3: 48339.58 | E3: 49387.7 | F3: 49257.45 | G3: 60644.54 | H3: 70919.03 | I3: 67931.94 | J3: 75323.34 | K3: 78868.4 | M3: Sales | P3: 491.91 | Q3: 771.9 | R3: 1386.35 | S3: 2040.1 | T3: 2598.13 | U3: 2754.71 | V3: 3564.38 | W3: 4251.04 | Y3: Sales | AC3: 1459.15 | AD3: 1538.17 | AE3: 1702.33 | AF3: 2014.69 | AG3: 1686.67 | AH3: 1870.25 | AI3: 1987.94
A4: Raw Material Cost | B4: 15456.59 | C4: 14827.72 | D4: 17623.52 | E4: 18048.6 | F4: 20776.71 | G4: 27071.07 | H4: 29364.36 | I4: 27348.57 | J4: 32704.37 | K4: 35098.34 | M4: Raw Material Cost | P4: 341.3 | Q4: 574.84 | R4: 1064.92 | S4: 1576.81 | T4: 1796.66 | U4: 1895.35 | V4: 2304.66 | W4: 3349.62 | Y4: Raw Material Cost | AC4: 889.68 | AD4: 1094.93 | AE4: 1230.02 | AF4: 1323.7 | AG4: 1545.46 | AH4: 1260.55 | AI4: 1517.97
A5: Change in Inventory | B5: -592.57 | C5: -1027.76 | D5: 203.19 | E5: 703.13 | F5: 645.27 | G5: 686 | H5: 358.59 | I5: 367.77 | J5: 725.65 | K5: 2550.46 | M5: Change in Inventory | P5: 7.2 | Q5: 30.41 | R5: 9.26 | S5: 35.69 | T5: 14.2 | U5: 59.83 | V5: 37.8 | W5: 21.85 | Y5: Change in Inventory | AC5: -182.16 | AD5: 37.69 | AE5: 41.53 | AF5: -60.31 | AG5: 368.43 | AH5: -124.61 | AI5: 91.36
A6: Power and Fuel | B6: 584.33 | C6: 653.5 | D6: 746.73 | E6: 780.85 | F6: 699.56 | G6: 889.77 | H6: 1232.34 | I6: 952.9 | J6: 975.35 | M6: Power and Fuel | P6: 8.82 | Q6: 9.64 | R6: 13.3 | S6: 20.63 | T6: 31.6 | U6: 39.92 | V6: 62.02 | Y6: Power and Fuel | AC6: 78.75 | AD6: 83.79 | AE6: 99.74 | AF6: 146.16 | AG6: 80.13 | AH6: 71.74
A7: Other Mfr. Exp | B7: 1683.9 | C7: 1697.62 | D7: 1871.01 | E7: 1908.29 | F7: 1587.18 | G7: 1887.67 | H7: 2327.8 | I7: 2183.76 | J7: 2345.36 | M7: Other Mfr. Exp | P7: 81.37 | Q7: 121.58 | R7: 182.72 | S7: 295.94 | T7: 524.12 | U7: 530.41 | V7: 646.69 | Y7: Other Mfr. Exp | AC7: 66.7 | AD7: 76.54 | AE7: 91.34 | AF7: 105.73 | AG7: 98.48 | AH7: 99.04
A8: Employee Cost | B8: 3631.73 | C8: 3760.9 | D8: 4177.88 | E8: 4295.79 | F8: 4463.33 | G8: 4890.55 | H8: 5736.22 | I8: 5548.53 | J8: 6169.78 | K8: 6781.5 | M8: Employee Cost | P8: 18.54 | Q8: 24.31 | R8: 30.68 | S8: 40.9 | T8: 55.79 | U8: 82.85 | V8: 222.6 | W8: 252.51 | Y8: Employee Cost | AC8: 84.46 | AD8: 85.79 | AE8: 99.61 | AF8: 116.82 | AG8: 118.45 | AH8: 125.71 | AI8: 135.22
A9: Selling and admin | B9: 4179.74 | C9: 3954.87 | D9: 4546.39 | E9: 4488.63 | F9: 4236.77 | G9: 4858.38 | H9: 5604.08 | I9: 5312.45 | J9: 5793.29 | M9: Selling and admin | P9: 12.95 | Q9: 14.32 | R9: 17.73 | S9: 22.85 | T9: 26.45 | U9: 35.95 | V9: 63.24 | Y9: Selling and admin | AC9: 50.8 | AD9: 68.26 | AE9: 82.95 | AF9: 112.97 | AG9: 78.05 | AH9: 82.07
A10: Other Expenses | B10: 1169.23 | C10: 1005.98 | D10: 1039.85 | E10: 1225.13 | F10: 1074.39 | G10: 1109.95 | H10: 1308.56 | I10: 1765.97 | J10: 2221.39 | K10: 12221.11 | M10: Other Expenses | P10: 3.57 | Q10: 2.61 | R10: 4.8 | S10: 6.02 | T10: 4.36 | U10: 8.14 | V10: 8.53 | W10: 307.82 | Y10: Other Expenses | AC10: 3.27 | AD10: 8.93 | AE10: 6.05 | AF10: 1.55 | AG10: 0.77 | AH10: 2.64 | AI10: 298.99
A11: Other Income | B11: 1758.63 | C11: 2239.81 | D11: 2080.44 | E11: 2417.32 | F11: 2576.95 | G11: 1909.72 | H11: 2097.64 | I11: 3330.45 | J11: 17794.88 | K11: 2511.18 | M11: Other Income | P11: 0.65 | Q11: 1.21 | R11: 2.66 | S11: 3.69 | T11: 4.51 | U11: 7.17 | V11: 14.55 | W11: 9.08 | Y11: Other Income | AC11: 13.65 | AD11: 8.21 | AE11: 6.38 | AF11: 7.17 | AG11: 14.17 | AH11: 16.42 | AI11: -18.93
A12: Depreciation | B12: 1152.79 | C12: 1236.28 | D12: 1396.61 | E12: 1644.91 | F12: 1645.59 | G12: 1732.41 | H12: 1809.01 | I12: 1518.05 | J12: 1646.32 | K12: 1710.53 | M12: Depreciation | P12: 7.46 | Q12: 11.28 | R12: 17.2 | S12: 24.51 | T12: 37.41 | U12: 54.8 | V12: 79.73 | W12: 90.08 | Y12: Depreciation | AC12: 44.95 | AD12: 47.13 | AE12: 48.03 | AF12: 50.08 | AG12: 59.93 | AH12: 50.06 | AI12: 54.49
A13: Interest | B13: 49.03 | C13: 115.01 | D13: 71.4 | E13: 81.38 | F13: 57.97 | G13: 59.99 | H13: 77.77 | I13: 39.11 | J13: 45.06 | K13: 85.17 | M13: Interest | P13: 7.52 | Q13: 11.13 | R13: 18.86 | S13: 20.34 | T13: 35.95 | U13: 56.88 | V13: 81.33 | W13: 82.3 | Y13: Interest | AC13: 68.74 | AD13: 72.38 | AE13: 60.44 | AF13: 72.79 | AG13: 75.56 | AH13: 71.79 | AI13: 49.13
A14: Profit before tax | B14: 16026.32 | C14: 17409.11 | D14: 19149.82 | E14: 20034.57 | F14: 17938.17 | G14: 20740.47 | H14: 25915.12 | I14: 26960.82 | J14: 41942.95 | K14: 28033.39 | M14: Profit before tax | P14: 18.23 | Q14: 33.81 | R14: 48.06 | S14: 71.48 | T14: 104.5 | U14: 117.41 | V14: 147.93 | W14: 199.64 | Y14: Profit before tax | AC14: 3.29 | AD14: 46.32 | AE14: 32.06 | AF14: 31.75 | AG14: 12.44 | AH14: -1.54 | AI14: 4.57
A15: Tax | B15: 5549.09 | C15: 5916.43 | D15: 6313.92 | E15: 4441.79 | F15: 4555.29 | G15: 5237.34 | H15: 6438.4 | I15: 6209.46 | J15: 6890.47 | K15: 7015.24 | M15: Tax | P15: 6.31 | Q15: 11.9 | R15: 13.67 | S15: 26.82 | T15: 33.39 | U15: 24.39 | V15: 38.29 | W15: 50.61 | Y15: Tax | AC15: -0.78 | AD15: 19.17 | AE15: 12.97 | AF15: 12.12 | AG15: 0.15 | AH15: 21.88 | AI15: 1.04
A16: Net profit | B16: 10289.44 | C16: 11271.2 | D16: 12592.33 | E16: 15306.23 | F16: 13161.19 | G16: 15242.66 | H16: 19191.66 | I16: 20458.78 | J16: 34746.63 | K16: 20689.47 | M16: Net profit | P16: 11.91 | Q16: 21.91 | R16: 34.4 | S16: 44.66 | T16: 71.12 | U16: 93.02 | V16: 109.64 | W16: 149.03 | Y16: Net profit | AC16: 4.06 | AD16: 27.15 | AE16: 19.1 | AF16: 19.64 | AG16: 12.3 | AH16: -23.41 | AI16: 3.53
A17: Dividend Amount | B17: 5770.02 | C17: 6285.21 | D17: 7048.7 | E17: 12476.58 | F17: 13231.96 | G17: 14171.8 | H17: 19263.4 | I17: 17166.46 | J17: 17957.73 | K17: 18167.78 | M17: Dividend Amount | Y17: Dividend Amount
A19: Balance sheet | M19: BALANCE SHEET | Y19: BALANCE SHEET
A20: Report Date | B20: 42825 | C20: 43190 | D20: 43555 | E20: 43921 | F20: 44286 | G20: 44651 | H20: 45016 | I20: 45382 | J20: 45747 | K20: 46112 | M20: Report Date | P20: 43555 | Q20: 43921 | R20: 44286 | S20: 44651 | T20: 45016 | U20: 45382 | V20: 45747 | W20: 46112 | Y20: Report Date | AC20: 43921 | AD20: 44286 | AE20: 44651 | AF20: 45016 | AG20: 45382 | AH20: 45747 | AI20: 46112
A21: Equity Share Capital | B21: 1214.74 | C21: 1220.43 | D21: 1225.86 | E21: 1229.22 | F21: 1230.88 | G21: 1232.33 | H21: 1242.8 | I21: 1248.47 | J21: 1251.41 | K21: 1252.95 | M21: Equity Share Capital | P21: 13.49 | Q21: 21.2 | R21: 21.2 | S21: 22.55 | T21: 22.55 | U21: 22.91 | V21: 23.5 | W21: 23.9 | Y21: Equity Share Capital | AC21: 41.94 | AD21: 41.94 | AE21: 41.94 | AF21: 41.94 | AG21: 41.94 | AH21: 51.18 | AI21: 51.18
A22: Reserves | B22: 45198.19 | C22: 51289.68 | D22: 57915.01 | E22: 64044.04 | F22: 59116.46 | G22: 61223.24 | H22: 67912.46 | I22: 73258.53 | J22: 68778.64 | K22: 71254.35 | M22: Reserves | P22: 50.87 | Q22: 164.98 | R22: 199.47 | S22: 280.72 | T22: 351.52 | U22: 623.22 | V22: 867.52 | W22: 1141.18 | Y22: Reserves | AC22: 385.19 | AD22: 411.98 | AE22: 431.06 | AF22: 447.51 | AG22: 458.74 | AH22: 730.79 | AI22: 737.11
A23: Borrowings | B23: 45.72 | C23: 35.92 | D23: 13.44 | E23: 277.45 | F23: 270.83 | G23: 249.44 | H23: 306.04 | I23: 303.43 | J23: 284.54 | K23: 2399.06 | M23: Borrowings | P23: 99.5 | Q23: 165.07 | R23: 217.8 | S23: 350.2 | T23: 515.8 | U23: 726.52 | V23: 892.33 | W23: 1088.26 | Y23: Borrowings | AC23: 589.06 | AD23: 569.22 | AE23: 635.61 | AF23: 735.89 | AG23: 654.59 | AH23: 489.77 | AI23: 530.76
A24: Other Liabilities | B24: 9439.67 | C24: 11694.85 | D24: 12584.73 | E24: 11760.04 | F24: 13142.59 | G24: 14491.01 | H24: 16369.66 | I24: 16943.54 | J24: 17688.11 | K24: 18886.02 | M24: Other Liabilities | P24: 102.37 | Q24: 187.87 | R24: 255.95 | S24: 330.93 | T24: 444.89 | U24: 551.84 | V24: 699.3 | W24: 920.37 | Y24: Other Liabilities | AC24: 418.29 | AD24: 418.56 | AE24: 624.93 | AF24: 518.18 | AG24: 836.23 | AH24: 683.35 | AI24: 733.2
A25: Total | B25: 55898.32 | C25: 64240.88 | D25: 71739.04 | E25: 77310.75 | F25: 73760.76 | G25: 77196.02 | H25: 85830.96 | I25: 91753.97 | J25: 88002.7 | K25: 93792.38 | M25: Total | P25: 266.23 | Q25: 539.12 | R25: 694.42 | S25: 984.4 | T25: 1334.76 | U25: 1924.49 | V25: 2482.65 | W25: 3173.71 | Y25: Total | AC25: 1434.48 | AD25: 1441.7 | AE25: 1733.54 | AF25: 1743.52 | AG25: 1991.5 | AH25: 1955.09 | AI25: 2052.25
A26: Net Block | B26: 15893.48 | C26: 16523.96 | D26: 19374.19 | E26: 21713.34 | F26: 23298.48 | G26: 24231.59 | H26: 25851.27 | I26: 27820.22 | J26: 21954.85 | K26: 22545 | M26: Net Block | P26: 133.16 | Q26: 249.76 | R26: 270.86 | S26: 427.01 | T26: 553.67 | U26: 908.38 | V26: 1012.06 | W26: 1302.05 | Y26: Net Block | AC26: 734.96 | AD26: 707.82 | AE26: 666.96 | AF26: 866.4 | AG26: 849.76 | AH26: 862.4 | AI26: 884.57
A27: Capital Work in Progress | B27: 3729.89 | C27: 5508.33 | D27: 4136.42 | E27: 3256.46 | F27: 4011.29 | G27: 3225.54 | H27: 3003.3 | I27: 2860.78 | J27: 1090.91 | K27: 1499.41 | M27: Capital Work in Progress | P27: 0.34 | Q27: 25.56 | R27: 53.47 | S27: 87.16 | T27: 125.12 | U27: 8.74 | V27: 119.51 | W27: 150.32 | Y27: Capital Work in Progress | AC27: 16.69 | AD27: 8.65 | AE27: 50.35 | AF27: 17.04 | AG27: 28.78 | AH27: 37.38 | AI27: 129.34
A28: Investments | B28: 17581.38 | C28: 22052.86 | D28: 25043.49 | E28: 28663.35 | F28: 24870.87 | G28: 24841.01 | H28: 29415.02 | I28: 31114.02 | J28: 34719.82 | K28: 38128.43 | M28: Investments | Q28: 2.35 | R28: 0.41 | W28: 5.28 | Y28: Investments | AC28: 0.05 | AD28: 0.05 | AI28: 0.05
A29: Other Assets | B29: 18693.57 | C29: 20155.73 | D29: 23184.94 | E29: 23677.6 | F29: 21580.12 | G29: 24897.88 | H29: 27561.37 | I29: 29958.95 | J29: 30237.12 | K29: 31619.54 | M29: Other Assets | P29: 132.73 | Q29: 261.45 | R29: 369.68 | S29: 470.23 | T29: 655.97 | U29: 1007.37 | V29: 1351.08 | W29: 1716.06 | Y29: Other Assets | AC29: 682.78 | AD29: 725.18 | AE29: 1016.23 | AF29: 860.08 | AG29: 1112.96 | AH29: 1055.31 | AI29: 1038.29
A30: Total | B30: 55898.32 | C30: 64240.88 | D30: 71739.04 | E30: 77310.75 | F30: 73760.76 | G30: 77196.02 | H30: 85830.96 | I30: 91753.97 | J30: 88002.7 | K30: 93792.38 | M30: Total | P30: 266.23 | Q30: 539.12 | R30: 694.42 | S30: 984.4 | T30: 1334.76 | U30: 1924.49 | V30: 2482.65 | W30: 3173.71 | Y30: Total | AC30: 1434.48 | AD30: 1441.7 | AE30: 1733.54 | AF30: 1743.52 | AG30: 1991.5 | AH30: 1955.09 | AI30: 2052.25
A31: Receivables | B31: 2474.29 | C31: 2682.29 | D31: 4035.28 | E31: 2562.48 | F31: 2501.7 | G31: 2461.9 | H31: 2956.17 | I31: 4025.82 | J31: 4719.67 | K31: 3922.86 | M31: Receivables | P31: 42.61 | Q31: 37.47 | R31: 49.69 | S31: 72.19 | T31: 104.49 | U31: 175.77 | V31: 209.31 | W31: 254.76 | Y31: Receivables | AC31: 125.7 | AD31: 169.15 | AE31: 172.73 | AF31: 202.04 | AG31: 189.8 | AH31: 138.22 | AI31: 113.6
A32: Inventory | B32: 8116.1 | C32: 7495.09 | D32: 7859.56 | E32: 8879.33 | F32: 10397.16 | G32: 10864.15 | H32: 11771.16 | I32: 14152.88 | J32: 15637.56 | K32: 18622.96 | M32: Inventory | P32: 49.04 | Q32: 109.73 | R32: 169.08 | S32: 237.77 | T32: 333.91 | U32: 493.4 | V32: 752.82 | W32: 969.47 | Y32: Inventory | AC32: 382.84 | AD32: 423.66 | AE32: 652.25 | AF32: 519.33 | AG32: 805.21 | AH32: 739.71 | AI32: 775.8
A33: Cash & Bank | B33: 2967.4 | C33: 2899.6 | D33: 4152.03 | E33: 7277.34 | F33: 4659.02 | G33: 4654.42 | H33: 4880.19 | I33: 7217.68 | J33: 4012.36 | K33: 3008.79 | M33: Cash & Bank | P33: 4.53 | Q33: 38.98 | R33: 58.53 | S33: 43.4 | T33: 50.47 | U33: 49.29 | V33: 83.62 | W33: 51.71 | Y33: Cash & Bank | AC33: 44.06 | AD33: 40.14 | AE33: 46.74 | AF33: 44.78 | AG33: 32.57 | AH33: 31.38 | AI33: 32.15
A35: other ssets | B35: =B29-SUM(B31:B33) -> 5135.78 | C35: =C29-SUM(C31:C33) -> 7078.75 | D35: =D29-SUM(D31:D33) -> 7138.07 | E35: =E29-SUM(E31:E33) -> 4958.45 | F35: =F29-SUM(F31:F33) -> 4022.24 | G35: =G29-SUM(G31:G33) -> 6917.41 | H35: =H29-SUM(H31:H33) -> 7953.85 | I35: =I29-SUM(I31:I33) -> 4562.57 | ... K35: =K29-SUM(K31:K33) -> 6064.93 | M35: other assets | P35: =P29-SUM(P31:P33) -> 36.55 | Q35: =Q29-SUM(Q31:Q33) -> 75.27 | R35: =R29-SUM(R31:R33) -> 92.38 | S35: =S29-SUM(S31:S33) -> 116.87 | T35: =T29-SUM(T31:T33) -> 167.1 | U35: =U29-SUM(U31:U33) -> 288.91 | V35: =V29-SUM(V31:V33) -> 305.33 | W35: =W29-SUM(W31:W33) -> 440.12 | Y35: Other Assets | AC35: =AC29-SUM(AC31:AC33) -> 130.18 | AD35: =AD29-SUM(AD31:AD33) -> 92.23 | AE35: =AE29-SUM(AE31:AE33) -> 144.51 | AF35: =AF29-SUM(AF31:AF33) -> 93.93 | AG35: =AG29-SUM(AG31:AG33) -> 85.38 | AH35: =AH29-SUM(AH31:AH33) -> 146 | AI35: =AI29-SUM(AI31:AI33) -> 116.74

Sheet Manual Data
A1: Cash from Operating Activity - | B1: 3292 | C1: 4171 | D1: 5185 | E1: 6059 | F1: 5800 | G1: 7623 | H1: 9163 | I1: 9048 | J1: 9991 | K1: 15469 | L1: 11886 | M1: 10999
A2: Profit from operations | B2: 5510 | C2: 6025 | D2: 6512 | E2: 7485 | F2: 8909 | G2: 9723 | H2: 11672 | I2: 12829 | J2: 14089 | K2: 14537 | L2: 14942 | M2: 15153
A3: Receivables | B3: 3 | C3: -257 | D3: 173 | E3: 0 | F3: 0 | G3: 0 | H3: 0 | I3: 0 | J3: 0 | K3: 0 | L3: 0 | M3: 0
A4: Inventory | B4: 91 | C4: 89 | D4: 37 | E4: -146 | F4: -195 | G4: -331 | H4: -543 | I4: -758 | J4: -339 | K4: 74 | L4: -584 | M4: -692
A5: Payables | B5: -327 | C5: 164 | D5: 501 | E5: 0 | F5: 0 | G5: 0 | H5: 0 | I5: 0 | J5: 0 | K5: 0 | L5: 0 | M5: 0
A6: Loans Advances | B6: -148 | C6: 0 | D6: 0 | E6: 0 | F6: 0 | G6: 0 | H6: 0 | I6: 0 | J6: 0 | K6: 0 | L6: 0 | M6: 0
A7: Operating Deposits | B7: 0 | C7: 0 | D7: -46 | E7: 0 | F7: 0 | G7: 0 | H7: 0 | I7: 0 | J7: 0 | K7: 0 | L7: 0 | M7: 0
A8: Other WC items | B8: 38 | C8: -77 | D8: -99 | E8: 982 | F8: -147 | G8: 742 | H8: 442 | I8: -242 | J8: -621 | K8: 1239 | L8: -204 | M8: 1378
A9: Working capital changes | B9: -342 | C9: -81 | D9: 566 | E9: 836 | F9: -342 | G9: 411 | H9: -101 | I9: -1000 | J9: -960 | K9: 1313 | L9: -788 | M9: 686
A10: Direct taxes | B10: -1862 | C10: -1765 | D10: -1859 | E10: -2264 | F10: -2767 | G10: -2505 | H10: -2407 | I10: -2784 | J10: -3138 | K10: -381 | L10: -2268 | M10: -4840
A11: Other operating items | B11: -14 | C11: -8 | D11: -21 | E11: 0 | F11: 0 | G11: 0 | H11: 0 | I11: 0 | J11: 0 | K11: 0 | L11: 0 | M11: 0
A12: Exceptional CF items | B12: 0 | C12: 0 | D12: -13 | E12: 2 | F12: 0 | G12: -6 | H12: -1 | I12: 3 | J12: 0 | K12: 0 | L12: 0 | M12: 0
... A35: Other financing items | B35: -533 | C35: -685 | D35: -728 | E35: -781 | F35: -928 | G35: -1061 | H35: 0 | I35: 0 | J35: -2 | K35: 0 | L35: 0 | M35: 0
A37: Current Liablitity | J37: =120280000/10000 -> 12028 | K37: =128790000/10000 -> 12879 | L37: =165370000/10000 -> 16537 | M37: =155490000/10000 -> 15549
A38: Non-Current Liability | J38: =105370000/10000 -> 10537 | K38: =141970000/10000 -> 14197 | L38: =137340000/10000 -> 13734 | M38: =151960000/10000 -> 15196
A39: Trade payables | D39: 6186 | E39: 7170 | F39: 7206 | G39: 7535 | H39: 8802 | I39: 9068 | J39: 9574 | K39: 10486 | L39: 11315 | M39: 13325

Sheet Data Sheet2
A1: Numbers | B1: Breakdown | C1: Total Assets | D1: Current Assets | E1: Total non-current assets | F1: Total Liabilities Net Minority Interest | G1: Current Liabilities | H1: Total Non Current Liabilities Net Minority Interest | I1: Share Issued
A2: 4 | B2: 3/31/2023 | C2: 730870000 | D2: 169980000 | E2: 560890000 | F2: 225650000 | G2: 120280000 | H2: 105370000 | I2: 2349591.3
A3: 3 | B3: 3/31/2024 | C3: 784990000 | D3: 213240000 | E3: 571750000 | F3: 270760000 | G3: 128790000 | H3: 141970000 | I3: 2349591.3
A4: 2 | B4: 3/31/2025 | C4: 798800000 | D4: 220510000 | E4: 578290000 | F4: 302710000 | G4: 165370000 | H4: 137340000 | I4: 2349591.3
A5: 1 | B5: 3/31/2026 | C5: 797520000 | D5: 190210000 | E5: 607310000 | F5: 307450000 | G5: 155490000 | H5: 151960000 | I5: 2349591.3
G15: Total Equity Gross Minority Interest
G16: 490070000
G17: 496090000
G18: 514230000
G19: 505220000
G21: Stockholders' Equity
G22: 487380000
G23: 494020000
G24: 512180000
G25: 503040000
G26: Minority Interest
G27: 2690000
G28: 2070000
G29: 2050000
G30: 2180000
G31: Total Capitalization
G32: 487380000
G33: 494020000
G34: 512180000
G35: 503040000
G36: Common Stock Equity
G37: 487380000
G38: 494020000
G39: 512180000
G40: 503040000
G41: Capital Lease Obligations
G42: 14780000
G43: 16470000
G44: 14710000
G45: 11210000
G46: Net Tangible Assets
G47: -5080000
G48: 36930000
G49: 55050000
G50: 45750000
G51: Working Capital
G52: 34720000
G53: 55140000
G54: 84450000
G55: 49700000
G56: Invested Capital
G57: 487380000
G58: 494030000
G59: 512310000
G60: 504020000
G61: Tangible Book Value
G62: -5080000
G63: 36930000
G64: 55050000
G65: 45750000
G66: Total Debt
G67: 14780000
G68: 16480000
G69: 14840000
G70: 12190000
G71: Share Issued
G72: 2349591.3
G73: 2349591.3
G74: 2349591.3
G75: 2349591.3
G76: Ordinary Shares Number
G77: 2349591.3
G78: 2349591.3
G79: 2349591.3
G80: 2349591.3
